Workbook

Sheet README
A1: SCW BUDGETING & PROJECTIONS TOOL — 2026
A2: Built 2026-08-21 from: Xero General Ledger Detail (Jan 1 – Aug 21 2026, accrual), the legacy budgeting tool exports (contractsexpenses.csv + allocations.csv), and the legacy BUDGET workbook (staffing roster, sales roster, ramp schedules).
A4: HOW THE TABS FIT TOGETHER
A5: PROJECTIONS — the leadership view. Actual months show Xero as booked; projected months are driven by the three control tabs. Modest and stretch scenarios display side by side.
A6: SALES TEAM — one row per rep. Set MODEST % and STRETCH % attainment per person (e.g. Zach 80% / Stu 100%), ramp curve and start month. Rep commissions + Sales Manager + Director overrides = the comp liability that flows to PROJECTIONS.
A7: STAFFING — headcount × fully-loaded monthly cost for every role. Model hires/exits by editing monthly headcount or adding rows; raise levers: per-role $ or %, or department-wide % (table at the bottom), from a chosen month.
A8: EXPENSES — every recurring cost with ON/OFF, XERO/BUDGET source pick, $ override, % adjust, and FROM/TO months. Blank rows at the bottom to add new expenses.
A9: XERO ACTUALS — expenses as booked, by vendor by month, with trend status (STEADY / GROWING / DROPPING / DROPPED / NEW / ONE-TIME / PERIODIC) and a suggested forward $/mo. Bottom block = actual P&L summary that PROJECTIONS reads.
A10: RAMP SCHEDULES — editable revenue ramp curves referenced by SALES TEAM.
A12: COLOR LEGEND
A13: BLUE text = yours to edit. YELLOW fill = master levers. Black = formulas (leave). GREEN = pulls from another tab. Dark gray = static data imported from Xero/the budget tool (refresh by re-running the build script).
A15: RULES & ASSUMPTIONS BAKED IN
... A26: Re-export the Xero GL Detail + the two CSVs, re-run the aggregation + tools/budgeting/build_budget_workbook.py in the repo, and a fresh workbook is produced. Your edits live in this file, so copy your blue cells forward (or ask Claude to merge).

Sheet PROJECTIONS
A1: PROJECTIONS — 2026 P&L: Xero actuals through the cutoff month, model after
A2: For leadership review. Columns up to the cutoff show Xero as booked; later columns are driven by STAFFING (payroll), SALES TEAM (revenue + variable comp, modest vs stretch), and EXPENSES (planned opex). Both scenarios display simultaneously. Yellow cells are the master levers.
A3: Actuals through month # | B3: 7 | C3: COGS % fwd | D3: 0.432 | E3: Other income $/mo fwd | F3: 3000 | G3: Labor hedge % fwd | H3: 0 | I3: Opex hedge % fwd | J3: 0 | K3: (Aug is partial in Xero — leave cutoff at 7 unless data refreshed)
B4: 1 | C4: 2 | D4: 3 | E4: 4 | F4: 5 | G4: 6 | H4: 7 | I4: 8 | J4: 9 | K4: 10 | L4: 11 | M4: 12
A5: 2026 | B5: Jan | C5: Feb | D5: Mar | E5: Apr | F5: May | G5: Jun | H5: Jul | I5: Aug | J5: Sep | K5: Oct | L5: Nov | M5: Dec | N5: FY 2026
B6: =IF(B$4<=$B$3,"ACTUAL","PROJ") -> ACTUAL | C6: =IF(C$4<=$B$3,"ACTUAL","PROJ") -> ACTUAL | D6: =IF(D$4<=$B$3,"ACTUAL","PROJ") -> ACTUAL | E6: =IF(E$4<=$B$3,"ACTUAL","PROJ") -> ACTUAL | F6: =IF(F$4<=$B$3,"ACTUAL","PROJ") -> ACTUAL | G6: =IF(G$4<=$B$3,"ACTUAL","PROJ") -> ACTUAL | H6: =IF(H$4<=$B$3,"ACTUAL","PROJ") -> ACTUAL | I6: =IF(I$4<=$B$3,"ACTUAL","PROJ") -> PROJ | ... M6: =IF(M$4<=$B$3,"ACTUAL","PROJ") -> PROJ
A8: REVENUE
A9: Sales revenue — MODEST | B9: =IF(B$4<=$B$3,'XERO ACTUALS'!B$137,'SALES TEAM'!I$26) -> 1040301.8 | C9: =IF(C$4<=$B$3,'XERO ACTUALS'!C$137,'SALES TEAM'!J$26) -> 962653.48 | D9: =IF(D$4<=$B$3,'XERO ACTUALS'!D$137,'SALES TEAM'!K$26) -> 807402.94 | E9: =IF(E$4<=$B$3,'XERO ACTUALS'!E$137,'SALES TEAM'!L$26) -> 1266520.8 | F9: =IF(F$4<=$B$3,'XERO ACTUALS'!F$137,'SALES TEAM'!M$26) -> 1375720.8 | G9: =IF(G$4<=$B$3,'XERO ACTUALS'!G$137,'SALES TEAM'!N$26) -> 1116661.8 | H9: =IF(H$4<=$B$3,'XERO ACTUALS'!H$137,'SALES TEAM'!O$26) -> 1363598.3 | I9: =IF(I$4<=$B$3,'XERO ACTUALS'!I$137,'SALES TEAM'!P$26) -> 1173201.6 | ... M9: =IF(M$4<=$B$3,'XERO ACTUALS'!M$137,'SALES TEAM'!T$26) -> 1250536 | N9: =SUM(B9:M9) -> 13956206
A10: Sales revenue — STRETCH | B10: =IF(B$4<=$B$3,'XERO ACTUALS'!B$137,'SALES TEAM'!I$27) -> 1040301.8 | C10: =IF(C$4<=$B$3,'XERO ACTUALS'!C$137,'SALES TEAM'!J$27) -> 962653.48 | D10: =IF(D$4<=$B$3,'XERO ACTUALS'!D$137,'SALES TEAM'!K$27) -> 807402.94 | E10: =IF(E$4<=$B$3,'XERO ACTUALS'!E$137,'SALES TEAM'!L$27) -> 1266520.8 | F10: =IF(F$4<=$B$3,'XERO ACTUALS'!F$137,'SALES TEAM'!M$27) -> 1375720.8 | G10: =IF(G$4<=$B$3,'XERO ACTUALS'!G$137,'SALES TEAM'!N$27) -> 1116661.8 | H10: =IF(H$4<=$B$3,'XERO ACTUALS'!H$137,'SALES TEAM'!O$27) -> 1363598.3 | I10: =IF(I$4<=$B$3,'XERO ACTUALS'!I$137,'SALES TEAM'!P$27) -> 1384002 | ... M10: =IF(M$4<=$B$3,'XERO ACTUALS'!M$137,'SALES TEAM'!T$27) -> 1480670 | N10: =SUM(B10:M10) -> 15049542
A11: Other income (rental, interest, rebates) | B11: =IF(B$4<=$B$3,'XERO ACTUALS'!B$138,$F$3) -> 129229.59 | C11: =IF(C$4<=$B$3,'XERO ACTUALS'!C$138,$F$3) -> 613.42 | D11: =IF(D$4<=$B$3,'XERO ACTUALS'!D$138,$F$3) -> 15629.36 | E11: =IF(E$4<=$B$3,'XERO ACTUALS'!E$138,$F$3) -> 1233.33 | F11: =IF(F$4<=$B$3,'XERO ACTUALS'!F$138,$F$3) -> 3051.67 | G11: =IF(G$4<=$B$3,'XERO ACTUALS'!G$138,$F$3) -> 3744.51 | H11: =IF(H$4<=$B$3,'XERO ACTUALS'!H$138,$F$3) -> 11390.34 | I11: =IF(I$4<=$B$3,'XERO ACTUALS'!I$138,$F$3) -> 3000 | ... M11: =IF(M$4<=$B$3,'XERO ACTUALS'!M$138,$F$3) -> 3000 | N11: =SUM(B11:M11) -> 179892.22
A12: TOTAL REVENUE — MODEST | B12: =B9+B11 -> 1169531.4 | C12: =C9+C11 -> 963266.9 | D12: =D9+D11 -> 823032.3 | E12: =E9+E11 -> 1267754.1 | F12: =F9+F11 -> 1378772.4 | G12: =G9+G11 -> 1120406.3 | H12: =H9+H11 -> 1374988.6 | I12: =I9+I11 -> 1176201.6 | ... M12: =M9+M11 -> 1253536 | N12: =SUM(B12:M12) -> 14136098
A13: TOTAL REVENUE — STRETCH | B13: =B10+B11 -> 1169531.4 | C13: =C10+C11 -> 963266.9 | D13: =D10+D11 -> 823032.3 | E13: =E10+E11 -> 1267754.1 | F13: =F10+F11 -> 1378772.4 | G13: =G10+G11 -> 1120406.3 | H13: =H10+H11 -> 1374988.6 | I13: =I10+I11 -> 1387002 | ... M13: =M10+M11 -> 1483670 | N13: =SUM(B13:M13) -> 15229434
A15: COST OF GOODS & INSTALL DELIVERY
A16: COGS % of sales revenue | B16: =IF(B$4<=$B$3,'XERO ACTUALS'!B$140,$D$3) -> 0.50827916 | C16: =IF(C$4<=$B$3,'XERO ACTUALS'!C$140,$D$3) -> 0.47260159 | D16: =IF(D$4<=$B$3,'XERO ACTUALS'!D$140,$D$3) -> 0.46386814 | E16: =IF(E$4<=$B$3,'XERO ACTUALS'!E$140,$D$3) -> 0.4958447 | F16: =IF(F$4<=$B$3,'XERO ACTUALS'!F$140,$D$3) -> 0.50527715 | G16: =IF(G$4<=$B$3,'XERO ACTUALS'!G$140,$D$3) -> 0.46093625 | H16: =IF(H$4<=$B$3,'XERO ACTUALS'!H$140,$D$3) -> 0.1703022 | I16: =IF(I$4<=$B$3,'XERO ACTUALS'!I$140,$D$3) -> 0.432 | ... M16: =IF(M$4<=$B$3,'XERO ACTUALS'!M$140,$D$3) -> 0.432 | N16: =IFERROR(N17/N9,0) -> 0.43209314
A17: COGS — MODEST | B17: =IF(B$4<=$B$3,'XERO ACTUALS'!B$139,B9*B16) -> 528763.75 | C17: =IF(C$4<=$B$3,'XERO ACTUALS'!C$139,C9*C16) -> 454951.57 | D17: =IF(D$4<=$B$3,'XERO ACTUALS'!D$139,D9*D16) -> 374528.5 | E17: =IF(E$4<=$B$3,'XERO ACTUALS'!E$139,E9*E16) -> 627997.63 | F17: =IF(F$4<=$B$3,'XERO ACTUALS'!F$139,F9*F16) -> 695120.27 | G17: =IF(G$4<=$B$3,'XERO ACTUALS'!G$139,G9*G16) -> 514709.89 | H17: =IF(H$4<=$B$3,'XERO ACTUALS'!H$139,H9*H16) -> 232223.79 | I17: =IF(I$4<=$B$3,'XERO ACTUALS'!I$139,I9*I16) -> 506823.09 | ... M17: =IF(M$4<=$B$3,'XERO ACTUALS'!M$139,M9*M16) -> 540231.55 | N17: =SUM(B17:M17) -> 6030380.7
A18: COGS — STRETCH | B18: =IF(B$4<=$B$3,'XERO ACTUALS'!B$139,B10*B16) -> 528763.75 | C18: =IF(C$4<=$B$3,'XERO ACTUALS'!C$139,C10*C16) -> 454951.57 | D18: =IF(D$4<=$B$3,'XERO ACTUALS'!D$139,D10*D16) -> 374528.5 | E18: =IF(E$4<=$B$3,'XERO ACTUALS'!E$139,E10*E16) -> 627997.63 | F18: =IF(F$4<=$B$3,'XERO ACTUALS'!F$139,F10*F16) -> 695120.27 | G18: =IF(G$4<=$B$3,'XERO ACTUALS'!G$139,G10*G16) -> 514709.89 | H18: =IF(H$4<=$B$3,'XERO ACTUALS'!H$139,H10*H16) -> 232223.79 | I18: =IF(I$4<=$B$3,'XERO ACTUALS'!I$139,I10*I16) -> 597888.86 | ... M18: =IF(M$4<=$B$3,'XERO ACTUALS'!M$139,M10*M16) -> 639649.44 | N18: =SUM(B18:M18) -> 6502702
A19: GROSS PROFIT — MODEST | B19: =B12-B17 -> 640767.68 | C19: =C12-C17 -> 508315.33 | D19: =D12-D17 -> 448503.8 | E19: =E12-E17 -> 639756.52 | F19: =F12-F17 -> 683652.18 | G19: =G12-G17 -> 605696.39 | H19: =H12-H17 -> 1142764.8 | I19: =I12-I17 -> 669378.51 | ... M19: =M12-M17 -> 713304.45 | N19: =SUM(B19:M19) -> 8105717
A20: GROSS PROFIT — STRETCH | B20: =B13-B18 -> 640767.68 | C20: =C13-C18 -> 508315.33 | D20: =D13-D18 -> 448503.8 | E20: =E13-E18 -> 639756.52 | F20: =F13-F18 -> 683652.18 | G20: =G13-G18 -> 605696.39 | H20: =H13-H18 -> 1142764.8 | I20: =I13-I18 -> 789113.14 | ... M20: =M13-M18 -> 844020.56 | N20: =SUM(B20:M20) -> 8726732.1
A22: PAYROLL & SALES COMP
A23: Payroll — staffing model (base + benefits + licenses) | B23: =IF(B$4<=$B$3,'XERO ACTUALS'!B$141,STAFFING!Z$47*(1+$H$3)) -> 340010.78 | C23: =IF(C$4<=$B$3,'XERO ACTUALS'!C$141,STAFFING!AA$47*(1+$H$3)) -> 306521.04 | D23: =IF(D$4<=$B$3,'XERO ACTUALS'!D$141,STAFFING!AB$47*(1+$H$3)) -> 338404.82 | E23: =IF(E$4<=$B$3,'XERO ACTUALS'!E$141,STAFFING!AC$47*(1+$H$3)) -> 356191.85 | F23: =IF(F$4<=$B$3,'XERO ACTUALS'!F$141,STAFFING!AD$47*(1+$H$3)) -> 302930.9 | G23: =IF(G$4<=$B$3,'XERO ACTUALS'!G$141,STAFFING!AE$47*(1+$H$3)) -> 232740.43 | H23: =IF(H$4<=$B$3,'XERO ACTUALS'!H$141,STAFFING!AF$47*(1+$H$3)) -> 285805.48 | I23: =IF(I$4<=$B$3,'XERO ACTUALS'!I$141,STAFFING!AG$47*(1+$H$3)) -> 326366.98 | ... M23: =IF(M$4<=$B$3,'XERO ACTUALS'!M$141,STAFFING!AK$47*(1+$H$3)) -> 326366.98 | N23: =SUM(B23:M23) -> 3794440.2
A24: Variable sales comp — MODEST (in booked payroll for actual months) | B24: =IF(B$4<=$B$3,0,'SALES TEAM'!I$34) -> 0 | C24: =IF(C$4<=$B$3,0,'SALES TEAM'!J$34) -> 0 | D24: =IF(D$4<=$B$3,0,'SALES TEAM'!K$34) -> 0 | E24: =IF(E$4<=$B$3,0,'SALES TEAM'!L$34) -> 0 | F24: =IF(F$4<=$B$3,0,'SALES TEAM'!M$34) -> 0 | G24: =IF(G$4<=$B$3,0,'SALES TEAM'!N$34) -> 0 | H24: =IF(H$4<=$B$3,0,'SALES TEAM'!O$34) -> 0 | I24: =IF(I$4<=$B$3,0,'SALES TEAM'!P$34) -> 46289.287 | ... M24: =IF(M$4<=$B$3,0,'SALES TEAM'!T$34) -> 52089.367 | N24: =SUM(B24:M24) -> 243246.75
A25: Variable sales comp — STRETCH (in booked payroll for actual months) | B25: =IF(B$4<=$B$3,0,'SALES TEAM'!I$35) -> 0 | C25: =IF(C$4<=$B$3,0,'SALES TEAM'!J$35) -> 0 | D25: =IF(D$4<=$B$3,0,'SALES TEAM'!K$35) -> 0 | E25: =IF(E$4<=$B$3,0,'SALES TEAM'!L$35) -> 0 | F25: =IF(F$4<=$B$3,0,'SALES TEAM'!M$35) -> 0 | G25: =IF(G$4<=$B$3,0,'SALES TEAM'!N$35) -> 0 | H25: =IF(H$4<=$B$3,0,'SALES TEAM'!O$35) -> 0 | I25: =IF(I$4<=$B$3,0,'SALES TEAM'!P$35) -> 61079.317 | ... M25: =IF(M$4<=$B$3,0,'SALES TEAM'!T$35) -> 68329.417 | N25: =SUM(B25:M25) -> 320146.98
A27: OPERATING EXPENSES (dept view — budgeting-tool allocations win)
A28: Sales | B28: =IF(B$4<=$B$3,'XERO ACTUALS'!B$142,EXPENSES!B$204*(1+$J$3)) -> 23880.9 | C28: =IF(C$4<=$B$3,'XERO ACTUALS'!C$142,EXPENSES!C$204*(1+$J$3)) -> 26194.9 | D28: =IF(D$4<=$B$3,'XERO ACTUALS'!D$142,EXPENSES!D$204*(1+$J$3)) -> 23702.9 | E28: =IF(E$4<=$B$3,'XERO ACTUALS'!E$142,EXPENSES!E$204*(1+$J$3)) -> 33135.62 | F28: =IF(F$4<=$B$3,'XERO ACTUALS'!F$142,EXPENSES!F$204*(1+$J$3)) -> 21940.07 | G28: =IF(G$4<=$B$3,'XERO ACTUALS'!G$142,EXPENSES!G$204*(1+$J$3)) -> 23914.68 | H28: =IF(H$4<=$B$3,'XERO ACTUALS'!H$142,EXPENSES!H$204*(1+$J$3)) -> 34292.15 | I28: =IF(I$4<=$B$3,'XERO ACTUALS'!I$142,EXPENSES!I$204*(1+$J$3)) -> 24880.618 | ... M28: =IF(M$4<=$B$3,'XERO ACTUALS'!M$142,EXPENSES!M$204*(1+$J$3)) -> 24880.618 | N28: =SUM(B28:M28) -> 311464.31
A29: Marketing | B29: =IF(B$4<=$B$3,'XERO ACTUALS'!B$143,EXPENSES!B$205*(1+$J$3)) -> 101112.98 | C29: =IF(C$4<=$B$3,'XERO ACTUALS'!C$143,EXPENSES!C$205*(1+$J$3)) -> 104346.54 | D29: =IF(D$4<=$B$3,'XERO ACTUALS'!D$143,EXPENSES!D$205*(1+$J$3)) -> 113683.94 | E29: =IF(E$4<=$B$3,'XERO ACTUALS'!E$143,EXPENSES!E$205*(1+$J$3)) -> 105145.29 | F29: =IF(F$4<=$B$3,'XERO ACTUALS'!F$143,EXPENSES!F$205*(1+$J$3)) -> 102201.14 | G29: =IF(G$4<=$B$3,'XERO ACTUALS'!G$143,EXPENSES!G$205*(1+$J$3)) -> 111565 | H29: =IF(H$4<=$B$3,'XERO ACTUALS'!H$143,EXPENSES!H$205*(1+$J$3)) -> 97344.03 | I29: =IF(I$4<=$B$3,'XERO ACTUALS'!I$143,EXPENSES!I$205*(1+$J$3)) -> 101984.67 | ... M29: =IF(M$4<=$B$3,'XERO ACTUALS'!M$143,EXPENSES!M$205*(1+$J$3)) -> 101984.67 | N29: =SUM(B29:M29) -> 1245322.3
A30: Software Development | B30: =IF(B$4<=$B$3,'XERO ACTUALS'!B$144,EXPENSES!B$206*(1+$J$3)) -> 15329.12 | C30: =IF(C$4<=$B$3,'XERO ACTUALS'!C$144,EXPENSES!C$206*(1+$J$3)) -> 18543.25 | D30: =IF(D$4<=$B$3,'XERO ACTUALS'!D$144,EXPENSES!D$206*(1+$J$3)) -> 14275.73 | E30: =IF(E$4<=$B$3,'XERO ACTUALS'!E$144,EXPENSES!E$206*(1+$J$3)) -> 15372.76 | F30: =IF(F$4<=$B$3,'XERO ACTUALS'!F$144,EXPENSES!F$206*(1+$J$3)) -> 15712.7 | G30: =IF(G$4<=$B$3,'XERO ACTUALS'!G$144,EXPENSES!G$206*(1+$J$3)) -> 15725.04 | H30: =IF(H$4<=$B$3,'XERO ACTUALS'!H$144,EXPENSES!H$206*(1+$J$3)) -> 15218.69 | I30: =IF(I$4<=$B$3,'XERO ACTUALS'!I$144,EXPENSES!I$206*(1+$J$3)) -> 16555.143 | ... M30: =IF(M$4<=$B$3,'XERO ACTUALS'!M$144,EXPENSES!M$206*(1+$J$3)) -> 16555.143 | N30: =SUM(B30:M30) -> 192953.01
A31: Installation Services | B31: =IF(B$4<=$B$3,'XERO ACTUALS'!B$145,EXPENSES!B$207*(1+$J$3)) -> 1317.66 | C31: =IF(C$4<=$B$3,'XERO ACTUALS'!C$145,EXPENSES!C$207*(1+$J$3)) -> 752.62 | D31: =IF(D$4<=$B$3,'XERO ACTUALS'!D$145,EXPENSES!D$207*(1+$J$3)) -> 922.49 | E31: =IF(E$4<=$B$3,'XERO ACTUALS'!E$145,EXPENSES!E$207*(1+$J$3)) -> 921.14 | F31: =IF(F$4<=$B$3,'XERO ACTUALS'!F$145,EXPENSES!F$207*(1+$J$3)) -> 830.47 | G31: =IF(G$4<=$B$3,'XERO ACTUALS'!G$145,EXPENSES!G$207*(1+$J$3)) -> 892.67 | H31: =IF(H$4<=$B$3,'XERO ACTUALS'!H$145,EXPENSES!H$207*(1+$J$3)) -> 796.3 | I31: =IF(I$4<=$B$3,'XERO ACTUALS'!I$145,EXPENSES!I$207*(1+$J$3)) -> 2086.6659 | ... M31: =IF(M$4<=$B$3,'XERO ACTUALS'!M$145,EXPENSES!M$207*(1+$J$3)) -> 2086.6659 | N31: =SUM(B31:M31) -> 16866.68
A32: Technical Support | B32: =IF(B$4<=$B$3,'XERO ACTUALS'!B$146,EXPENSES!B$208*(1+$J$3)) -> 319 | C32: =IF(C$4<=$B$3,'XERO ACTUALS'!C$146,EXPENSES!C$208*(1+$J$3)) -> 319 | D32: =IF(D$4<=$B$3,'XERO ACTUALS'!D$146,EXPENSES!D$208*(1+$J$3)) -> 319 | E32: =IF(E$4<=$B$3,'XERO ACTUALS'!E$146,EXPENSES!E$208*(1+$J$3)) -> 341.33 | F32: =IF(F$4<=$B$3,'XERO ACTUALS'!F$146,EXPENSES!F$208*(1+$J$3)) -> 341.33 | G32: =IF(G$4<=$B$3,'XERO ACTUALS'!G$146,EXPENSES!G$208*(1+$J$3)) -> 341.33 | H32: =IF(H$4<=$B$3,'XERO ACTUALS'!H$146,EXPENSES!H$208*(1+$J$3)) -> 341.33 | I32: =IF(I$4<=$B$3,'XERO ACTUALS'!I$146,EXPENSES!I$208*(1+$J$3)) -> 372.31212 | ... M32: =IF(M$4<=$B$3,'XERO ACTUALS'!M$146,EXPENSES!M$208*(1+$J$3)) -> 372.31212 | N32: =SUM(B32:M32) -> 4183.8806
A33: Purchasing & Fulfillment | B33: =IF(B$4<=$B$3,'XERO ACTUALS'!B$147,EXPENSES!B$209*(1+$J$3)) -> 1043 | C33: =IF(C$4<=$B$3,'XERO ACTUALS'!C$147,EXPENSES!C$209*(1+$J$3)) -> 1043 | D33: =IF(D$4<=$B$3,'XERO ACTUALS'!D$147,EXPENSES!D$209*(1+$J$3)) -> 1043 | E33: =IF(E$4<=$B$3,'XERO ACTUALS'!E$147,EXPENSES!E$209*(1+$J$3)) -> 1043 | F33: =IF(F$4<=$B$3,'XERO ACTUALS'!F$147,EXPENSES!F$209*(1+$J$3)) -> 1043 | G33: =IF(G$4<=$B$3,'XERO ACTUALS'!G$147,EXPENSES!G$209*(1+$J$3)) -> 1043 | H33: =IF(H$4<=$B$3,'XERO ACTUALS'!H$147,EXPENSES!H$209*(1+$J$3)) -> 1043 | I33: =IF(I$4<=$B$3,'XERO ACTUALS'!I$147,EXPENSES!I$209*(1+$J$3)) -> 1043 | ... M33: =IF(M$4<=$B$3,'XERO ACTUALS'!M$147,EXPENSES!M$209*(1+$J$3)) -> 1043 | N33: =SUM(B33:M33) -> 12516
A34: 03 - HR & Business Administration Manager | B34: =IF(B$4<=$B$3,'XERO ACTUALS'!B$148,EXPENSES!B$210*(1+$J$3)) -> 14365.42 | C34: =IF(C$4<=$B$3,'XERO ACTUALS'!C$148,EXPENSES!C$210*(1+$J$3)) -> 10285.7 | D34: =IF(D$4<=$B$3,'XERO ACTUALS'!D$148,EXPENSES!D$210*(1+$J$3)) -> 14282.72 | E34: =IF(E$4<=$B$3,'XERO ACTUALS'!E$148,EXPENSES!E$210*(1+$J$3)) -> 16199.33 | F34: =IF(F$4<=$B$3,'XERO ACTUALS'!F$148,EXPENSES!F$210*(1+$J$3)) -> 5398.56 | G34: =IF(G$4<=$B$3,'XERO ACTUALS'!G$148,EXPENSES!G$210*(1+$J$3)) -> 8066.8 | H34: =IF(H$4<=$B$3,'XERO ACTUALS'!H$148,EXPENSES!H$210*(1+$J$3)) -> 6304.26 | I34: =IF(I$4<=$B$3,'XERO ACTUALS'!I$148,EXPENSES!I$210*(1+$J$3)) -> 5812.718 | ... M34: =IF(M$4<=$B$3,'XERO ACTUALS'!M$148,EXPENSES!M$210*(1+$J$3)) -> 5812.718 | N34: =SUM(B34:M34) -> 103966.38
A35: Facillities | B35: =IF(B$4<=$B$3,'XERO ACTUALS'!B$149,EXPENSES!B$211*(1+$J$3)) -> 15328.39 | C35: =IF(C$4<=$B$3,'XERO ACTUALS'!C$149,EXPENSES!C$211*(1+$J$3)) -> 14036.16 | D35: =IF(D$4<=$B$3,'XERO ACTUALS'!D$149,EXPENSES!D$211*(1+$J$3)) -> 15051.56 | E35: =IF(E$4<=$B$3,'XERO ACTUALS'!E$149,EXPENSES!E$211*(1+$J$3)) -> 16688.63 | F35: =IF(F$4<=$B$3,'XERO ACTUALS'!F$149,EXPENSES!F$211*(1+$J$3)) -> 27807.18 | G35: =IF(G$4<=$B$3,'XERO ACTUALS'!G$149,EXPENSES!G$211*(1+$J$3)) -> 14012.26 | H35: =IF(H$4<=$B$3,'XERO ACTUALS'!H$149,EXPENSES!H$211*(1+$J$3)) -> 14283.72 | I35: =IF(I$4<=$B$3,'XERO ACTUALS'!I$149,EXPENSES!I$211*(1+$J$3)) -> 16759.561 | ... M35: =IF(M$4<=$B$3,'XERO ACTUALS'!M$149,EXPENSES!M$211*(1+$J$3)) -> 16759.561 | N35: =SUM(B35:M35) -> 201005.71
A36: Exec | B36: =IF(B$4<=$B$3,'XERO ACTUALS'!B$150,EXPENSES!B$212*(1+$J$3)) -> 0 | C36: =IF(C$4<=$B$3,'XERO ACTUALS'!C$150,EXPENSES!C$212*(1+$J$3)) -> 0 | D36: =IF(D$4<=$B$3,'XERO ACTUALS'!D$150,EXPENSES!D$212*(1+$J$3)) -> 0 | E36: =IF(E$4<=$B$3,'XERO ACTUALS'!E$150,EXPENSES!E$212*(1+$J$3)) -> 0 | F36: =IF(F$4<=$B$3,'XERO ACTUALS'!F$150,EXPENSES!F$212*(1+$J$3)) -> 0 | G36: =IF(G$4<=$B$3,'XERO ACTUALS'!G$150,EXPENSES!G$212*(1+$J$3)) -> 1407.43 | H36: =IF(H$4<=$B$3,'XERO ACTUALS'!H$150,EXPENSES!H$212*(1+$J$3)) -> 56.37 | I36: =IF(I$4<=$B$3,'XERO ACTUALS'!I$150,EXPENSES!I$212*(1+$J$3)) -> 884.34691 | ... M36: =IF(M$4<=$B$3,'XERO ACTUALS'!M$150,EXPENSES!M$212*(1+$J$3)) -> 884.34691 | N36: =SUM(B36:M36) -> 5885.5346
A37: Product | B37: =IF(B$4<=$B$3,'XERO ACTUALS'!B$151,EXPENSES!B$213*(1+$J$3)) -> 0 | C37: =IF(C$4<=$B$3,'XERO ACTUALS'!C$151,EXPENSES!C$213*(1+$J$3)) -> 0 | D37: =IF(D$4<=$B$3,'XERO ACTUALS'!D$151,EXPENSES!D$213*(1+$J$3)) -> 0 | E37: =IF(E$4<=$B$3,'XERO ACTUALS'!E$151,EXPENSES!E$213*(1+$J$3)) -> 0 | F37: =IF(F$4<=$B$3,'XERO ACTUALS'!F$151,EXPENSES!F$213*(1+$J$3)) -> 0 | G37: =IF(G$4<=$B$3,'XERO ACTUALS'!G$151,EXPENSES!G$213*(1+$J$3)) -> 0 | H37: =IF(H$4<=$B$3,'XERO ACTUALS'!H$151,EXPENSES!H$213*(1+$J$3)) -> 0 | I37: =IF(I$4<=$B$3,'XERO ACTUALS'!I$151,EXPENSES!I$213*(1+$J$3)) -> 0 | ... M37: =IF(M$4<=$B$3,'XERO ACTUALS'!M$151,EXPENSES!M$213*(1+$J$3)) -> 0 | N37: =SUM(B37:M37) -> 0
A38: General Overhead | B38: =IF(B$4<=$B$3,'XERO ACTUALS'!B$152,EXPENSES!B$214*(1+$J$3)) -> 3409 | C38: =IF(C$4<=$B$3,'XERO ACTUALS'!C$152,EXPENSES!C$214*(1+$J$3)) -> 3978.92 | D38: =IF(D$4<=$B$3,'XERO ACTUALS'!D$152,EXPENSES!D$214*(1+$J$3)) -> 3910 | E38: =IF(E$4<=$B$3,'XERO ACTUALS'!E$152,EXPENSES!E$214*(1+$J$3)) -> 4244 | F38: =IF(F$4<=$B$3,'XERO ACTUALS'!F$152,EXPENSES!F$214*(1+$J$3)) -> 4173.75 | G38: =IF(G$4<=$B$3,'XERO ACTUALS'!G$152,EXPENSES!G$214*(1+$J$3)) -> 4028.6 | H38: =IF(H$4<=$B$3,'XERO ACTUALS'!H$152,EXPENSES!H$214*(1+$J$3)) -> 4126 | I38: =IF(I$4<=$B$3,'XERO ACTUALS'!I$152,EXPENSES!I$214*(1+$J$3)) -> 2754.992 | ... M38: =IF(M$4<=$B$3,'XERO ACTUALS'!M$152,EXPENSES!M$214*(1+$J$3)) -> 2754.992 | N38: =SUM(B38:M38) -> 41645.23
A39: Unassigned | B39: =IF(B$4<=$B$3,'XERO ACTUALS'!B$153,EXPENSES!B$215*(1+$J$3)) -> 20046.46 | C39: =IF(C$4<=$B$3,'XERO ACTUALS'!C$153,EXPENSES!C$215*(1+$J$3)) -> 21603.25 | D39: =IF(D$4<=$B$3,'XERO ACTUALS'!D$153,EXPENSES!D$215*(1+$J$3)) -> 49688.47 | E39: =IF(E$4<=$B$3,'XERO ACTUALS'!E$153,EXPENSES!E$215*(1+$J$3)) -> 24996.78 | F39: =IF(F$4<=$B$3,'XERO ACTUALS'!F$153,EXPENSES!F$215*(1+$J$3)) -> 19300.85 | G39: =IF(G$4<=$B$3,'XERO ACTUALS'!G$153,EXPENSES!G$215*(1+$J$3)) -> 26848.19 | H39: =IF(H$4<=$B$3,'XERO ACTUALS'!H$153,EXPENSES!H$215*(1+$J$3)) -> 26078.03 | I39: =IF(I$4<=$B$3,'XERO ACTUALS'!I$153,EXPENSES!I$215*(1+$J$3)) -> 23294.033 | ... M39: =IF(M$4<=$B$3,'XERO ACTUALS'!M$153,EXPENSES!M$215*(1+$J$3)) -> 23294.033 | N39: =SUM(B39:M39) -> 305032.2
A40: TOTAL OPERATING EXPENSES | B40: =SUM(B28:B39) -> 196151.93 | C40: =SUM(C28:C39) -> 201103.34 | D40: =SUM(D28:D39) -> 236879.81 | E40: =SUM(E28:E39) -> 218087.88 | F40: =SUM(F28:F39) -> 198749.05 | G40: =SUM(G28:G39) -> 207845 | H40: =SUM(H28:H39) -> 199883.88 | I40: =SUM(I28:I39) -> 196428.06 | ... M40: =SUM(M28:M39) -> 196428.06 | N40: =SUM(B40:M40) -> 2440841.2
A42: BOTTOM LINE
A43: NET PROFIT — MODEST | B43: =B19-B23-B24-B40 -> 104604.97 | C43: =C19-C23-C24-C40 -> 690.95 | D43: =D19-D23-D24-D40 -> -126780.83 | E43: =E19-E23-E24-E40 -> 65476.79 | F43: =F19-F23-F24-F40 -> 181972.23 | G43: =G19-G23-G24-G40 -> 165110.96 | H43: =H19-H23-H24-H40 -> 657075.48 | I43: =I19-I23-I24-I40 -> 100294.18 | ... M43: =M19-M23-M24-M40 -> 138420.04 | N43: =SUM(B43:M43) -> 1627188.9
A44: NET PROFIT — STRETCH | B44: =B20-B23-B25-B40 -> 104604.97 | C44: =C20-C23-C25-C40 -> 690.95 | D44: =D20-D23-D25-D40 -> -126780.83 | E44: =E20-E23-E25-E40 -> 65476.79 | F44: =F20-F23-F25-F40 -> 181972.23 | G44: =G20-G23-G25-G40 -> 165110.96 | H44: =H20-H23-H25-H40 -> 657075.48 | I44: =I20-I23-I25-I40 -> 205238.77 | ... M44: =M20-M23-M25-M40 -> 252896.1 | N44: =SUM(B44:M44) -> 2171303.7
A45: Net margin — modest | B45: =IFERROR(B43/B12,0) -> 0.089441778 | C45: =IFERROR(C43/C12,0) -> 0.0007172986 | D45: =IFERROR(D43/D12,0) -> -0.15404114 | E45: =IFERROR(E43/E12,0) -> 0.051647861 | F45: =IFERROR(F43/F12,0) -> 0.13198134 | G45: =IFERROR(G43/G12,0) -> 0.14736704 | H45: =IFERROR(H43/H12,0) -> 0.47787703 | I45: =IFERROR(I43/I12,0) -> 0.085269546 | ... N45: =IFERROR(N43/N12,0) -> 0.11510877
A46: Net margin — stretch | B46: =IFERROR(B44/B13,0) -> 0.089441778 | C46: =IFERROR(C44/C13,0) -> 0.0007172986 | D46: =IFERROR(D44/D13,0) -> -0.15404114 | E46: =IFERROR(E44/E13,0) -> 0.051647861 | F46: =IFERROR(F44/F13,0) -> 0.13198134 | G46: =IFERROR(G44/G13,0) -> 0.14736704 | H46: =IFERROR(H44/H13,0) -> 0.47787703 | I46: =IFERROR(I44/I13,0) -> 0.14797295 | ... N46: =IFERROR(N44/N13,0) -> 0.14257284
A47: Break-even sales revenue (payroll + opex, excl. variable comp) | B47: =IFERROR((B23+B40-B11)/(1-B16),0) -> 827569.41 | C47: =IFERROR((C23+C40-C11)/(1-C16),0) -> 961343.37 | D47: =IFERROR((D23+D40-D11)/(1-D16),0) -> 1043876.2 | E47: =IFERROR((E23+E40-E11)/(1-E16),0) -> 1136646.6 | F47: =IFERROR((F23+F40-F11)/(1-F16),0) -> 1007894.2 | G47: =IFERROR((G23+G40-G11)/(1-G16),0) -> 810369.68 | H47: =IFERROR((H23+H40-H11)/(1-H16),0) -> 571652.74 | I47: =IFERROR((I23+I40-I11)/(1-I16),0) -> 915132.12 | ... M47: =IFERROR((M23+M40-M11)/(1-M16),0) -> 915132.12
A48: Cumulative net — modest | B48: =SUM($B$43:B43) -> 104604.97 | C48: =SUM($B$43:C43) -> 105295.92 | D48: =SUM($B$43:D43) -> -21484.91 | E48: =SUM($B$43:E43) -> 43991.88 | F48: =SUM($B$43:F43) -> 225964.11 | G48: =SUM($B$43:G43) -> 391075.07 | H48: =SUM($B$43:H43) -> 1048150.6 | I48: =SUM($B$43:I43) -> 1148444.7 | ... M48: =SUM($B$43:M43) -> 1627188.9
A49: Cumulative net — stretch | B49: =SUM($B$44:B44) -> 104604.97 | C49: =SUM($B$44:C44) -> 105295.92 | D49: =SUM($B$44:D44) -> -21484.91 | E49: =SUM($B$44:E44) -> 43991.88 | F49: =SUM($B$44:F44) -> 225964.11 | G49: =SUM($B$44:G44) -> 391075.07 | H49: =SUM($B$44:H44) -> 1048150.6 | I49: =SUM($B$44:I44) -> 1253389.3 | ... M49: =SUM($B$44:M44) -> 2171303.7

Sheet SALES TEAM
A1: SALES TEAM — individual reps, ramps, MODEST vs STRETCH attainment, and comp liability
A2: Blue = editable. Each rep: pick a ramp curve, a start month (may be ≤ 0 if they started before 2026), then set attainment per scenario — e.g. Zach 80% modest / 100% stretch. Monthly revenue = ramp value for their tenure month × attainment. COMM % is paid on attained revenue (defaults from the legacy tool: AE 2.5%, AM 1.5%, Sr AE 1.75% — edit freely). Sales Manager + Director overrides are computed below the table. Base salaries live on STAFFING.
A3: Annual revenue target ($) | B3: 12050000 | D3: SM override % (of all sales) | E3: 0.015 | G3: Director override % (above target) | H3: 0.035 | J3: Monthly target | K3: =$B$3/12 -> 1004166.7
I4: 1 | J4: 2 | K4: 3 | L4: 4 | M4: 5 | N4: 6 | O4: 7 | P4: 8 | Q4: 9 | R4: 10 | S4: 11 | T4: 12 | U4: 1 | V4: 2 | W4: 3 | X4: 4 | Y4: 5 | Z4: 6 | AA4: 7 | AB4: 8 | AC4: 9 | AD4: 10 | AE4: 11 | AF4: 12
A5: REP / SOURCE | B5: ROLE | C5: RAMP CURVE | D5: START MO (≤0 = pre-2026) | E5: MODEST % | F5: STRETCH % | G5: COMM % | H5: FY RUN-RATE QUOTA | I5: MOD Jan | J5: MOD Feb | K5: MOD Mar | L5: MOD Apr | M5: MOD May | N5: MOD Jun | O5: MOD Jul | P5: MOD Aug | Q5: MOD Sep | R5: MOD Oct | S5: MOD Nov | T5: MOD Dec | U5: STR Jan | V5: STR Feb | W5: STR Mar | X5: STR Apr | Y5: STR May | Z5: STR Jun | AA5: STR Jul | AB5: STR Aug | AC5: STR Sep | AD5: STR Oct | AE5: STR Nov | AF5: STR Dec | AG5: FY MODEST | AH5: FY STRETCH | AI5: FY COMM MOD | AJ5: FY COMM STR
A6: Senior Account Executive - Stu Moore | B6: Senior Account Executive - Stu Moore | C6: STU | D6: -8 | E6: 1 | F6: 1 | G6: 0.0175 | H6: =IF($C6="",0,12*INDEX('RAMP SCHEDULES'!$B$4:$M$13,MATCH($C6,'RAMP SCHEDULES'!$A$4:$A$13,0),12)) -> 3960000 | I6: =IF(OR($C6="",I$4<$D6),0,INDEX('RAMP SCHEDULES'!$B$4:$M$13,MATCH($C6,'RAMP SCHEDULES'!$A$4:$A$13,0),MIN(12,I$4-$D6+1))*$E6) -> 330000 | J6: =IF(OR($C6="",J$4<$D6),0,INDEX('RAMP SCHEDULES'!$B$4:$M$13,MATCH($C6,'RAMP SCHEDULES'!$A$4:$A$13,0),MIN(12,J$4-$D6+1))*$E6) -> 330000 | K6: =IF(OR($C6="",K$4<$D6),0,INDEX('RAMP SCHEDULES'!$B$4:$M$13,MATCH($C6,'RAMP SCHEDULES'!$A$4:$A$13,0),MIN(12,K$4-$D6+1))*$E6) -> 330000 | L6: =IF(OR($C6="",L$4<$D6),0,INDEX('RAMP SCHEDULES'!$B$4:$M$13,MATCH($C6,'RAMP SCHEDULES'!$A$4:$A$13,0),MIN(12,L$4-$D6+1))*$E6) -> 330000 | M6: =IF(OR($C6="",M$4<$D6),0,INDEX('RAMP SCHEDULES'!$B$4:$M$13,MATCH($C6,'RAMP SCHEDULES'!$A$4:$A$13,0),MIN(12,M$4-$D6+1))*$E6) -> 330000 | N6: =IF(OR($C6="",N$4<$D6),0,INDEX('RAMP SCHEDULES'!$B$4:$M$13,MATCH($C6,'RAMP SCHEDULES'!$A$4:$A$13,0),MIN(12,N$4-$D6+1))*$E6) -> 330000 | O6: =IF(OR($C6="",O$4<$D6),0,INDEX('RAMP SCHEDULES'!$B$4:$M$13,MATCH($C6,'RAMP SCHEDULES'!$A$4:$A$13,0),MIN(12,O$4-$D6+1))*$E6) -> 330000 | P6: =IF(OR($C6="",P$4<$D6),0,INDEX('RAMP SCHEDULES'!$B$4:$M$13,MATCH($C6,'RAMP SCHEDULES'!$A$4:$A$13,0),MIN(12,P$4-$D6+1))*$E6) -> 330000 | ... T6: =IF(OR($C6="",T$4<$D6),0,INDEX('RAMP SCHEDULES'!$B$4:$M$13,MATCH($C6,'RAMP SCHEDULES'!$A$4:$A$13,0),MIN(12,T$4-$D6+1))*$E6) -> 330000 | U6: =IF(OR($C6="",U$4<$D6),0,INDEX('RAMP SCHEDULES'!$B$4:$M$13,MATCH($C6,'RAMP SCHEDULES'!$A$4:$A$13,0),MIN(12,U$4-$D6+1))*$F6) -> 330000 | V6: =IF(OR($C6="",V$4<$D6),0,INDEX('RAMP SCHEDULES'!$B$4:$M$13,MATCH($C6,'RAMP SCHEDULES'!$A$4:$A$13,0),MIN(12,V$4-$D6+1))*$F6) -> 330000 | W6: =IF(OR($C6="",W$4<$D6),0,INDEX('RAMP SCHEDULES'!$B$4:$M$13,MATCH($C6,'RAMP SCHEDULES'!$A$4:$A$13,0),MIN(12,W$4-$D6+1))*$F6) -> 330000 | X6: =IF(OR($C6="",X$4<$D6),0,INDEX('RAMP SCHEDULES'!$B$4:$M$13,MATCH($C6,'RAMP SCHEDULES'!$A$4:$A$13,0),MIN(12,X$4-$D6+1))*$F6) -> 330000 | Y6: =IF(OR($C6="",Y$4<$D6),0,INDEX('RAMP SCHEDULES'!$B$4:$M$13,MATCH($C6,'RAMP SCHEDULES'!$A$4:$A$13,0),MIN(12,Y$4-$D6+1))*$F6) -> 330000 | Z6: =IF(OR($C6="",Z$4<$D6),0,INDEX('RAMP SCHEDULES'!$B$4:$M$13,MATCH($C6,'RAMP SCHEDULES'!$A$4:$A$13,0),MIN(12,Z$4-$D6+1))*$F6) -> 330000 | AA6: =IF(OR($C6="",AA$4<$D6),0,INDEX('RAMP SCHEDULES'!$B$4:$M$13,MATCH($C6,'RAMP SCHEDULES'!$A$4:$A$13,0),MIN(12,AA$4-$D6+1))*$F6) -> 330000 | AB6: =IF(OR($C6="",AB$4<$D6),0,INDEX('RAMP SCHEDULES'!$B$4:$M$13,MATCH($C6,'RAMP SCHEDULES'!$A$4:$A$13,0),MIN(12,AB$4-$D6+1))*$F6) -> 330000 | ... AF6: =IF(OR($C6="",AF$4<$D6),0,INDEX('RAMP SCHEDULES'!$B$4:$M$13,MATCH($C6,'RAMP SCHEDULES'!$A$4:$A$13,0),MIN(12,AF$4-$D6+1))*$F6) -> 330000 | AG6: =SUM(I6:T6) -> 3960000 | AH6: =SUM(U6:AF6) -> 3960000 | AI6: =AG6*$G6 -> 69300 | AJ6: =AH6*$G6 -> 69300
A7: Danny Mize | B7: Account Executive - RAMP | C7: AM -> AE | D7: -8 | E7: 0.8 | F7: 1 | G7: 0.025 | H7: =IF($C7="",0,12*INDEX('RAMP SCHEDULES'!$B$4:$M$13,MATCH($C7,'RAMP SCHEDULES'!$A$4:$A$13,0),12)) -> 1000008 | I7: =IF(OR($C7="",I$4<$D7),0,INDEX('RAMP SCHEDULES'!$B$4:$M$13,MATCH($C7,'RAMP SCHEDULES'!$A$4:$A$13,0),MIN(12,I$4-$D7+1))*$E7) -> 66666.4 | J7: =IF(OR($C7="",J$4<$D7),0,INDEX('RAMP SCHEDULES'!$B$4:$M$13,MATCH($C7,'RAMP SCHEDULES'!$A$4:$A$13,0),MIN(12,J$4-$D7+1))*$E7) -> 66666.4 | K7: =IF(OR($C7="",K$4<$D7),0,INDEX('RAMP SCHEDULES'!$B$4:$M$13,MATCH($C7,'RAMP SCHEDULES'!$A$4:$A$13,0),MIN(12,K$4-$D7+1))*$E7) -> 66667.2 | L7: =IF(OR($C7="",L$4<$D7),0,INDEX('RAMP SCHEDULES'!$B$4:$M$13,MATCH($C7,'RAMP SCHEDULES'!$A$4:$A$13,0),MIN(12,L$4-$D7+1))*$E7) -> 66667.2 | M7: =IF(OR($C7="",M$4<$D7),0,INDEX('RAMP SCHEDULES'!$B$4:$M$13,MATCH($C7,'RAMP SCHEDULES'!$A$4:$A$13,0),MIN(12,M$4-$D7+1))*$E7) -> 66667.2 | N7: =IF(OR($C7="",N$4<$D7),0,INDEX('RAMP SCHEDULES'!$B$4:$M$13,MATCH($C7,'RAMP SCHEDULES'!$A$4:$A$13,0),MIN(12,N$4-$D7+1))*$E7) -> 66667.2 | O7: =IF(OR($C7="",O$4<$D7),0,INDEX('RAMP SCHEDULES'!$B$4:$M$13,MATCH($C7,'RAMP SCHEDULES'!$A$4:$A$13,0),MIN(12,O$4-$D7+1))*$E7) -> 66667.2 | P7: =IF(OR($C7="",P$4<$D7),0,INDEX('RAMP SCHEDULES'!$B$4:$M$13,MATCH($C7,'RAMP SCHEDULES'!$A$4:$A$13,0),MIN(12,P$4-$D7+1))*$E7) -> 66667.2 | ... T7: =IF(OR($C7="",T$4<$D7),0,INDEX('RAMP SCHEDULES'!$B$4:$M$13,MATCH($C7,'RAMP SCHEDULES'!$A$4:$A$13,0),MIN(12,T$4-$D7+1))*$E7) -> 66667.2 | U7: =IF(OR($C7="",U$4<$D7),0,INDEX('RAMP SCHEDULES'!$B$4:$M$13,MATCH($C7,'RAMP SCHEDULES'!$A$4:$A$13,0),MIN(12,U$4-$D7+1))*$F7) -> 83333 | V7: =IF(OR($C7="",V$4<$D7),0,INDEX('RAMP SCHEDULES'!$B$4:$M$13,MATCH($C7,'RAMP SCHEDULES'!$A$4:$A$13,0),MIN(12,V$4-$D7+1))*$F7) -> 83333 | W7: =IF(OR($C7="",W$4<$D7),0,INDEX('RAMP SCHEDULES'!$B$4:$M$13,MATCH($C7,'RAMP SCHEDULES'!$A$4:$A$13,0),MIN(12,W$4-$D7+1))*$F7) -> 83334 | X7: =IF(OR($C7="",X$4<$D7),0,INDEX('RAMP SCHEDULES'!$B$4:$M$13,MATCH($C7,'RAMP SCHEDULES'!$A$4:$A$13,0),MIN(12,X$4-$D7+1))*$F7) -> 83334 | Y7: =IF(OR($C7="",Y$4<$D7),0,INDEX('RAMP SCHEDULES'!$B$4:$M$13,MATCH($C7,'RAMP SCHEDULES'!$A$4:$A$13,0),MIN(12,Y$4-$D7+1))*$F7) -> 83334 | Z7: =IF(OR($C7="",Z$4<$D7),0,INDEX('RAMP SCHEDULES'!$B$4:$M$13,MATCH($C7,'RAMP SCHEDULES'!$A$4:$A$13,0),MIN(12,Z$4-$D7+1))*$F7) -> 83334 | AA7: =IF(OR($C7="",AA$4<$D7),0,INDEX('RAMP SCHEDULES'!$B$4:$M$13,MATCH($C7,'RAMP SCHEDULES'!$A$4:$A$13,0),MIN(12,AA$4-$D7+1))*$F7) -> 83334 | AB7: =IF(OR($C7="",AB$4<$D7),0,INDEX('RAMP SCHEDULES'!$B$4:$M$13,MATCH($C7,'RAMP SCHEDULES'!$A$4:$A$13,0),MIN(12,AB$4-$D7+1))*$F7) -> 83334 | ... AF7: =IF(OR($C7="",AF$4<$D7),0,INDEX('RAMP SCHEDULES'!$B$4:$M$13,MATCH($C7,'RAMP SCHEDULES'!$A$4:$A$13,0),MIN(12,AF$4-$D7+1))*$F7) -> 83334 | AG7: =SUM(I7:T7) -> 800004.8 | AH7: =SUM(U7:AF7) -> 1000006 | AI7: =AG7*$G7 -> 20000.12 | AJ7: =AH7*$G7 -> 25000.15
A8: Sam Childers | B8: Account Executive - RAMP | C8: NEW AE | D8: -8 | E8: 0.8 | F8: 1 | G8: 0.025 | H8: =IF($C8="",0,12*INDEX('RAMP SCHEDULES'!$B$4:$M$13,MATCH($C8,'RAMP SCHEDULES'!$A$4:$A$13,0),12)) -> 1000008 | I8: =IF(OR($C8="",I$4<$D8),0,INDEX('RAMP SCHEDULES'!$B$4:$M$13,MATCH($C8,'RAMP SCHEDULES'!$A$4:$A$13,0),MIN(12,I$4-$D8+1))*$E8) -> 66666.4 | J8: =IF(OR($C8="",J$4<$D8),0,INDEX('RAMP SCHEDULES'!$B$4:$M$13,MATCH($C8,'RAMP SCHEDULES'!$A$4:$A$13,0),MIN(12,J$4-$D8+1))*$E8) -> 66666.4 | K8: =IF(OR($C8="",K$4<$D8),0,INDEX('RAMP SCHEDULES'!$B$4:$M$13,MATCH($C8,'RAMP SCHEDULES'!$A$4:$A$13,0),MIN(12,K$4-$D8+1))*$E8) -> 66667.2 | L8: =IF(OR($C8="",L$4<$D8),0,INDEX('RAMP SCHEDULES'!$B$4:$M$13,MATCH($C8,'RAMP SCHEDULES'!$A$4:$A$13,0),MIN(12,L$4-$D8+1))*$E8) -> 66667.2 | M8: =IF(OR($C8="",M$4<$D8),0,INDEX('RAMP SCHEDULES'!$B$4:$M$13,MATCH($C8,'RAMP SCHEDULES'!$A$4:$A$13,0),MIN(12,M$4-$D8+1))*$E8) -> 66667.2 | N8: =IF(OR($C8="",N$4<$D8),0,INDEX('RAMP SCHEDULES'!$B$4:$M$13,MATCH($C8,'RAMP SCHEDULES'!$A$4:$A$13,0),MIN(12,N$4-$D8+1))*$E8) -> 66667.2 | O8: =IF(OR($C8="",O$4<$D8),0,INDEX('RAMP SCHEDULES'!$B$4:$M$13,MATCH($C8,'RAMP SCHEDULES'!$A$4:$A$13,0),MIN(12,O$4-$D8+1))*$E8) -> 66667.2 | P8: =IF(OR($C8="",P$4<$D8),0,INDEX('RAMP SCHEDULES'!$B$4:$M$13,MATCH($C8,'RAMP SCHEDULES'!$A$4:$A$13,0),MIN(12,P$4-$D8+1))*$E8) -> 66667.2 | ... T8: =IF(OR($C8="",T$4<$D8),0,INDEX('RAMP SCHEDULES'!$B$4:$M$13,MATCH($C8,'RAMP SCHEDULES'!$A$4:$A$13,0),MIN(12,T$4-$D8+1))*$E8) -> 66667.2 | U8: =IF(OR($C8="",U$4<$D8),0,INDEX('RAMP SCHEDULES'!$B$4:$M$13,MATCH($C8,'RAMP SCHEDULES'!$A$4:$A$13,0),MIN(12,U$4-$D8+1))*$F8) -> 83333 | V8: =IF(OR($C8="",V$4<$D8),0,INDEX('RAMP SCHEDULES'!$B$4:$M$13,MATCH($C8,'RAMP SCHEDULES'!$A$4:$A$13,0),MIN(12,V$4-$D8+1))*$F8) -> 83333 | W8: =IF(OR($C8="",W$4<$D8),0,INDEX('RAMP SCHEDULES'!$B$4:$M$13,MATCH($C8,'RAMP SCHEDULES'!$A$4:$A$13,0),MIN(12,W$4-$D8+1))*$F8) -> 83334 | X8: =IF(OR($C8="",X$4<$D8),0,INDEX('RAMP SCHEDULES'!$B$4:$M$13,MATCH($C8,'RAMP SCHEDULES'!$A$4:$A$13,0),MIN(12,X$4-$D8+1))*$F8) -> 83334 | Y8: =IF(OR($C8="",Y$4<$D8),0,INDEX('RAMP SCHEDULES'!$B$4:$M$13,MATCH($C8,'RAMP SCHEDULES'!$A$4:$A$13,0),MIN(12,Y$4-$D8+1))*$F8) -> 83334 | Z8: =IF(OR($C8="",Z$4<$D8),0,INDEX('RAMP SCHEDULES'!$B$4:$M$13,MATCH($C8,'RAMP SCHEDULES'!$A$4:$A$13,0),MIN(12,Z$4-$D8+1))*$F8) -> 83334 | AA8: =IF(OR($C8="",AA$4<$D8),0,INDEX('RAMP SCHEDULES'!$B$4:$M$13,MATCH($C8,'RAMP SCHEDULES'!$A$4:$A$13,0),MIN(12,AA$4-$D8+1))*$F8) -> 83334 | AB8: =IF(OR($C8="",AB$4<$D8),0,INDEX('RAMP SCHEDULES'!$B$4:$M$13,MATCH($C8,'RAMP SCHEDULES'!$A$4:$A$13,0),MIN(12,AB$4-$D8+1))*$F8) -> 83334 | ... AF8: =IF(OR($C8="",AF$4<$D8),0,INDEX('RAMP SCHEDULES'!$B$4:$M$13,MATCH($C8,'RAMP SCHEDULES'!$A$4:$A$13,0),MIN(12,AF$4-$D8+1))*$F8) -> 83334 | AG8: =SUM(I8:T8) -> 800004.8 | AH8: =SUM(U8:AF8) -> 1000006 | AI8: =AG8*$G8 -> 20000.12 | AJ8: =AH8*$G8 -> 25000.15
A9: Zach Schiff | B9: Account Executive - RAMP | C9: NEW AE | D9: -8 | E9: 0.8 | F9: 1 | G9: 0.025 | H9: =IF($C9="",0,12*INDEX('RAMP SCHEDULES'!$B$4:$M$13,MATCH($C9,'RAMP SCHEDULES'!$A$4:$A$13,0),12)) -> 1000008 | I9: =IF(OR($C9="",I$4<$D9),0,INDEX('RAMP SCHEDULES'!$B$4:$M$13,MATCH($C9,'RAMP SCHEDULES'!$A$4:$A$13,0),MIN(12,I$4-$D9+1))*$E9) -> 66666.4 | J9: =IF(OR($C9="",J$4<$D9),0,INDEX('RAMP SCHEDULES'!$B$4:$M$13,MATCH($C9,'RAMP SCHEDULES'!$A$4:$A$13,0),MIN(12,J$4-$D9+1))*$E9) -> 66666.4 | K9: =IF(OR($C9="",K$4<$D9),0,INDEX('RAMP SCHEDULES'!$B$4:$M$13,MATCH($C9,'RAMP SCHEDULES'!$A$4:$A$13,0),MIN(12,K$4-$D9+1))*$E9) -> 66667.2 | L9: =IF(OR($C9="",L$4<$D9),0,INDEX('RAMP SCHEDULES'!$B$4:$M$13,MATCH($C9,'RAMP SCHEDULES'!$A$4:$A$13,0),MIN(12,L$4-$D9+1))*$E9) -> 66667.2 | M9: =IF(OR($C9="",M$4<$D9),0,INDEX('RAMP SCHEDULES'!$B$4:$M$13,MATCH($C9,'RAMP SCHEDULES'!$A$4:$A$13,0),MIN(12,M$4-$D9+1))*$E9) -> 66667.2 | N9: =IF(OR($C9="",N$4<$D9),0,INDEX('RAMP SCHEDULES'!$B$4:$M$13,MATCH($C9,'RAMP SCHEDULES'!$A$4:$A$13,0),MIN(12,N$4-$D9+1))*$E9) -> 66667.2 | O9: =IF(OR($C9="",O$4<$D9),0,INDEX('RAMP SCHEDULES'!$B$4:$M$13,MATCH($C9,'RAMP SCHEDULES'!$A$4:$A$13,0),MIN(12,O$4-$D9+1))*$E9) -> 66667.2 | P9: =IF(OR($C9="",P$4<$D9),0,INDEX('RAMP SCHEDULES'!$B$4:$M$13,MATCH($C9,'RAMP SCHEDULES'!$A$4:$A$13,0),MIN(12,P$4-$D9+1))*$E9) -> 66667.2 | ... T9: =IF(OR($C9="",T$4<$D9),0,INDEX('RAMP SCHEDULES'!$B$4:$M$13,MATCH($C9,'RAMP SCHEDULES'!$A$4:$A$13,0),MIN(12,T$4-$D9+1))*$E9) -> 66667.2 | U9: =IF(OR($C9="",U$4<$D9),0,INDEX('RAMP SCHEDULES'!$B$4:$M$13,MATCH($C9,'RAMP SCHEDULES'!$A$4:$A$13,0),MIN(12,U$4-$D9+1))*$F9) -> 83333 | V9: =IF(OR($C9="",V$4<$D9),0,INDEX('RAMP SCHEDULES'!$B$4:$M$13,MATCH($C9,'RAMP SCHEDULES'!$A$4:$A$13,0),MIN(12,V$4-$D9+1))*$F9) -> 83333 | W9: =IF(OR($C9="",W$4<$D9),0,INDEX('RAMP SCHEDULES'!$B$4:$M$13,MATCH($C9,'RAMP SCHEDULES'!$A$4:$A$13,0),MIN(12,W$4-$D9+1))*$F9) -> 83334 | X9: =IF(OR($C9="",X$4<$D9),0,INDEX('RAMP SCHEDULES'!$B$4:$M$13,MATCH($C9,'RAMP SCHEDULES'!$A$4:$A$13,0),MIN(12,X$4-$D9+1))*$F9) -> 83334 | Y9: =IF(OR($C9="",Y$4<$D9),0,INDEX('RAMP SCHEDULES'!$B$4:$M$13,MATCH($C9,'RAMP SCHEDULES'!$A$4:$A$13,0),MIN(12,Y$4-$D9+1))*$F9) -> 83334 | Z9: =IF(OR($C9="",Z$4<$D9),0,INDEX('RAMP SCHEDULES'!$B$4:$M$13,MATCH($C9,'RAMP SCHEDULES'!$A$4:$A$13,0),MIN(12,Z$4-$D9+1))*$F9) -> 83334 | AA9: =IF(OR($C9="",AA$4<$D9),0,INDEX('RAMP SCHEDULES'!$B$4:$M$13,MATCH($C9,'RAMP SCHEDULES'!$A$4:$A$13,0),MIN(12,AA$4-$D9+1))*$F9) -> 83334 | AB9: =IF(OR($C9="",AB$4<$D9),0,INDEX('RAMP SCHEDULES'!$B$4:$M$13,MATCH($C9,'RAMP SCHEDULES'!$A$4:$A$13,0),MIN(12,AB$4-$D9+1))*$F9) -> 83334 | ... AF9: =IF(OR($C9="",AF$4<$D9),0,INDEX('RAMP SCHEDULES'!$B$4:$M$13,MATCH($C9,'RAMP SCHEDULES'!$A$4:$A$13,0),MIN(12,AF$4-$D9+1))*$F9) -> 83334 | AG9: =SUM(I9:T9) -> 800004.8 | AH9: =SUM(U9:AF9) -> 1000006 | AI9: =AG9*$G9 -> 20000.12 | AJ9: =AH9*$G9 -> 25000.15
A10: Kenny Hester | B10: Account Executive - RAMP | C10: NEW AE | D10: -4 | E10: 0.8 | F10: 1 | G10: 0.025 | H10: =IF($C10="",0,12*INDEX('RAMP SCHEDULES'!$B$4:$M$13,MATCH($C10,'RAMP SCHEDULES'!$A$4:$A$13,0),12)) -> 1000008 | I10: =IF(OR($C10="",I$4<$D10),0,INDEX('RAMP SCHEDULES'!$B$4:$M$13,MATCH($C10,'RAMP SCHEDULES'!$A$4:$A$13,0),MIN(12,I$4-$D10+1))*$E10) -> 36000 | J10: =IF(OR($C10="",J$4<$D10),0,INDEX('RAMP SCHEDULES'!$B$4:$M$13,MATCH($C10,'RAMP SCHEDULES'!$A$4:$A$13,0),MIN(12,J$4-$D10+1))*$E10) -> 40000 | K10: =IF(OR($C10="",K$4<$D10),0,INDEX('RAMP SCHEDULES'!$B$4:$M$13,MATCH($C10,'RAMP SCHEDULES'!$A$4:$A$13,0),MIN(12,K$4-$D10+1))*$E10) -> 44000 | L10: =IF(OR($C10="",L$4<$D10),0,INDEX('RAMP SCHEDULES'!$B$4:$M$13,MATCH($C10,'RAMP SCHEDULES'!$A$4:$A$13,0),MIN(12,L$4-$D10+1))*$E10) -> 56000 | M10: =IF(OR($C10="",M$4<$D10),0,INDEX('RAMP SCHEDULES'!$B$4:$M$13,MATCH($C10,'RAMP SCHEDULES'!$A$4:$A$13,0),MIN(12,M$4-$D10+1))*$E10) -> 66666.4 | N10: =IF(OR($C10="",N$4<$D10),0,INDEX('RAMP SCHEDULES'!$B$4:$M$13,MATCH($C10,'RAMP SCHEDULES'!$A$4:$A$13,0),MIN(12,N$4-$D10+1))*$E10) -> 66666.4 | O10: =IF(OR($C10="",O$4<$D10),0,INDEX('RAMP SCHEDULES'!$B$4:$M$13,MATCH($C10,'RAMP SCHEDULES'!$A$4:$A$13,0),MIN(12,O$4-$D10+1))*$E10) -> 66667.2 | P10: =IF(OR($C10="",P$4<$D10),0,INDEX('RAMP SCHEDULES'!$B$4:$M$13,MATCH($C10,'RAMP SCHEDULES'!$A$4:$A$13,0),MIN(12,P$4-$D10+1))*$E10) -> 66667.2 | ... T10: =IF(OR($C10="",T$4<$D10),0,INDEX('RAMP SCHEDULES'!$B$4:$M$13,MATCH($C10,'RAMP SCHEDULES'!$A$4:$A$13,0),MIN(12,T$4-$D10+1))*$E10) -> 66667.2 | U10: =IF(OR($C10="",U$4<$D10),0,INDEX('RAMP SCHEDULES'!$B$4:$M$13,MATCH($C10,'RAMP SCHEDULES'!$A$4:$A$13,0),MIN(12,U$4-$D10+1))*$F10) -> 45000 | V10: =IF(OR($C10="",V$4<$D10),0,INDEX('RAMP SCHEDULES'!$B$4:$M$13,MATCH($C10,'RAMP SCHEDULES'!$A$4:$A$13,0),MIN(12,V$4-$D10+1))*$F10) -> 50000 | W10: =IF(OR($C10="",W$4<$D10),0,INDEX('RAMP SCHEDULES'!$B$4:$M$13,MATCH($C10,'RAMP SCHEDULES'!$A$4:$A$13,0),MIN(12,W$4-$D10+1))*$F10) -> 55000 | X10: =IF(OR($C10="",X$4<$D10),0,INDEX('RAMP SCHEDULES'!$B$4:$M$13,MATCH($C10,'RAMP SCHEDULES'!$A$4:$A$13,0),MIN(12,X$4-$D10+1))*$F10) -> 70000 | Y10: =IF(OR($C10="",Y$4<$D10),0,INDEX('RAMP SCHEDULES'!$B$4:$M$13,MATCH($C10,'RAMP SCHEDULES'!$A$4:$A$13,0),MIN(12,Y$4-$D10+1))*$F10) -> 83333 | Z10: =IF(OR($C10="",Z$4<$D10),0,INDEX('RAMP SCHEDULES'!$B$4:$M$13,MATCH($C10,'RAMP SCHEDULES'!$A$4:$A$13,0),MIN(12,Z$4-$D10+1))*$F10) -> 83333 | AA10: =IF(OR($C10="",AA$4<$D10),0,INDEX('RAMP SCHEDULES'!$B$4:$M$13,MATCH($C10,'RAMP SCHEDULES'!$A$4:$A$13,0),MIN(12,AA$4-$D10+1))*$F10) -> 83334 | AB10: =IF(OR($C10="",AB$4<$D10),0,INDEX('RAMP SCHEDULES'!$B$4:$M$13,MATCH($C10,'RAMP SCHEDULES'!$A$4:$A$13,0),MIN(12,AB$4-$D10+1))*$F10) -> 83334 | ... AF10: =IF(OR($C10="",AF$4<$D10),0,INDEX('RAMP SCHEDULES'!$B$4:$M$13,MATCH($C10,'RAMP SCHEDULES'!$A$4:$A$13,0),MIN(12,AF$4-$D10+1))*$F10) -> 83334 | AG10: =SUM(I10:T10) -> 709336 | AH10: =SUM(U10:AF10) -> 886670 | AI10: =AG10*$G10 -> 17733.4 | AJ10: =AH10*$G10 -> 22166.75
A11: Brian Burke | B11: Account Executive - RAMP | C11: NEW AE | D11: -1 | E11: 0.8 | F11: 1 | G11: 0.025 | H11: =IF($C11="",0,12*INDEX('RAMP SCHEDULES'!$B$4:$M$13,MATCH($C11,'RAMP SCHEDULES'!$A$4:$A$13,0),12)) -> 1000008 | I11: =IF(OR($C11="",I$4<$D11),0,INDEX('RAMP SCHEDULES'!$B$4:$M$13,MATCH($C11,'RAMP SCHEDULES'!$A$4:$A$13,0),MIN(12,I$4-$D11+1))*$E11) -> 32000 | J11: =IF(OR($C11="",J$4<$D11),0,INDEX('RAMP SCHEDULES'!$B$4:$M$13,MATCH($C11,'RAMP SCHEDULES'!$A$4:$A$13,0),MIN(12,J$4-$D11+1))*$E11) -> 32000 | K11: =IF(OR($C11="",K$4<$D11),0,INDEX('RAMP SCHEDULES'!$B$4:$M$13,MATCH($C11,'RAMP SCHEDULES'!$A$4:$A$13,0),MIN(12,K$4-$D11+1))*$E11) -> 36000 | L11: =IF(OR($C11="",L$4<$D11),0,INDEX('RAMP SCHEDULES'!$B$4:$M$13,MATCH($C11,'RAMP SCHEDULES'!$A$4:$A$13,0),MIN(12,L$4-$D11+1))*$E11) -> 36000 | M11: =IF(OR($C11="",M$4<$D11),0,INDEX('RAMP SCHEDULES'!$B$4:$M$13,MATCH($C11,'RAMP SCHEDULES'!$A$4:$A$13,0),MIN(12,M$4-$D11+1))*$E11) -> 40000 | N11: =IF(OR($C11="",N$4<$D11),0,INDEX('RAMP SCHEDULES'!$B$4:$M$13,MATCH($C11,'RAMP SCHEDULES'!$A$4:$A$13,0),MIN(12,N$4-$D11+1))*$E11) -> 44000 | O11: =IF(OR($C11="",O$4<$D11),0,INDEX('RAMP SCHEDULES'!$B$4:$M$13,MATCH($C11,'RAMP SCHEDULES'!$A$4:$A$13,0),MIN(12,O$4-$D11+1))*$E11) -> 56000 | P11: =IF(OR($C11="",P$4<$D11),0,INDEX('RAMP SCHEDULES'!$B$4:$M$13,MATCH($C11,'RAMP SCHEDULES'!$A$4:$A$13,0),MIN(12,P$4-$D11+1))*$E11) -> 66666.4 | ... T11: =IF(OR($C11="",T$4<$D11),0,INDEX('RAMP SCHEDULES'!$B$4:$M$13,MATCH($C11,'RAMP SCHEDULES'!$A$4:$A$13,0),MIN(12,T$4-$D11+1))*$E11) -> 66667.2 | U11: =IF(OR($C11="",U$4<$D11),0,INDEX('RAMP SCHEDULES'!$B$4:$M$13,MATCH($C11,'RAMP SCHEDULES'!$A$4:$A$13,0),MIN(12,U$4-$D11+1))*$F11) -> 40000 | V11: =IF(OR($C11="",V$4<$D11),0,INDEX('RAMP SCHEDULES'!$B$4:$M$13,MATCH($C11,'RAMP SCHEDULES'!$A$4:$A$13,0),MIN(12,V$4-$D11+1))*$F11) -> 40000 | W11: =IF(OR($C11="",W$4<$D11),0,INDEX('RAMP SCHEDULES'!$B$4:$M$13,MATCH($C11,'RAMP SCHEDULES'!$A$4:$A$13,0),MIN(12,W$4-$D11+1))*$F11) -> 45000 | X11: =IF(OR($C11="",X$4<$D11),0,INDEX('RAMP SCHEDULES'!$B$4:$M$13,MATCH($C11,'RAMP SCHEDULES'!$A$4:$A$13,0),MIN(12,X$4-$D11+1))*$F11) -> 45000 | Y11: =IF(OR($C11="",Y$4<$D11),0,INDEX('RAMP SCHEDULES'!$B$4:$M$13,MATCH($C11,'RAMP SCHEDULES'!$A$4:$A$13,0),MIN(12,Y$4-$D11+1))*$F11) -> 50000 | Z11: =IF(OR($C11="",Z$4<$D11),0,INDEX('RAMP SCHEDULES'!$B$4:$M$13,MATCH($C11,'RAMP SCHEDULES'!$A$4:$A$13,0),MIN(12,Z$4-$D11+1))*$F11) -> 55000 | AA11: =IF(OR($C11="",AA$4<$D11),0,INDEX('RAMP SCHEDULES'!$B$4:$M$13,MATCH($C11,'RAMP SCHEDULES'!$A$4:$A$13,0),MIN(12,AA$4-$D11+1))*$F11) -> 70000 | AB11: =IF(OR($C11="",AB$4<$D11),0,INDEX('RAMP SCHEDULES'!$B$4:$M$13,MATCH($C11,'RAMP SCHEDULES'!$A$4:$A$13,0),MIN(12,AB$4-$D11+1))*$F11) -> 83333 | ... AF11: =IF(OR($C11="",AF$4<$D11),0,INDEX('RAMP SCHEDULES'!$B$4:$M$13,MATCH($C11,'RAMP SCHEDULES'!$A$4:$A$13,0),MIN(12,AF$4-$D11+1))*$F11) -> 83334 | AG11: =SUM(I11:T11) -> 609334.4 | AH11: =SUM(U11:AF11) -> 761668 | AI11: =AG11*$G11 -> 15233.36 | AJ11: =AH11*$G11 -> 19041.7
A12: Jonathan Pierce | B12: Account Executive - RAMP | C12: NEW AE | D12: 3 | E12: 0.8 | F12: 1 | G12: 0.025 | H12: =IF($C12="",0,12*INDEX('RAMP SCHEDULES'!$B$4:$M$13,MATCH($C12,'RAMP SCHEDULES'!$A$4:$A$13,0),12)) -> 1000008 | I12: =IF(OR($C12="",I$4<$D12),0,INDEX('RAMP SCHEDULES'!$B$4:$M$13,MATCH($C12,'RAMP SCHEDULES'!$A$4:$A$13,0),MIN(12,I$4-$D12+1))*$E12) -> 0 | J12: =IF(OR($C12="",J$4<$D12),0,INDEX('RAMP SCHEDULES'!$B$4:$M$13,MATCH($C12,'RAMP SCHEDULES'!$A$4:$A$13,0),MIN(12,J$4-$D12+1))*$E12) -> 0 | K12: =IF(OR($C12="",K$4<$D12),0,INDEX('RAMP SCHEDULES'!$B$4:$M$13,MATCH($C12,'RAMP SCHEDULES'!$A$4:$A$13,0),MIN(12,K$4-$D12+1))*$E12) -> 0 | L12: =IF(OR($C12="",L$4<$D12),0,INDEX('RAMP SCHEDULES'!$B$4:$M$13,MATCH($C12,'RAMP SCHEDULES'!$A$4:$A$13,0),MIN(12,L$4-$D12+1))*$E12) -> 24000 | M12: =IF(OR($C12="",M$4<$D12),0,INDEX('RAMP SCHEDULES'!$B$4:$M$13,MATCH($C12,'RAMP SCHEDULES'!$A$4:$A$13,0),MIN(12,M$4-$D12+1))*$E12) -> 32000 | N12: =IF(OR($C12="",N$4<$D12),0,INDEX('RAMP SCHEDULES'!$B$4:$M$13,MATCH($C12,'RAMP SCHEDULES'!$A$4:$A$13,0),MIN(12,N$4-$D12+1))*$E12) -> 32000 | O12: =IF(OR($C12="",O$4<$D12),0,INDEX('RAMP SCHEDULES'!$B$4:$M$13,MATCH($C12,'RAMP SCHEDULES'!$A$4:$A$13,0),MIN(12,O$4-$D12+1))*$E12) -> 36000 | P12: =IF(OR($C12="",P$4<$D12),0,INDEX('RAMP SCHEDULES'!$B$4:$M$13,MATCH($C12,'RAMP SCHEDULES'!$A$4:$A$13,0),MIN(12,P$4-$D12+1))*$E12) -> 36000 | ... T12: =IF(OR($C12="",T$4<$D12),0,INDEX('RAMP SCHEDULES'!$B$4:$M$13,MATCH($C12,'RAMP SCHEDULES'!$A$4:$A$13,0),MIN(12,T$4-$D12+1))*$E12) -> 66666.4 | U12: =IF(OR($C12="",U$4<$D12),0,INDEX('RAMP SCHEDULES'!$B$4:$M$13,MATCH($C12,'RAMP SCHEDULES'!$A$4:$A$13,0),MIN(12,U$4-$D12+1))*$F12) -> 0 | V12: =IF(OR($C12="",V$4<$D12),0,INDEX('RAMP SCHEDULES'!$B$4:$M$13,MATCH($C12,'RAMP SCHEDULES'!$A$4:$A$13,0),MIN(12,V$4-$D12+1))*$F12) -> 0 | W12: =IF(OR($C12="",W$4<$D12),0,INDEX('RAMP SCHEDULES'!$B$4:$M$13,MATCH($C12,'RAMP SCHEDULES'!$A$4:$A$13,0),MIN(12,W$4-$D12+1))*$F12) -> 0 | X12: =IF(OR($C12="",X$4<$D12),0,INDEX('RAMP SCHEDULES'!$B$4:$M$13,MATCH($C12,'RAMP SCHEDULES'!$A$4:$A$13,0),MIN(12,X$4-$D12+1))*$F12) -> 30000 | Y12: =IF(OR($C12="",Y$4<$D12),0,INDEX('RAMP SCHEDULES'!$B$4:$M$13,MATCH($C12,'RAMP SCHEDULES'!$A$4:$A$13,0),MIN(12,Y$4-$D12+1))*$F12) -> 40000 | Z12: =IF(OR($C12="",Z$4<$D12),0,INDEX('RAMP SCHEDULES'!$B$4:$M$13,MATCH($C12,'RAMP SCHEDULES'!$A$4:$A$13,0),MIN(12,Z$4-$D12+1))*$F12) -> 40000 | AA12: =IF(OR($C12="",AA$4<$D12),0,INDEX('RAMP SCHEDULES'!$B$4:$M$13,MATCH($C12,'RAMP SCHEDULES'!$A$4:$A$13,0),MIN(12,AA$4-$D12+1))*$F12) -> 45000 | AB12: =IF(OR($C12="",AB$4<$D12),0,INDEX('RAMP SCHEDULES'!$B$4:$M$13,MATCH($C12,'RAMP SCHEDULES'!$A$4:$A$13,0),MIN(12,AB$4-$D12+1))*$F12) -> 45000 | ... AF12: =IF(OR($C12="",AF$4<$D12),0,INDEX('RAMP SCHEDULES'!$B$4:$M$13,MATCH($C12,'RAMP SCHEDULES'!$A$4:$A$13,0),MIN(12,AF$4-$D12+1))*$F12) -> 83333 | AG12: =SUM(I12:T12) -> 366666.4 | AH12: =SUM(U12:AF12) -> 458333 | AI12: =AG12*$G12 -> 9166.66 | AJ12: =AH12*$G12 -> 11458.325
A13: Cory Anderson | B13: Account Executive - RAMP | C13: NEW AE | D13: 3 | E13: 0.8 | F13: 1 | G13: 0.025 | H13: =IF($C13="",0,12*INDEX('RAMP SCHEDULES'!$B$4:$M$13,MATCH($C13,'RAMP SCHEDULES'!$A$4:$A$13,0),12)) -> 1000008 | I13: =IF(OR($C13="",I$4<$D13),0,INDEX('RAMP SCHEDULES'!$B$4:$M$13,MATCH($C13,'RAMP SCHEDULES'!$A$4:$A$13,0),MIN(12,I$4-$D13+1))*$E13) -> 0 | J13: =IF(OR($C13="",J$4<$D13),0,INDEX('RAMP SCHEDULES'!$B$4:$M$13,MATCH($C13,'RAMP SCHEDULES'!$A$4:$A$13,0),MIN(12,J$4-$D13+1))*$E13) -> 0 | K13: =IF(OR($C13="",K$4<$D13),0,INDEX('RAMP SCHEDULES'!$B$4:$M$13,MATCH($C13,'RAMP SCHEDULES'!$A$4:$A$13,0),MIN(12,K$4-$D13+1))*$E13) -> 0 | L13: =IF(OR($C13="",L$4<$D13),0,INDEX('RAMP SCHEDULES'!$B$4:$M$13,MATCH($C13,'RAMP SCHEDULES'!$A$4:$A$13,0),MIN(12,L$4-$D13+1))*$E13) -> 24000 | M13: =IF(OR($C13="",M$4<$D13),0,INDEX('RAMP SCHEDULES'!$B$4:$M$13,MATCH($C13,'RAMP SCHEDULES'!$A$4:$A$13,0),MIN(12,M$4-$D13+1))*$E13) -> 32000 | N13: =IF(OR($C13="",N$4<$D13),0,INDEX('RAMP SCHEDULES'!$B$4:$M$13,MATCH($C13,'RAMP SCHEDULES'!$A$4:$A$13,0),MIN(12,N$4-$D13+1))*$E13) -> 32000 | O13: =IF(OR($C13="",O$4<$D13),0,INDEX('RAMP SCHEDULES'!$B$4:$M$13,MATCH($C13,'RAMP SCHEDULES'!$A$4:$A$13,0),MIN(12,O$4-$D13+1))*$E13) -> 36000 | P13: =IF(OR($C13="",P$4<$D13),0,INDEX('RAMP SCHEDULES'!$B$4:$M$13,MATCH($C13,'RAMP SCHEDULES'!$A$4:$A$13,0),MIN(12,P$4-$D13+1))*$E13) -> 36000 | ... T13: =IF(OR($C13="",T$4<$D13),0,INDEX('RAMP SCHEDULES'!$B$4:$M$13,MATCH($C13,'RAMP SCHEDULES'!$A$4:$A$13,0),MIN(12,T$4-$D13+1))*$E13) -> 66666.4 | U13: =IF(OR($C13="",U$4<$D13),0,INDEX('RAMP SCHEDULES'!$B$4:$M$13,MATCH($C13,'RAMP SCHEDULES'!$A$4:$A$13,0),MIN(12,U$4-$D13+1))*$F13) -> 0 | V13: =IF(OR($C13="",V$4<$D13),0,INDEX('RAMP SCHEDULES'!$B$4:$M$13,MATCH($C13,'RAMP SCHEDULES'!$A$4:$A$13,0),MIN(12,V$4-$D13+1))*$F13) -> 0 | W13: =IF(OR($C13="",W$4<$D13),0,INDEX('RAMP SCHEDULES'!$B$4:$M$13,MATCH($C13,'RAMP SCHEDULES'!$A$4:$A$13,0),MIN(12,W$4-$D13+1))*$F13) -> 0 | X13: =IF(OR($C13="",X$4<$D13),0,INDEX('RAMP SCHEDULES'!$B$4:$M$13,MATCH($C13,'RAMP SCHEDULES'!$A$4:$A$13,0),MIN(12,X$4-$D13+1))*$F13) -> 30000 | Y13: =IF(OR($C13="",Y$4<$D13),0,INDEX('RAMP SCHEDULES'!$B$4:$M$13,MATCH($C13,'RAMP SCHEDULES'!$A$4:$A$13,0),MIN(12,Y$4-$D13+1))*$F13) -> 40000 | Z13: =IF(OR($C13="",Z$4<$D13),0,INDEX('RAMP SCHEDULES'!$B$4:$M$13,MATCH($C13,'RAMP SCHEDULES'!$A$4:$A$13,0),MIN(12,Z$4-$D13+1))*$F13) -> 40000 | AA13: =IF(OR($C13="",AA$4<$D13),0,INDEX('RAMP SCHEDULES'!$B$4:$M$13,MATCH($C13,'RAMP SCHEDULES'!$A$4:$A$13,0),MIN(12,AA$4-$D13+1))*$F13) -> 45000 | AB13: =IF(OR($C13="",AB$4<$D13),0,INDEX('RAMP SCHEDULES'!$B$4:$M$13,MATCH($C13,'RAMP SCHEDULES'!$A$4:$A$13,0),MIN(12,AB$4-$D13+1))*$F13) -> 45000 | ... AF13: =IF(OR($C13="",AF$4<$D13),0,INDEX('RAMP SCHEDULES'!$B$4:$M$13,MATCH($C13,'RAMP SCHEDULES'!$A$4:$A$13,0),MIN(12,AF$4-$D13+1))*$F13) -> 83333 | AG13: =SUM(I13:T13) -> 366666.4 | AH13: =SUM(U13:AF13) -> 458333 | AI13: =AG13*$G13 -> 9166.66 | AJ13: =AH13*$G13 -> 11458.325
A14: Justin Atherton | B14: Account Executive - RAMP | C14: NEW AE | D14: -1 | E14: 0.8 | F14: 1 | G14: 0.025 | H14: =IF($C14="",0,12*INDEX('RAMP SCHEDULES'!$B$4:$M$13,MATCH($C14,'RAMP SCHEDULES'!$A$4:$A$13,0),12)) -> 1000008 | I14: =IF(OR($C14="",I$4<$D14),0,INDEX('RAMP SCHEDULES'!$B$4:$M$13,MATCH($C14,'RAMP SCHEDULES'!$A$4:$A$13,0),MIN(12,I$4-$D14+1))*$E14) -> 32000 | J14: =IF(OR($C14="",J$4<$D14),0,INDEX('RAMP SCHEDULES'!$B$4:$M$13,MATCH($C14,'RAMP SCHEDULES'!$A$4:$A$13,0),MIN(12,J$4-$D14+1))*$E14) -> 32000 | K14: =IF(OR($C14="",K$4<$D14),0,INDEX('RAMP SCHEDULES'!$B$4:$M$13,MATCH($C14,'RAMP SCHEDULES'!$A$4:$A$13,0),MIN(12,K$4-$D14+1))*$E14) -> 36000 | L14: =IF(OR($C14="",L$4<$D14),0,INDEX('RAMP SCHEDULES'!$B$4:$M$13,MATCH($C14,'RAMP SCHEDULES'!$A$4:$A$13,0),MIN(12,L$4-$D14+1))*$E14) -> 36000 | M14: =IF(OR($C14="",M$4<$D14),0,INDEX('RAMP SCHEDULES'!$B$4:$M$13,MATCH($C14,'RAMP SCHEDULES'!$A$4:$A$13,0),MIN(12,M$4-$D14+1))*$E14) -> 40000 | N14: =IF(OR($C14="",N$4<$D14),0,INDEX('RAMP SCHEDULES'!$B$4:$M$13,MATCH($C14,'RAMP SCHEDULES'!$A$4:$A$13,0),MIN(12,N$4-$D14+1))*$E14) -> 44000 | O14: =IF(OR($C14="",O$4<$D14),0,INDEX('RAMP SCHEDULES'!$B$4:$M$13,MATCH($C14,'RAMP SCHEDULES'!$A$4:$A$13,0),MIN(12,O$4-$D14+1))*$E14) -> 56000 | P14: =IF(OR($C14="",P$4<$D14),0,INDEX('RAMP SCHEDULES'!$B$4:$M$13,MATCH($C14,'RAMP SCHEDULES'!$A$4:$A$13,0),MIN(12,P$4-$D14+1))*$E14) -> 66666.4 | ... T14: =IF(OR($C14="",T$4<$D14),0,INDEX('RAMP SCHEDULES'!$B$4:$M$13,MATCH($C14,'RAMP SCHEDULES'!$A$4:$A$13,0),MIN(12,T$4-$D14+1))*$E14) -> 66667.2 | U14: =IF(OR($C14="",U$4<$D14),0,INDEX('RAMP SCHEDULES'!$B$4:$M$13,MATCH($C14,'RAMP SCHEDULES'!$A$4:$A$13,0),MIN(12,U$4-$D14+1))*$F14) -> 40000 | V14: =IF(OR($C14="",V$4<$D14),0,INDEX('RAMP SCHEDULES'!$B$4:$M$13,MATCH($C14,'RAMP SCHEDULES'!$A$4:$A$13,0),MIN(12,V$4-$D14+1))*$F14) -> 40000 | W14: =IF(OR($C14="",W$4<$D14),0,INDEX('RAMP SCHEDULES'!$B$4:$M$13,MATCH($C14,'RAMP SCHEDULES'!$A$4:$A$13,0),MIN(12,W$4-$D14+1))*$F14) -> 45000 | X14: =IF(OR($C14="",X$4<$D14),0,INDEX('RAMP SCHEDULES'!$B$4:$M$13,MATCH($C14,'RAMP SCHEDULES'!$A$4:$A$13,0),MIN(12,X$4-$D14+1))*$F14) -> 45000 | Y14: =IF(OR($C14="",Y$4<$D14),0,INDEX('RAMP SCHEDULES'!$B$4:$M$13,MATCH($C14,'RAMP SCHEDULES'!$A$4:$A$13,0),MIN(12,Y$4-$D14+1))*$F14) -> 50000 | Z14: =IF(OR($C14="",Z$4<$D14),0,INDEX('RAMP SCHEDULES'!$B$4:$M$13,MATCH($C14,'RAMP SCHEDULES'!$A$4:$A$13,0),MIN(12,Z$4-$D14+1))*$F14) -> 55000 | AA14: =IF(OR($C14="",AA$4<$D14),0,INDEX('RAMP SCHEDULES'!$B$4:$M$13,MATCH($C14,'RAMP SCHEDULES'!$A$4:$A$13,0),MIN(12,AA$4-$D14+1))*$F14) -> 70000 | AB14: =IF(OR($C14="",AB$4<$D14),0,INDEX('RAMP SCHEDULES'!$B$4:$M$13,MATCH($C14,'RAMP SCHEDULES'!$A$4:$A$13,0),MIN(12,AB$4-$D14+1))*$F14) -> 83333 | ... AF14: =IF(OR($C14="",AF$4<$D14),0,INDEX('RAMP SCHEDULES'!$B$4:$M$13,MATCH($C14,'RAMP SCHEDULES'!$A$4:$A$13,0),MIN(12,AF$4-$D14+1))*$F14) -> 83334 | AG14: =SUM(I14:T14) -> 609334.4 | AH14: =SUM(U14:AF14) -> 761668 | AI14: =AG14*$G14 -> 15233.36 | AJ14: =AH14*$G14 -> 19041.7
A15: TBD | B15: Account Executive - RAMP | C15: NEW AE | D15: 6 | E15: 0.8 | F15: 1 | G15: 0.025 | H15: =IF($C15="",0,12*INDEX('RAMP SCHEDULES'!$B$4:$M$13,MATCH($C15,'RAMP SCHEDULES'!$A$4:$A$13,0),12)) -> 1000008 | I15: =IF(OR($C15="",I$4<$D15),0,INDEX('RAMP SCHEDULES'!$B$4:$M$13,MATCH($C15,'RAMP SCHEDULES'!$A$4:$A$13,0),MIN(12,I$4-$D15+1))*$E15) -> 0 | J15: =IF(OR($C15="",J$4<$D15),0,INDEX('RAMP SCHEDULES'!$B$4:$M$13,MATCH($C15,'RAMP SCHEDULES'!$A$4:$A$13,0),MIN(12,J$4-$D15+1))*$E15) -> 0 | K15: =IF(OR($C15="",K$4<$D15),0,INDEX('RAMP SCHEDULES'!$B$4:$M$13,MATCH($C15,'RAMP SCHEDULES'!$A$4:$A$13,0),MIN(12,K$4-$D15+1))*$E15) -> 0 | L15: =IF(OR($C15="",L$4<$D15),0,INDEX('RAMP SCHEDULES'!$B$4:$M$13,MATCH($C15,'RAMP SCHEDULES'!$A$4:$A$13,0),MIN(12,L$4-$D15+1))*$E15) -> 0 | M15: =IF(OR($C15="",M$4<$D15),0,INDEX('RAMP SCHEDULES'!$B$4:$M$13,MATCH($C15,'RAMP SCHEDULES'!$A$4:$A$13,0),MIN(12,M$4-$D15+1))*$E15) -> 0 | N15: =IF(OR($C15="",N$4<$D15),0,INDEX('RAMP SCHEDULES'!$B$4:$M$13,MATCH($C15,'RAMP SCHEDULES'!$A$4:$A$13,0),MIN(12,N$4-$D15+1))*$E15) -> 0 | O15: =IF(OR($C15="",O$4<$D15),0,INDEX('RAMP SCHEDULES'!$B$4:$M$13,MATCH($C15,'RAMP SCHEDULES'!$A$4:$A$13,0),MIN(12,O$4-$D15+1))*$E15) -> 24000 | P15: =IF(OR($C15="",P$4<$D15),0,INDEX('RAMP SCHEDULES'!$B$4:$M$13,MATCH($C15,'RAMP SCHEDULES'!$A$4:$A$13,0),MIN(12,P$4-$D15+1))*$E15) -> 32000 | ... T15: =IF(OR($C15="",T$4<$D15),0,INDEX('RAMP SCHEDULES'!$B$4:$M$13,MATCH($C15,'RAMP SCHEDULES'!$A$4:$A$13,0),MIN(12,T$4-$D15+1))*$E15) -> 40000 | U15: =IF(OR($C15="",U$4<$D15),0,INDEX('RAMP SCHEDULES'!$B$4:$M$13,MATCH($C15,'RAMP SCHEDULES'!$A$4:$A$13,0),MIN(12,U$4-$D15+1))*$F15) -> 0 | V15: =IF(OR($C15="",V$4<$D15),0,INDEX('RAMP SCHEDULES'!$B$4:$M$13,MATCH($C15,'RAMP SCHEDULES'!$A$4:$A$13,0),MIN(12,V$4-$D15+1))*$F15) -> 0 | W15: =IF(OR($C15="",W$4<$D15),0,INDEX('RAMP SCHEDULES'!$B$4:$M$13,MATCH($C15,'RAMP SCHEDULES'!$A$4:$A$13,0),MIN(12,W$4-$D15+1))*$F15) -> 0 | X15: =IF(OR($C15="",X$4<$D15),0,INDEX('RAMP SCHEDULES'!$B$4:$M$13,MATCH($C15,'RAMP SCHEDULES'!$A$4:$A$13,0),MIN(12,X$4-$D15+1))*$F15) -> 0 | Y15: =IF(OR($C15="",Y$4<$D15),0,INDEX('RAMP SCHEDULES'!$B$4:$M$13,MATCH($C15,'RAMP SCHEDULES'!$A$4:$A$13,0),MIN(12,Y$4-$D15+1))*$F15) -> 0 | Z15: =IF(OR($C15="",Z$4<$D15),0,INDEX('RAMP SCHEDULES'!$B$4:$M$13,MATCH($C15,'RAMP SCHEDULES'!$A$4:$A$13,0),MIN(12,Z$4-$D15+1))*$F15) -> 0 | AA15: =IF(OR($C15="",AA$4<$D15),0,INDEX('RAMP SCHEDULES'!$B$4:$M$13,MATCH($C15,'RAMP SCHEDULES'!$A$4:$A$13,0),MIN(12,AA$4-$D15+1))*$F15) -> 30000 | AB15: =IF(OR($C15="",AB$4<$D15),0,INDEX('RAMP SCHEDULES'!$B$4:$M$13,MATCH($C15,'RAMP SCHEDULES'!$A$4:$A$13,0),MIN(12,AB$4-$D15+1))*$F15) -> 40000 | ... AF15: =IF(OR($C15="",AF$4<$D15),0,INDEX('RAMP SCHEDULES'!$B$4:$M$13,MATCH($C15,'RAMP SCHEDULES'!$A$4:$A$13,0),MIN(12,AF$4-$D15+1))*$F15) -> 50000 | AG15: =SUM(I15:T15) -> 200000 | AH15: =SUM(U15:AF15) -> 250000 | AI15: =AG15*$G15 -> 5000 | AJ15: =AH15*$G15 -> 6250
A16: TBD | B16: Account Executive - RAMP | C16: NEW AE | D16: 6 | E16: 0.8 | F16: 1 | G16: 0.025 | H16: =IF($C16="",0,12*INDEX('RAMP SCHEDULES'!$B$4:$M$13,MATCH($C16,'RAMP SCHEDULES'!$A$4:$A$13,0),12)) -> 1000008 | I16: =IF(OR($C16="",I$4<$D16),0,INDEX('RAMP SCHEDULES'!$B$4:$M$13,MATCH($C16,'RAMP SCHEDULES'!$A$4:$A$13,0),MIN(12,I$4-$D16+1))*$E16) -> 0 | J16: =IF(OR($C16="",J$4<$D16),0,INDEX('RAMP SCHEDULES'!$B$4:$M$13,MATCH($C16,'RAMP SCHEDULES'!$A$4:$A$13,0),MIN(12,J$4-$D16+1))*$E16) -> 0 | K16: =IF(OR($C16="",K$4<$D16),0,INDEX('RAMP SCHEDULES'!$B$4:$M$13,MATCH($C16,'RAMP SCHEDULES'!$A$4:$A$13,0),MIN(12,K$4-$D16+1))*$E16) -> 0 | L16: =IF(OR($C16="",L$4<$D16),0,INDEX('RAMP SCHEDULES'!$B$4:$M$13,MATCH($C16,'RAMP SCHEDULES'!$A$4:$A$13,0),MIN(12,L$4-$D16+1))*$E16) -> 0 | M16: =IF(OR($C16="",M$4<$D16),0,INDEX('RAMP SCHEDULES'!$B$4:$M$13,MATCH($C16,'RAMP SCHEDULES'!$A$4:$A$13,0),MIN(12,M$4-$D16+1))*$E16) -> 0 | N16: =IF(OR($C16="",N$4<$D16),0,INDEX('RAMP SCHEDULES'!$B$4:$M$13,MATCH($C16,'RAMP SCHEDULES'!$A$4:$A$13,0),MIN(12,N$4-$D16+1))*$E16) -> 0 | O16: =IF(OR($C16="",O$4<$D16),0,INDEX('RAMP SCHEDULES'!$B$4:$M$13,MATCH($C16,'RAMP SCHEDULES'!$A$4:$A$13,0),MIN(12,O$4-$D16+1))*$E16) -> 24000 | P16: =IF(OR($C16="",P$4<$D16),0,INDEX('RAMP SCHEDULES'!$B$4:$M$13,MATCH($C16,'RAMP SCHEDULES'!$A$4:$A$13,0),MIN(12,P$4-$D16+1))*$E16) -> 32000 | ... T16: =IF(OR($C16="",T$4<$D16),0,INDEX('RAMP SCHEDULES'!$B$4:$M$13,MATCH($C16,'RAMP SCHEDULES'!$A$4:$A$13,0),MIN(12,T$4-$D16+1))*$E16) -> 40000 | U16: =IF(OR($C16="",U$4<$D16),0,INDEX('RAMP SCHEDULES'!$B$4:$M$13,MATCH($C16,'RAMP SCHEDULES'!$A$4:$A$13,0),MIN(12,U$4-$D16+1))*$F16) -> 0 | V16: =IF(OR($C16="",V$4<$D16),0,INDEX('RAMP SCHEDULES'!$B$4:$M$13,MATCH($C16,'RAMP SCHEDULES'!$A$4:$A$13,0),MIN(12,V$4-$D16+1))*$F16) -> 0 | W16: =IF(OR($C16="",W$4<$D16),0,INDEX('RAMP SCHEDULES'!$B$4:$M$13,MATCH($C16,'RAMP SCHEDULES'!$A$4:$A$13,0),MIN(12,W$4-$D16+1))*$F16) -> 0 | X16: =IF(OR($C16="",X$4<$D16),0,INDEX('RAMP SCHEDULES'!$B$4:$M$13,MATCH($C16,'RAMP SCHEDULES'!$A$4:$A$13,0),MIN(12,X$4-$D16+1))*$F16) -> 0 | Y16: =IF(OR($C16="",Y$4<$D16),0,INDEX('RAMP SCHEDULES'!$B$4:$M$13,MATCH($C16,'RAMP SCHEDULES'!$A$4:$A$13,0),MIN(12,Y$4-$D16+1))*$F16) -> 0 | Z16: =IF(OR($C16="",Z$4<$D16),0,INDEX('RAMP SCHEDULES'!$B$4:$M$13,MATCH($C16,'RAMP SCHEDULES'!$A$4:$A$13,0),MIN(12,Z$4-$D16+1))*$F16) -> 0 | AA16: =IF(OR($C16="",AA$4<$D16),0,INDEX('RAMP SCHEDULES'!$B$4:$M$13,MATCH($C16,'RAMP SCHEDULES'!$A$4:$A$13,0),MIN(12,AA$4-$D16+1))*$F16) -> 30000 | AB16: =IF(OR($C16="",AB$4<$D16),0,INDEX('RAMP SCHEDULES'!$B$4:$M$13,MATCH($C16,'RAMP SCHEDULES'!$A$4:$A$13,0),MIN(12,AB$4-$D16+1))*$F16) -> 40000 | ... AF16: =IF(OR($C16="",AF$4<$D16),0,INDEX('RAMP SCHEDULES'!$B$4:$M$13,MATCH($C16,'RAMP SCHEDULES'!$A$4:$A$13,0),MIN(12,AF$4-$D16+1))*$F16) -> 50000 | AG16: =SUM(I16:T16) -> 200000 | AH16: =SUM(U16:AF16) -> 250000 | AI16: =AG16*$G16 -> 5000 | AJ16: =AH16*$G16 -> 6250
A17: Coalter Wilson | B17: Account Manager - 55K Base | C17: NEW AM | D17: -8 | E17: 0.8 | F17: 1 | G17: 0.015 | H17: =IF($C17="",0,12*INDEX('RAMP SCHEDULES'!$B$4:$M$13,MATCH($C17,'RAMP SCHEDULES'!$A$4:$A$13,0),12)) -> 1200000 | I17: =IF(OR($C17="",I$4<$D17),0,INDEX('RAMP SCHEDULES'!$B$4:$M$13,MATCH($C17,'RAMP SCHEDULES'!$A$4:$A$13,0),MIN(12,I$4-$D17+1))*$E17) -> 80000 | J17: =IF(OR($C17="",J$4<$D17),0,INDEX('RAMP SCHEDULES'!$B$4:$M$13,MATCH($C17,'RAMP SCHEDULES'!$A$4:$A$13,0),MIN(12,J$4-$D17+1))*$E17) -> 80000 | K17: =IF(OR($C17="",K$4<$D17),0,INDEX('RAMP SCHEDULES'!$B$4:$M$13,MATCH($C17,'RAMP SCHEDULES'!$A$4:$A$13,0),MIN(12,K$4-$D17+1))*$E17) -> 80000 | L17: =IF(OR($C17="",L$4<$D17),0,INDEX('RAMP SCHEDULES'!$B$4:$M$13,MATCH($C17,'RAMP SCHEDULES'!$A$4:$A$13,0),MIN(12,L$4-$D17+1))*$E17) -> 80000 | M17: =IF(OR($C17="",M$4<$D17),0,INDEX('RAMP SCHEDULES'!$B$4:$M$13,MATCH($C17,'RAMP SCHEDULES'!$A$4:$A$13,0),MIN(12,M$4-$D17+1))*$E17) -> 80000 | N17: =IF(OR($C17="",N$4<$D17),0,INDEX('RAMP SCHEDULES'!$B$4:$M$13,MATCH($C17,'RAMP SCHEDULES'!$A$4:$A$13,0),MIN(12,N$4-$D17+1))*$E17) -> 80000 | O17: =IF(OR($C17="",O$4<$D17),0,INDEX('RAMP SCHEDULES'!$B$4:$M$13,MATCH($C17,'RAMP SCHEDULES'!$A$4:$A$13,0),MIN(12,O$4-$D17+1))*$E17) -> 80000 | P17: =IF(OR($C17="",P$4<$D17),0,INDEX('RAMP SCHEDULES'!$B$4:$M$13,MATCH($C17,'RAMP SCHEDULES'!$A$4:$A$13,0),MIN(12,P$4-$D17+1))*$E17) -> 80000 | ... T17: =IF(OR($C17="",T$4<$D17),0,INDEX('RAMP SCHEDULES'!$B$4:$M$13,MATCH($C17,'RAMP SCHEDULES'!$A$4:$A$13,0),MIN(12,T$4-$D17+1))*$E17) -> 80000 | U17: =IF(OR($C17="",U$4<$D17),0,INDEX('RAMP SCHEDULES'!$B$4:$M$13,MATCH($C17,'RAMP SCHEDULES'!$A$4:$A$13,0),MIN(12,U$4-$D17+1))*$F17) -> 100000 | V17: =IF(OR($C17="",V$4<$D17),0,INDEX('RAMP SCHEDULES'!$B$4:$M$13,MATCH($C17,'RAMP SCHEDULES'!$A$4:$A$13,0),MIN(12,V$4-$D17+1))*$F17) -> 100000 | W17: =IF(OR($C17="",W$4<$D17),0,INDEX('RAMP SCHEDULES'!$B$4:$M$13,MATCH($C17,'RAMP SCHEDULES'!$A$4:$A$13,0),MIN(12,W$4-$D17+1))*$F17) -> 100000 | X17: =IF(OR($C17="",X$4<$D17),0,INDEX('RAMP SCHEDULES'!$B$4:$M$13,MATCH($C17,'RAMP SCHEDULES'!$A$4:$A$13,0),MIN(12,X$4-$D17+1))*$F17) -> 100000 | Y17: =IF(OR($C17="",Y$4<$D17),0,INDEX('RAMP SCHEDULES'!$B$4:$M$13,MATCH($C17,'RAMP SCHEDULES'!$A$4:$A$13,0),MIN(12,Y$4-$D17+1))*$F17) -> 100000 | Z17: =IF(OR($C17="",Z$4<$D17),0,INDEX('RAMP SCHEDULES'!$B$4:$M$13,MATCH($C17,'RAMP SCHEDULES'!$A$4:$A$13,0),MIN(12,Z$4-$D17+1))*$F17) -> 100000 | AA17: =IF(OR($C17="",AA$4<$D17),0,INDEX('RAMP SCHEDULES'!$B$4:$M$13,MATCH($C17,'RAMP SCHEDULES'!$A$4:$A$13,0),MIN(12,AA$4-$D17+1))*$F17) -> 100000 | AB17: =IF(OR($C17="",AB$4<$D17),0,INDEX('RAMP SCHEDULES'!$B$4:$M$13,MATCH($C17,'RAMP SCHEDULES'!$A$4:$A$13,0),MIN(12,AB$4-$D17+1))*$F17) -> 100000 | ... AF17: =IF(OR($C17="",AF$4<$D17),0,INDEX('RAMP SCHEDULES'!$B$4:$M$13,MATCH($C17,'RAMP SCHEDULES'!$A$4:$A$13,0),MIN(12,AF$4-$D17+1))*$F17) -> 100000 | AG17: =SUM(I17:T17) -> 960000 | AH17: =SUM(U17:AF17) -> 1200000 | AI17: =AG17*$G17 -> 14400 | AJ17: =AH17*$G17 -> 18000
... A21: MARKETING | B21: MARKETING | C21: MARKETING | D21: -8 | E21: 0.8 | F21: 1 | G21: 0 | H21: =IF($C21="",0,12*INDEX('RAMP SCHEDULES'!$B$4:$M$13,MATCH($C21,'RAMP SCHEDULES'!$A$4:$A$13,0),12)) -> 480000 | I21: =IF(OR($C21="",I$4<$D21),0,INDEX('RAMP SCHEDULES'!$B$4:$M$13,MATCH($C21,'RAMP SCHEDULES'!$A$4:$A$13,0),MIN(12,I$4-$D21+1))*$E21) -> 32000 | J21: =IF(OR($C21="",J$4<$D21),0,INDEX('RAMP SCHEDULES'!$B$4:$M$13,MATCH($C21,'RAMP SCHEDULES'!$A$4:$A$13,0),MIN(12,J$4-$D21+1))*$E21) -> 32000 | K21: =IF(OR($C21="",K$4<$D21),0,INDEX('RAMP SCHEDULES'!$B$4:$M$13,MATCH($C21,'RAMP SCHEDULES'!$A$4:$A$13,0),MIN(12,K$4-$D21+1))*$E21) -> 32000 | L21: =IF(OR($C21="",L$4<$D21),0,INDEX('RAMP SCHEDULES'!$B$4:$M$13,MATCH($C21,'RAMP SCHEDULES'!$A$4:$A$13,0),MIN(12,L$4-$D21+1))*$E21) -> 32000 | M21: =IF(OR($C21="",M$4<$D21),0,INDEX('RAMP SCHEDULES'!$B$4:$M$13,MATCH($C21,'RAMP SCHEDULES'!$A$4:$A$13,0),MIN(12,M$4-$D21+1))*$E21) -> 32000 | N21: =IF(OR($C21="",N$4<$D21),0,INDEX('RAMP SCHEDULES'!$B$4:$M$13,MATCH($C21,'RAMP SCHEDULES'!$A$4:$A$13,0),MIN(12,N$4-$D21+1))*$E21) -> 32000 | O21: =IF(OR($C21="",O$4<$D21),0,INDEX('RAMP SCHEDULES'!$B$4:$M$13,MATCH($C21,'RAMP SCHEDULES'!$A$4:$A$13,0),MIN(12,O$4-$D21+1))*$E21) -> 32000 | P21: =IF(OR($C21="",P$4<$D21),0,INDEX('RAMP SCHEDULES'!$B$4:$M$13,MATCH($C21,'RAMP SCHEDULES'!$A$4:$A$13,0),MIN(12,P$4-$D21+1))*$E21) -> 32000 | ... T21: =IF(OR($C21="",T$4<$D21),0,INDEX('RAMP SCHEDULES'!$B$4:$M$13,MATCH($C21,'RAMP SCHEDULES'!$A$4:$A$13,0),MIN(12,T$4-$D21+1))*$E21) -> 32000 | U21: =IF(OR($C21="",U$4<$D21),0,INDEX('RAMP SCHEDULES'!$B$4:$M$13,MATCH($C21,'RAMP SCHEDULES'!$A$4:$A$13,0),MIN(12,U$4-$D21+1))*$F21) -> 40000 | V21: =IF(OR($C21="",V$4<$D21),0,INDEX('RAMP SCHEDULES'!$B$4:$M$13,MATCH($C21,'RAMP SCHEDULES'!$A$4:$A$13,0),MIN(12,V$4-$D21+1))*$F21) -> 40000 | W21: =IF(OR($C21="",W$4<$D21),0,INDEX('RAMP SCHEDULES'!$B$4:$M$13,MATCH($C21,'RAMP SCHEDULES'!$A$4:$A$13,0),MIN(12,W$4-$D21+1))*$F21) -> 40000 | X21: =IF(OR($C21="",X$4<$D21),0,INDEX('RAMP SCHEDULES'!$B$4:$M$13,MATCH($C21,'RAMP SCHEDULES'!$A$4:$A$13,0),MIN(12,X$4-$D21+1))*$F21) -> 40000 | Y21: =IF(OR($C21="",Y$4<$D21),0,INDEX('RAMP SCHEDULES'!$B$4:$M$13,MATCH($C21,'RAMP SCHEDULES'!$A$4:$A$13,0),MIN(12,Y$4-$D21+1))*$F21) -> 40000 | Z21: =IF(OR($C21="",Z$4<$D21),0,INDEX('RAMP SCHEDULES'!$B$4:$M$13,MATCH($C21,'RAMP SCHEDULES'!$A$4:$A$13,0),MIN(12,Z$4-$D21+1))*$F21) -> 40000 | AA21: =IF(OR($C21="",AA$4<$D21),0,INDEX('RAMP SCHEDULES'!$B$4:$M$13,MATCH($C21,'RAMP SCHEDULES'!$A$4:$A$13,0),MIN(12,AA$4-$D21+1))*$F21) -> 40000 | AB21: =IF(OR($C21="",AB$4<$D21),0,INDEX('RAMP SCHEDULES'!$B$4:$M$13,MATCH($C21,'RAMP SCHEDULES'!$A$4:$A$13,0),MIN(12,AB$4-$D21+1))*$F21) -> 40000 | ... AF21: =IF(OR($C21="",AF$4<$D21),0,INDEX('RAMP SCHEDULES'!$B$4:$M$13,MATCH($C21,'RAMP SCHEDULES'!$A$4:$A$13,0),MIN(12,AF$4-$D21+1))*$F21) -> 40000 | AG21: =SUM(I21:T21) -> 384000 | AH21: =SUM(U21:AF21) -> 480000 | AI21: =AG21*$G21 -> 0 | AJ21: =AH21*$G21 -> 0
H22: =IF($C22="",0,12*INDEX('RAMP SCHEDULES'!$B$4:$M$13,MATCH($C22,'RAMP SCHEDULES'!$A$4:$A$13,0),12)) -> 0 | I22: =IF(OR($C22="",I$4<$D22),0,INDEX('RAMP SCHEDULES'!$B$4:$M$13,MATCH($C22,'RAMP SCHEDULES'!$A$4:$A$13,0),MIN(12,I$4-$D22+1))*$E22) -> 0 | J22: =IF(OR($C22="",J$4<$D22),0,INDEX('RAMP SCHEDULES'!$B$4:$M$13,MATCH($C22,'RAMP SCHEDULES'!$A$4:$A$13,0),MIN(12,J$4-$D22+1))*$E22) -> 0 | K22: =IF(OR($C22="",K$4<$D22),0,INDEX('RAMP SCHEDULES'!$B$4:$M$13,MATCH($C22,'RAMP SCHEDULES'!$A$4:$A$13,0),MIN(12,K$4-$D22+1))*$E22) -> 0 | L22: =IF(OR($C22="",L$4<$D22),0,INDEX('RAMP SCHEDULES'!$B$4:$M$13,MATCH($C22,'RAMP SCHEDULES'!$A$4:$A$13,0),MIN(12,L$4-$D22+1))*$E22) -> 0 | M22: =IF(OR($C22="",M$4<$D22),0,INDEX('RAMP SCHEDULES'!$B$4:$M$13,MATCH($C22,'RAMP SCHEDULES'!$A$4:$A$13,0),MIN(12,M$4-$D22+1))*$E22) -> 0 | N22: =IF(OR($C22="",N$4<$D22),0,INDEX('RAMP SCHEDULES'!$B$4:$M$13,MATCH($C22,'RAMP SCHEDULES'!$A$4:$A$13,0),MIN(12,N$4-$D22+1))*$E22) -> 0 | O22: =IF(OR($C22="",O$4<$D22),0,INDEX('RAMP SCHEDULES'!$B$4:$M$13,MATCH($C22,'RAMP SCHEDULES'!$A$4:$A$13,0),MIN(12,O$4-$D22+1))*$E22) -> 0 | P22: =IF(OR($C22="",P$4<$D22),0,INDEX('RAMP SCHEDULES'!$B$4:$M$13,MATCH($C22,'RAMP SCHEDULES'!$A$4:$A$13,0),MIN(12,P$4-$D22+1))*$E22) -> 0 | ... T22: =IF(OR($C22="",T$4<$D22),0,INDEX('RAMP SCHEDULES'!$B$4:$M$13,MATCH($C22,'RAMP SCHEDULES'!$A$4:$A$13,0),MIN(12,T$4-$D22+1))*$E22) -> 0 | U22: =IF(OR($C22="",U$4<$D22),0,INDEX('RAMP SCHEDULES'!$B$4:$M$13,MATCH($C22,'RAMP SCHEDULES'!$A$4:$A$13,0),MIN(12,U$4-$D22+1))*$F22) -> 0 | V22: =IF(OR($C22="",V$4<$D22),0,INDEX('RAMP SCHEDULES'!$B$4:$M$13,MATCH($C22,'RAMP SCHEDULES'!$A$4:$A$13,0),MIN(12,V$4-$D22+1))*$F22) -> 0 | W22: =IF(OR($C22="",W$4<$D22),0,INDEX('RAMP SCHEDULES'!$B$4:$M$13,MATCH($C22,'RAMP SCHEDULES'!$A$4:$A$13,0),MIN(12,W$4-$D22+1))*$F22) -> 0 | X22: =IF(OR($C22="",X$4<$D22),0,INDEX('RAMP SCHEDULES'!$B$4:$M$13,MATCH($C22,'RAMP SCHEDULES'!$A$4:$A$13,0),MIN(12,X$4-$D22+1))*$F22) -> 0 | Y22: =IF(OR($C22="",Y$4<$D22),0,INDEX('RAMP SCHEDULES'!$B$4:$M$13,MATCH($C22,'RAMP SCHEDULES'!$A$4:$A$13,0),MIN(12,Y$4-$D22+1))*$F22) -> 0 | Z22: =IF(OR($C22="",Z$4<$D22),0,INDEX('RAMP SCHEDULES'!$B$4:$M$13,MATCH($C22,'RAMP SCHEDULES'!$A$4:$A$13,0),MIN(12,Z$4-$D22+1))*$F22) -> 0 | AA22: =IF(OR($C22="",AA$4<$D22),0,INDEX('RAMP SCHEDULES'!$B$4:$M$13,MATCH($C22,'RAMP SCHEDULES'!$A$4:$A$13,0),MIN(12,AA$4-$D22+1))*$F22) -> 0 | AB22: =IF(OR($C22="",AB$4<$D22),0,INDEX('RAMP SCHEDULES'!$B$4:$M$13,MATCH($C22,'RAMP SCHEDULES'!$A$4:$A$13,0),MIN(12,AB$4-$D22+1))*$F22) -> 0 | ... AF22: =IF(OR($C22="",AF$4<$D22),0,INDEX('RAMP SCHEDULES'!$B$4:$M$13,MATCH($C22,'RAMP SCHEDULES'!$A$4:$A$13,0),MIN(12,AF$4-$D22+1))*$F22) -> 0 | AG22: =SUM(I22:T22) -> 0 | AH22: =SUM(U22:AF22) -> 0 | AI22: =AG22*$G22 -> 0 | AJ22: =AH22*$G22 -> 0
H23: =IF($C23="",0,12*INDEX('RAMP SCHEDULES'!$B$4:$M$13,MATCH($C23,'RAMP SCHEDULES'!$A$4:$A$13,0),12)) -> 0 | I23: =IF(OR($C23="",I$4<$D23),0,INDEX('RAMP SCHEDULES'!$B$4:$M$13,MATCH($C23,'RAMP SCHEDULES'!$A$4:$A$13,0),MIN(12,I$4-$D23+1))*$E23) -> 0 | J23: =IF(OR($C23="",J$4<$D23),0,INDEX('RAMP SCHEDULES'!$B$4:$M$13,MATCH($C23,'RAMP SCHEDULES'!$A$4:$A$13,0),MIN(12,J$4-$D23+1))*$E23) -> 0 | K23: =IF(OR($C23="",K$4<$D23),0,INDEX('RAMP SCHEDULES'!$B$4:$M$13,MATCH($C23,'RAMP SCHEDULES'!$A$4:$A$13,0),MIN(12,K$4-$D23+1))*$E23) -> 0 | L23: =IF(OR($C23="",L$4<$D23),0,INDEX('RAMP SCHEDULES'!$B$4:$M$13,MATCH($C23,'RAMP SCHEDULES'!$A$4:$A$13,0),MIN(12,L$4-$D23+1))*$E23) -> 0 | M23: =IF(OR($C23="",M$4<$D23),0,INDEX('RAMP SCHEDULES'!$B$4:$M$13,MATCH($C23,'RAMP SCHEDULES'!$A$4:$A$13,0),MIN(12,M$4-$D23+1))*$E23) -> 0 | N23: =IF(OR($C23="",N$4<$D23),0,INDEX('RAMP SCHEDULES'!$B$4:$M$13,MATCH($C23,'RAMP SCHEDULES'!$A$4:$A$13,0),MIN(12,N$4-$D23+1))*$E23) -> 0 | O23: =IF(OR($C23="",O$4<$D23),0,INDEX('RAMP SCHEDULES'!$B$4:$M$13,MATCH($C23,'RAMP SCHEDULES'!$A$4:$A$13,0),MIN(12,O$4-$D23+1))*$E23) -> 0 | P23: =IF(OR($C23="",P$4<$D23),0,INDEX('RAMP SCHEDULES'!$B$4:$M$13,MATCH($C23,'RAMP SCHEDULES'!$A$4:$A$13,0),MIN(12,P$4-$D23+1))*$E23) -> 0 | ... T23: =IF(OR($C23="",T$4<$D23),0,INDEX('RAMP SCHEDULES'!$B$4:$M$13,MATCH($C23,'RAMP SCHEDULES'!$A$4:$A$13,0),MIN(12,T$4-$D23+1))*$E23) -> 0 | U23: =IF(OR($C23="",U$4<$D23),0,INDEX('RAMP SCHEDULES'!$B$4:$M$13,MATCH($C23,'RAMP SCHEDULES'!$A$4:$A$13,0),MIN(12,U$4-$D23+1))*$F23) -> 0 | V23: =IF(OR($C23="",V$4<$D23),0,INDEX('RAMP SCHEDULES'!$B$4:$M$13,MATCH($C23,'RAMP SCHEDULES'!$A$4:$A$13,0),MIN(12,V$4-$D23+1))*$F23) -> 0 | W23: =IF(OR($C23="",W$4<$D23),0,INDEX('RAMP SCHEDULES'!$B$4:$M$13,MATCH($C23,'RAMP SCHEDULES'!$A$4:$A$13,0),MIN(12,W$4-$D23+1))*$F23) -> 0 | X23: =IF(OR($C23="",X$4<$D23),0,INDEX('RAMP SCHEDULES'!$B$4:$M$13,MATCH($C23,'RAMP SCHEDULES'!$A$4:$A$13,0),MIN(12,X$4-$D23+1))*$F23) -> 0 | Y23: =IF(OR($C23="",Y$4<$D23),0,INDEX('RAMP SCHEDULES'!$B$4:$M$13,MATCH($C23,'RAMP SCHEDULES'!$A$4:$A$13,0),MIN(12,Y$4-$D23+1))*$F23) -> 0 | Z23: =IF(OR($C23="",Z$4<$D23),0,INDEX('RAMP SCHEDULES'!$B$4:$M$13,MATCH($C23,'RAMP SCHEDULES'!$A$4:$A$13,0),MIN(12,Z$4-$D23+1))*$F23) -> 0 | AA23: =IF(OR($C23="",AA$4<$D23),0,INDEX('RAMP SCHEDULES'!$B$4:$M$13,MATCH($C23,'RAMP SCHEDULES'!$A$4:$A$13,0),MIN(12,AA$4-$D23+1))*$F23) -> 0 | AB23: =IF(OR($C23="",AB$4<$D23),0,INDEX('RAMP SCHEDULES'!$B$4:$M$13,MATCH($C23,'RAMP SCHEDULES'!$A$4:$A$13,0),MIN(12,AB$4-$D23+1))*$F23) -> 0 | ... AF23: =IF(OR($C23="",AF$4<$D23),0,INDEX('RAMP SCHEDULES'!$B$4:$M$13,MATCH($C23,'RAMP SCHEDULES'!$A$4:$A$13,0),MIN(12,AF$4-$D23+1))*$F23) -> 0 | AG23: =SUM(I23:T23) -> 0 | AH23: =SUM(U23:AF23) -> 0 | AI23: =AG23*$G23 -> 0 | AJ23: =AH23*$G23 -> 0
H24: =IF($C24="",0,12*INDEX('RAMP SCHEDULES'!$B$4:$M$13,MATCH($C24,'RAMP SCHEDULES'!$A$4:$A$13,0),12)) -> 0 | I24: =IF(OR($C24="",I$4<$D24),0,INDEX('RAMP SCHEDULES'!$B$4:$M$13,MATCH($C24,'RAMP SCHEDULES'!$A$4:$A$13,0),MIN(12,I$4-$D24+1))*$E24) -> 0 | J24: =IF(OR($C24="",J$4<$D24),0,INDEX('RAMP SCHEDULES'!$B$4:$M$13,MATCH($C24,'RAMP SCHEDULES'!$A$4:$A$13,0),MIN(12,J$4-$D24+1))*$E24) -> 0 | K24: =IF(OR($C24="",K$4<$D24),0,INDEX('RAMP SCHEDULES'!$B$4:$M$13,MATCH($C24,'RAMP SCHEDULES'!$A$4:$A$13,0),MIN(12,K$4-$D24+1))*$E24) -> 0 | L24: =IF(OR($C24="",L$4<$D24),0,INDEX('RAMP SCHEDULES'!$B$4:$M$13,MATCH($C24,'RAMP SCHEDULES'!$A$4:$A$13,0),MIN(12,L$4-$D24+1))*$E24) -> 0 | M24: =IF(OR($C24="",M$4<$D24),0,INDEX('RAMP SCHEDULES'!$B$4:$M$13,MATCH($C24,'RAMP SCHEDULES'!$A$4:$A$13,0),MIN(12,M$4-$D24+1))*$E24) -> 0 | N24: =IF(OR($C24="",N$4<$D24),0,INDEX('RAMP SCHEDULES'!$B$4:$M$13,MATCH($C24,'RAMP SCHEDULES'!$A$4:$A$13,0),MIN(12,N$4-$D24+1))*$E24) -> 0 | O24: =IF(OR($C24="",O$4<$D24),0,INDEX('RAMP SCHEDULES'!$B$4:$M$13,MATCH($C24,'RAMP SCHEDULES'!$A$4:$A$13,0),MIN(12,O$4-$D24+1))*$E24) -> 0 | P24: =IF(OR($C24="",P$4<$D24),0,INDEX('RAMP SCHEDULES'!$B$4:$M$13,MATCH($C24,'RAMP SCHEDULES'!$A$4:$A$13,0),MIN(12,P$4-$D24+1))*$E24) -> 0 | ... T24: =IF(OR($C24="",T$4<$D24),0,INDEX('RAMP SCHEDULES'!$B$4:$M$13,MATCH($C24,'RAMP SCHEDULES'!$A$4:$A$13,0),MIN(12,T$4-$D24+1))*$E24) -> 0 | U24: =IF(OR($C24="",U$4<$D24),0,INDEX('RAMP SCHEDULES'!$B$4:$M$13,MATCH($C24,'RAMP SCHEDULES'!$A$4:$A$13,0),MIN(12,U$4-$D24+1))*$F24) -> 0 | V24: =IF(OR($C24="",V$4<$D24),0,INDEX('RAMP SCHEDULES'!$B$4:$M$13,MATCH($C24,'RAMP SCHEDULES'!$A$4:$A$13,0),MIN(12,V$4-$D24+1))*$F24) -> 0 | W24: =IF(OR($C24="",W$4<$D24),0,INDEX('RAMP SCHEDULES'!$B$4:$M$13,MATCH($C24,'RAMP SCHEDULES'!$A$4:$A$13,0),MIN(12,W$4-$D24+1))*$F24) -> 0 | X24: =IF(OR($C24="",X$4<$D24),0,INDEX('RAMP SCHEDULES'!$B$4:$M$13,MATCH($C24,'RAMP SCHEDULES'!$A$4:$A$13,0),MIN(12,X$4-$D24+1))*$F24) -> 0 | Y24: =IF(OR($C24="",Y$4<$D24),0,INDEX('RAMP SCHEDULES'!$B$4:$M$13,MATCH($C24,'RAMP SCHEDULES'!$A$4:$A$13,0),MIN(12,Y$4-$D24+1))*$F24) -> 0 | Z24: =IF(OR($C24="",Z$4<$D24),0,INDEX('RAMP SCHEDULES'!$B$4:$M$13,MATCH($C24,'RAMP SCHEDULES'!$A$4:$A$13,0),MIN(12,Z$4-$D24+1))*$F24) -> 0 | AA24: =IF(OR($C24="",AA$4<$D24),0,INDEX('RAMP SCHEDULES'!$B$4:$M$13,MATCH($C24,'RAMP SCHEDULES'!$A$4:$A$13,0),MIN(12,AA$4-$D24+1))*$F24) -> 0 | AB24: =IF(OR($C24="",AB$4<$D24),0,INDEX('RAMP SCHEDULES'!$B$4:$M$13,MATCH($C24,'RAMP SCHEDULES'!$A$4:$A$13,0),MIN(12,AB$4-$D24+1))*$F24) -> 0 | ... AF24: =IF(OR($C24="",AF$4<$D24),0,INDEX('RAMP SCHEDULES'!$B$4:$M$13,MATCH($C24,'RAMP SCHEDULES'!$A$4:$A$13,0),MIN(12,AF$4-$D24+1))*$F24) -> 0 | AG24: =SUM(I24:T24) -> 0 | AH24: =SUM(U24:AF24) -> 0 | AI24: =AG24*$G24 -> 0 | AJ24: =AH24*$G24 -> 0
H25: =IF($C25="",0,12*INDEX('RAMP SCHEDULES'!$B$4:$M$13,MATCH($C25,'RAMP SCHEDULES'!$A$4:$A$13,0),12)) -> 0 | I25: =IF(OR($C25="",I$4<$D25),0,INDEX('RAMP SCHEDULES'!$B$4:$M$13,MATCH($C25,'RAMP SCHEDULES'!$A$4:$A$13,0),MIN(12,I$4-$D25+1))*$E25) -> 0 | J25: =IF(OR($C25="",J$4<$D25),0,INDEX('RAMP SCHEDULES'!$B$4:$M$13,MATCH($C25,'RAMP SCHEDULES'!$A$4:$A$13,0),MIN(12,J$4-$D25+1))*$E25) -> 0 | K25: =IF(OR($C25="",K$4<$D25),0,INDEX('RAMP SCHEDULES'!$B$4:$M$13,MATCH($C25,'RAMP SCHEDULES'!$A$4:$A$13,0),MIN(12,K$4-$D25+1))*$E25) -> 0 | L25: =IF(OR($C25="",L$4<$D25),0,INDEX('RAMP SCHEDULES'!$B$4:$M$13,MATCH($C25,'RAMP SCHEDULES'!$A$4:$A$13,0),MIN(12,L$4-$D25+1))*$E25) -> 0 | M25: =IF(OR($C25="",M$4<$D25),0,INDEX('RAMP SCHEDULES'!$B$4:$M$13,MATCH($C25,'RAMP SCHEDULES'!$A$4:$A$13,0),MIN(12,M$4-$D25+1))*$E25) -> 0 | N25: =IF(OR($C25="",N$4<$D25),0,INDEX('RAMP SCHEDULES'!$B$4:$M$13,MATCH($C25,'RAMP SCHEDULES'!$A$4:$A$13,0),MIN(12,N$4-$D25+1))*$E25) -> 0 | O25: =IF(OR($C25="",O$4<$D25),0,INDEX('RAMP SCHEDULES'!$B$4:$M$13,MATCH($C25,'RAMP SCHEDULES'!$A$4:$A$13,0),MIN(12,O$4-$D25+1))*$E25) -> 0 | P25: =IF(OR($C25="",P$4<$D25),0,INDEX('RAMP SCHEDULES'!$B$4:$M$13,MATCH($C25,'RAMP SCHEDULES'!$A$4:$A$13,0),MIN(12,P$4-$D25+1))*$E25) -> 0 | ... T25: =IF(OR($C25="",T$4<$D25),0,INDEX('RAMP SCHEDULES'!$B$4:$M$13,MATCH($C25,'RAMP SCHEDULES'!$A$4:$A$13,0),MIN(12,T$4-$D25+1))*$E25) -> 0 | U25: =IF(OR($C25="",U$4<$D25),0,INDEX('RAMP SCHEDULES'!$B$4:$M$13,MATCH($C25,'RAMP SCHEDULES'!$A$4:$A$13,0),MIN(12,U$4-$D25+1))*$F25) -> 0 | V25: =IF(OR($C25="",V$4<$D25),0,INDEX('RAMP SCHEDULES'!$B$4:$M$13,MATCH($C25,'RAMP SCHEDULES'!$A$4:$A$13,0),MIN(12,V$4-$D25+1))*$F25) -> 0 | W25: =IF(OR($C25="",W$4<$D25),0,INDEX('RAMP SCHEDULES'!$B$4:$M$13,MATCH($C25,'RAMP SCHEDULES'!$A$4:$A$13,0),MIN(12,W$4-$D25+1))*$F25) -> 0 | X25: =IF(OR($C25="",X$4<$D25),0,INDEX('RAMP SCHEDULES'!$B$4:$M$13,MATCH($C25,'RAMP SCHEDULES'!$A$4:$A$13,0),MIN(12,X$4-$D25+1))*$F25) -> 0 | Y25: =IF(OR($C25="",Y$4<$D25),0,INDEX('RAMP SCHEDULES'!$B$4:$M$13,MATCH($C25,'RAMP SCHEDULES'!$A$4:$A$13,0),MIN(12,Y$4-$D25+1))*$F25) -> 0 | Z25: =IF(OR($C25="",Z$4<$D25),0,INDEX('RAMP SCHEDULES'!$B$4:$M$13,MATCH($C25,'RAMP SCHEDULES'!$A$4:$A$13,0),MIN(12,Z$4-$D25+1))*$F25) -> 0 | AA25: =IF(OR($C25="",AA$4<$D25),0,INDEX('RAMP SCHEDULES'!$B$4:$M$13,MATCH($C25,'RAMP SCHEDULES'!$A$4:$A$13,0),MIN(12,AA$4-$D25+1))*$F25) -> 0 | AB25: =IF(OR($C25="",AB$4<$D25),0,INDEX('RAMP SCHEDULES'!$B$4:$M$13,MATCH($C25,'RAMP SCHEDULES'!$A$4:$A$13,0),MIN(12,AB$4-$D25+1))*$F25) -> 0 | ... AF25: =IF(OR($C25="",AF$4<$D25),0,INDEX('RAMP SCHEDULES'!$B$4:$M$13,MATCH($C25,'RAMP SCHEDULES'!$A$4:$A$13,0),MIN(12,AF$4-$D25+1))*$F25) -> 0 | AG25: =SUM(I25:T25) -> 0 | AH25: =SUM(U25:AF25) -> 0 | AI25: =AG25*$G25 -> 0 | AJ25: =AH25*$G25 -> 0
A26: TEAM REVENUE — MODEST | I26: =SUM(I6:I25) -> 937199.2 | J26: =SUM(J6:J25) -> 941199.2 | K26: =SUM(K6:K25) -> 953201.6 | L26: =SUM(L6:L25) -> 1013201.6 | M26: =SUM(M6:M25) -> 1047868 | N26: =SUM(N6:N25) -> 1055868 | O26: =SUM(O6:O25) -> 1135868.8 | P26: =SUM(P6:P25) -> 1173201.6 | ... T26: =SUM(T6:T25) -> 1250536 | AG26: =SUM(I26:T26) -> 13107752
A27: TEAM REVENUE — STRETCH | I27: =SUM(U6:U25) -> 1088999 | J27: =SUM(V6:V25) -> 1093999 | K27: =SUM(W6:W25) -> 1109002 | L27: =SUM(X6:X25) -> 1184002 | M27: =SUM(Y6:Y25) -> 1227335 | N27: =SUM(Z6:Z25) -> 1237335 | O27: =SUM(AA6:AA25) -> 1337336 | P27: =SUM(AB6:AB25) -> 1384002 | ... T27: =SUM(AF6:AF25) -> 1480670 | AG27: =SUM(I27:T27) -> 15394690
A28: Rep commissions — modest | I28: =SUMPRODUCT($G$6:$G$25,I$6:I$25) -> 16874.98 | J28: =SUMPRODUCT($G$6:$G$25,J$6:J$25) -> 16974.98 | K28: =SUMPRODUCT($G$6:$G$25,K$6:K$25) -> 17275.04 | L28: =SUMPRODUCT($G$6:$G$25,L$6:L$25) -> 18775.04 | M28: =SUMPRODUCT($G$6:$G$25,M$6:M$25) -> 19641.7 | N28: =SUMPRODUCT($G$6:$G$25,N$6:N$25) -> 19841.7 | O28: =SUMPRODUCT($G$6:$G$25,O$6:O$25) -> 21841.72 | P28: =SUMPRODUCT($G$6:$G$25,P$6:P$25) -> 22775.04 | ... T28: =SUMPRODUCT($G$6:$G$25,T$6:T$25) -> 24708.4 | AG28: =SUM(I28:T28) -> 249033.8
A29: Rep commissions — stretch | I29: =SUMPRODUCT($G$6:$G$25,U$6:U$25) -> 19649.975 | J29: =SUMPRODUCT($G$6:$G$25,V$6:V$25) -> 19774.975 | K29: =SUMPRODUCT($G$6:$G$25,W$6:W$25) -> 20150.05 | L29: =SUMPRODUCT($G$6:$G$25,X$6:X$25) -> 22025.05 | M29: =SUMPRODUCT($G$6:$G$25,Y$6:Y$25) -> 23108.375 | N29: =SUMPRODUCT($G$6:$G$25,Z$6:Z$25) -> 23358.375 | O29: =SUMPRODUCT($G$6:$G$25,AA$6:AA$25) -> 25858.4 | P29: =SUMPRODUCT($G$6:$G$25,AB$6:AB$25) -> 27025.05 | ... T29: =SUMPRODUCT($G$6:$G$25,AF$6:AF$25) -> 29441.75 | AG29: =SUM(I29:T29) -> 293967.25
A30: Sales Manager override — modest | I30: =$E$3*I$26 -> 14057.988 | J30: =$E$3*J$26 -> 14117.988 | K30: =$E$3*K$26 -> 14298.024 | L30: =$E$3*L$26 -> 15198.024 | M30: =$E$3*M$26 -> 15718.02 | N30: =$E$3*N$26 -> 15838.02 | O30: =$E$3*O$26 -> 17038.032 | P30: =$E$3*P$26 -> 17598.024 | ... T30: =$E$3*T$26 -> 18758.04 | AG30: =SUM(I30:T30) -> 196616.28
A31: Sales Manager override — stretch | I31: =$E$3*I$27 -> 16334.985 | J31: =$E$3*J$27 -> 16409.985 | K31: =$E$3*K$27 -> 16635.03 | L31: =$E$3*L$27 -> 17760.03 | M31: =$E$3*M$27 -> 18410.025 | N31: =$E$3*N$27 -> 18560.025 | O31: =$E$3*O$27 -> 20060.04 | P31: =$E$3*P$27 -> 20760.03 | ... T31: =$E$3*T$27 -> 22210.05 | AG31: =SUM(I31:T31) -> 230920.35
A32: Director override — modest (above target) | I32: =$H$3*MAX(0,I$26-$K$3) -> 0 | J32: =$H$3*MAX(0,J$26-$K$3) -> 0 | K32: =$H$3*MAX(0,K$26-$K$3) -> 0 | L32: =$H$3*MAX(0,L$26-$K$3) -> 316.22267 | M32: =$H$3*MAX(0,M$26-$K$3) -> 1529.5467 | N32: =$H$3*MAX(0,N$26-$K$3) -> 1809.5467 | O32: =$H$3*MAX(0,O$26-$K$3) -> 4609.5747 | P32: =$H$3*MAX(0,P$26-$K$3) -> 5916.2227 | ... T32: =$H$3*MAX(0,T$26-$K$3) -> 8622.9267 | AG32: =SUM(I32:T32) -> 43352.82
A33: Director override — stretch (above target) | I33: =$H$3*MAX(0,I$27-$K$3) -> 2969.1317 | J33: =$H$3*MAX(0,J$27-$K$3) -> 3144.1317 | K33: =$H$3*MAX(0,K$27-$K$3) -> 3669.2367 | L33: =$H$3*MAX(0,L$27-$K$3) -> 6294.2367 | M33: =$H$3*MAX(0,M$27-$K$3) -> 7810.8917 | N33: =$H$3*MAX(0,N$27-$K$3) -> 8160.8917 | O33: =$H$3*MAX(0,O$27-$K$3) -> 11660.927 | P33: =$H$3*MAX(0,P$27-$K$3) -> 13294.237 | ... T33: =$H$3*MAX(0,T$27-$K$3) -> 16677.617 | AG33: =SUM(I33:T33) -> 117064.15
A34: TOTAL VARIABLE SALES COMP — MODEST | I34: =I28+I30+I32 -> 30932.968 | J34: =J28+J30+J32 -> 31092.968 | K34: =K28+K30+K32 -> 31573.064 | L34: =L28+L30+L32 -> 34289.287 | M34: =M28+M30+M32 -> 36889.267 | N34: =N28+N30+N32 -> 37489.267 | O34: =O28+O30+O32 -> 43489.327 | P34: =P28+P30+P32 -> 46289.287 | ... T34: =T28+T30+T32 -> 52089.367 | AG34: =SUM(I34:T34) -> 489002.9
A35: TOTAL VARIABLE SALES COMP — STRETCH | I35: =I29+I31+I33 -> 38954.092 | J35: =J29+J31+J33 -> 39329.092 | K35: =K29+K31+K33 -> 40454.317 | L35: =L29+L31+L33 -> 46079.317 | M35: =M29+M31+M33 -> 49329.292 | N35: =N29+N31+N33 -> 50079.292 | O35: =O29+O31+O33 -> 57579.367 | P35: =P29+P31+P33 -> 61079.317 | ... T35: =T29+T31+T33 -> 68329.417 | AG35: =SUM(I35:T35) -> 641951.75
A37: Note: 'BEN' and 'MARKETING' rows are house/director-sourced revenue lines from the legacy tool (0% rep commission; director is paid via the override above).

Sheet STAFFING
A1: STAFFING — headcount & fully-loaded payroll model (all departments)
A2: Blue = editable. Monthly cost = (Salary/12 + $ raise + Salary/12 × (role % + dept %)) × (1 + tax&match %) + Health/mo + Licenses/mo. Raises apply from RAISE EFF. MONTH onward. Headcount cells: set the number of seats per month — add hires by raising the count from their start month, or add a whole new role in the blank rows. Sales commissions are NOT here — they are on SALES TEAM. Roster, salaries, benefits, per-seat license $ and tax % seeded from the legacy budget tool.
A5: month # → | N5: 1 | O5: 2 | P5: 3 | Q5: 4 | R5: 5 | S5: 6 | T5: 7 | U5: 8 | V5: 9 | W5: 10 | X5: 11 | Y5: 12 | Z5: 1 | AA5: 2 | AB5: 3 | AC5: 4 | AD5: 5 | AE5: 6 | AF5: 7 | AG5: 8 | AH5: 9 | AI5: 10 | AJ5: 11 | AK5: 12
A6: DEPARTMENT | B6: POSITION | C6: ANNUAL SALARY / OTE BASE | D6: SALARY /MO | E6: HEALTH (HDV) /MO | F6: LICENSES /MO (per seat) | G6: TAX + MATCH % | H6: CURRENT MONTHLY COST /HEAD | I6: $ RAISE /MO | J6: ROLE % RAISE | K6: DEPT % RAISE (auto) | L6: RAISE EFF. MONTH | M6: NEW MONTHLY COST /HEAD | N6: HC Jan | O6: HC Feb | P6: HC Mar | Q6: HC Apr | R6: HC May | S6: HC Jun | T6: HC Jul | U6: HC Aug | V6: HC Sep | W6: HC Oct | X6: HC Nov | Y6: HC Dec | Z6: COST Jan | AA6: COST Feb | AB6: COST Mar | AC6: COST Apr | AD6: COST May | AE6: COST Jun | AF6: COST Jul | AG6: COST Aug | AH6: COST Sep | AI6: COST Oct | AJ6: COST Nov | AK6: COST Dec | AL6: FY COST
A7: Installation Services | B7: Installation Operations Assistant | C7: 27040 | D7: =IF($C7="",0,$C7/12) -> 2253.3333 | E7: 0 | F7: 79.3 | G7: 0.01 | H7: =IF($C7="",0,$D7*(1+$G7)+$E7+$F7) -> 2355.1667 | I7: 0 | J7: 0 | K7: =IFERROR(INDEX($B$56:$B$66,MATCH($A7,$A$56:$A$66,0)),0) -> 0 | L7: 9 | M7: =IF($C7="",0,($D7+$I7+$D7*($J7+$K7))*(1+$G7)+$E7+$F7) -> 2355.1667 | N7: 1 | O7: 1 | P7: 1 | Q7: 1 | R7: 1 | S7: 1 | T7: 1 | U7: 1 | V7: 1 | W7: 1 | X7: 1 | Y7: 1 | Z7: =IF(N7="",0,N7*IF(Z$5>=$L7,$M7,$H7)) -> 2355.1667 | AA7: =IF(O7="",0,O7*IF(AA$5>=$L7,$M7,$H7)) -> 2355.1667 | AB7: =IF(P7="",0,P7*IF(AB$5>=$L7,$M7,$H7)) -> 2355.1667 | AC7: =IF(Q7="",0,Q7*IF(AC$5>=$L7,$M7,$H7)) -> 2355.1667 | AD7: =IF(R7="",0,R7*IF(AD$5>=$L7,$M7,$H7)) -> 2355.1667 | AE7: =IF(S7="",0,S7*IF(AE$5>=$L7,$M7,$H7)) -> 2355.1667 | AF7: =IF(T7="",0,T7*IF(AF$5>=$L7,$M7,$H7)) -> 2355.1667 | AG7: =IF(U7="",0,U7*IF(AG$5>=$L7,$M7,$H7)) -> 2355.1667 | ... AK7: =IF(Y7="",0,Y7*IF(AK$5>=$L7,$M7,$H7)) -> 2355.1667 | AL7: =SUM(Z7:AK7) -> 28262
A8: Technical Support | B8: Tech Support Manager | C8: 60000 | D8: =IF($C8="",0,$C8/12) -> 5000 | E8: 523.5 | F8: 182.72 | G8: 0.01 | H8: =IF($C8="",0,$D8*(1+$G8)+$E8+$F8) -> 5756.22 | I8: 0 | J8: 0 | K8: =IFERROR(INDEX($B$56:$B$66,MATCH($A8,$A$56:$A$66,0)),0) -> 0 | L8: 9 | M8: =IF($C8="",0,($D8+$I8+$D8*($J8+$K8))*(1+$G8)+$E8+$F8) -> 5756.22 | N8: 1 | O8: 1 | P8: 1 | Q8: 1 | R8: 1 | S8: 1 | T8: 1 | U8: 1 | V8: 1 | W8: 1 | X8: 1 | Y8: 1 | Z8: =IF(N8="",0,N8*IF(Z$5>=$L8,$M8,$H8)) -> 5756.22 | AA8: =IF(O8="",0,O8*IF(AA$5>=$L8,$M8,$H8)) -> 5756.22 | AB8: =IF(P8="",0,P8*IF(AB$5>=$L8,$M8,$H8)) -> 5756.22 | AC8: =IF(Q8="",0,Q8*IF(AC$5>=$L8,$M8,$H8)) -> 5756.22 | AD8: =IF(R8="",0,R8*IF(AD$5>=$L8,$M8,$H8)) -> 5756.22 | AE8: =IF(S8="",0,S8*IF(AE$5>=$L8,$M8,$H8)) -> 5756.22 | AF8: =IF(T8="",0,T8*IF(AF$5>=$L8,$M8,$H8)) -> 5756.22 | AG8: =IF(U8="",0,U8*IF(AG$5>=$L8,$M8,$H8)) -> 5756.22 | ... AK8: =IF(Y8="",0,Y8*IF(AK$5>=$L8,$M8,$H8)) -> 5756.22 | AL8: =SUM(Z8:AK8) -> 69074.64
A9: Technical Support | B9: Technical Support Team Member - Level II | C9: 46800 | D9: =IF($C9="",0,$C9/12) -> 3900 | E9: 523.5 | F9: 171.64 | G9: 0.01 | H9: =IF($C9="",0,$D9*(1+$G9)+$E9+$F9) -> 4634.14 | I9: 0 | J9: 0 | K9: =IFERROR(INDEX($B$56:$B$66,MATCH($A9,$A$56:$A$66,0)),0) -> 0 | L9: 9 | M9: =IF($C9="",0,($D9+$I9+$D9*($J9+$K9))*(1+$G9)+$E9+$F9) -> 4634.14 | N9: 4 | O9: 4 | P9: 4 | Q9: 4 | R9: 4 | S9: 4 | T9: 4 | U9: 4 | V9: 4 | W9: 4 | X9: 4 | Y9: 4 | Z9: =IF(N9="",0,N9*IF(Z$5>=$L9,$M9,$H9)) -> 18536.56 | AA9: =IF(O9="",0,O9*IF(AA$5>=$L9,$M9,$H9)) -> 18536.56 | AB9: =IF(P9="",0,P9*IF(AB$5>=$L9,$M9,$H9)) -> 18536.56 | AC9: =IF(Q9="",0,Q9*IF(AC$5>=$L9,$M9,$H9)) -> 18536.56 | AD9: =IF(R9="",0,R9*IF(AD$5>=$L9,$M9,$H9)) -> 18536.56 | AE9: =IF(S9="",0,S9*IF(AE$5>=$L9,$M9,$H9)) -> 18536.56 | AF9: =IF(T9="",0,T9*IF(AF$5>=$L9,$M9,$H9)) -> 18536.56 | AG9: =IF(U9="",0,U9*IF(AG$5>=$L9,$M9,$H9)) -> 18536.56 | ... AK9: =IF(Y9="",0,Y9*IF(AK$5>=$L9,$M9,$H9)) -> 18536.56 | AL9: =SUM(Z9:AK9) -> 222438.72
A10: Technical Support | B10: Technical Support Team Member - Level I | C10: 43680 | D10: =IF($C10="",0,$C10/12) -> 3640 | E10: 523.5 | F10: 219.5 | G10: 0.01 | H10: =IF($C10="",0,$D10*(1+$G10)+$E10+$F10) -> 4419.4 | I10: 0 | J10: 0 | K10: =IFERROR(INDEX($B$56:$B$66,MATCH($A10,$A$56:$A$66,0)),0) -> 0 | L10: 9 | M10: =IF($C10="",0,($D10+$I10+$D10*($J10+$K10))*(1+$G10)+$E10+$F10) -> 4419.4 | N10: 3 | O10: 3 | P10: 3 | Q10: 3 | R10: 3 | S10: 3 | T10: 3 | U10: 3 | V10: 3 | W10: 3 | X10: 3 | Y10: 3 | Z10: =IF(N10="",0,N10*IF(Z$5>=$L10,$M10,$H10)) -> 13258.2 | AA10: =IF(O10="",0,O10*IF(AA$5>=$L10,$M10,$H10)) -> 13258.2 | AB10: =IF(P10="",0,P10*IF(AB$5>=$L10,$M10,$H10)) -> 13258.2 | AC10: =IF(Q10="",0,Q10*IF(AC$5>=$L10,$M10,$H10)) -> 13258.2 | AD10: =IF(R10="",0,R10*IF(AD$5>=$L10,$M10,$H10)) -> 13258.2 | AE10: =IF(S10="",0,S10*IF(AE$5>=$L10,$M10,$H10)) -> 13258.2 | AF10: =IF(T10="",0,T10*IF(AF$5>=$L10,$M10,$H10)) -> 13258.2 | AG10: =IF(U10="",0,U10*IF(AG$5>=$L10,$M10,$H10)) -> 13258.2 | ... AK10: =IF(Y10="",0,Y10*IF(AK$5>=$L10,$M10,$H10)) -> 13258.2 | AL10: =SUM(Z10:AK10) -> 159098.4
A11: Installation Services | B11: Installation Services Director | C11: 90000 | D11: =IF($C11="",0,$C11/12) -> 7500 | E11: 523.5 | F11: 74.14 | G11: 0.01 | H11: =IF($C11="",0,$D11*(1+$G11)+$E11+$F11) -> 8172.64 | I11: 0 | J11: 0 | K11: =IFERROR(INDEX($B$56:$B$66,MATCH($A11,$A$56:$A$66,0)),0) -> 0 | L11: 9 | M11: =IF($C11="",0,($D11+$I11+$D11*($J11+$K11))*(1+$G11)+$E11+$F11) -> 8172.64 | N11: 1 | O11: 1 | P11: 1 | Q11: 1 | R11: 1 | S11: 1 | T11: 1 | U11: 1 | V11: 1 | W11: 1 | X11: 1 | Y11: 1 | Z11: =IF(N11="",0,N11*IF(Z$5>=$L11,$M11,$H11)) -> 8172.64 | AA11: =IF(O11="",0,O11*IF(AA$5>=$L11,$M11,$H11)) -> 8172.64 | AB11: =IF(P11="",0,P11*IF(AB$5>=$L11,$M11,$H11)) -> 8172.64 | AC11: =IF(Q11="",0,Q11*IF(AC$5>=$L11,$M11,$H11)) -> 8172.64 | AD11: =IF(R11="",0,R11*IF(AD$5>=$L11,$M11,$H11)) -> 8172.64 | AE11: =IF(S11="",0,S11*IF(AE$5>=$L11,$M11,$H11)) -> 8172.64 | AF11: =IF(T11="",0,T11*IF(AF$5>=$L11,$M11,$H11)) -> 8172.64 | AG11: =IF(U11="",0,U11*IF(AG$5>=$L11,$M11,$H11)) -> 8172.64 | ... AK11: =IF(Y11="",0,Y11*IF(AK$5>=$L11,$M11,$H11)) -> 8172.64 | AL11: =SUM(Z11:AK11) -> 98071.68
A12: Installation Services | B12: Senior Project Manager | C12: 78000 | D12: =IF($C12="",0,$C12/12) -> 6500 | E12: 523.5 | F12: 74.14 | G12: 0.01 | H12: =IF($C12="",0,$D12*(1+$G12)+$E12+$F12) -> 7162.64 | I12: 0 | J12: 0 | K12: =IFERROR(INDEX($B$56:$B$66,MATCH($A12,$A$56:$A$66,0)),0) -> 0 | L12: 9 | M12: =IF($C12="",0,($D12+$I12+$D12*($J12+$K12))*(1+$G12)+$E12+$F12) -> 7162.64 | N12: 1 | O12: 1 | P12: 1 | Q12: 1 | R12: 1 | S12: 1 | T12: 1 | U12: 1 | V12: 1 | W12: 1 | X12: 1 | Y12: 1 | Z12: =IF(N12="",0,N12*IF(Z$5>=$L12,$M12,$H12)) -> 7162.64 | AA12: =IF(O12="",0,O12*IF(AA$5>=$L12,$M12,$H12)) -> 7162.64 | AB12: =IF(P12="",0,P12*IF(AB$5>=$L12,$M12,$H12)) -> 7162.64 | AC12: =IF(Q12="",0,Q12*IF(AC$5>=$L12,$M12,$H12)) -> 7162.64 | AD12: =IF(R12="",0,R12*IF(AD$5>=$L12,$M12,$H12)) -> 7162.64 | AE12: =IF(S12="",0,S12*IF(AE$5>=$L12,$M12,$H12)) -> 7162.64 | AF12: =IF(T12="",0,T12*IF(AF$5>=$L12,$M12,$H12)) -> 7162.64 | AG12: =IF(U12="",0,U12*IF(AG$5>=$L12,$M12,$H12)) -> 7162.64 | ... AK12: =IF(Y12="",0,Y12*IF(AK$5>=$L12,$M12,$H12)) -> 7162.64 | AL12: =SUM(Z12:AK12) -> 85951.68
A13: Installation Services | B13: Project Manager | C13: 75000 | D13: =IF($C13="",0,$C13/12) -> 6250 | E13: 523.5 | F13: 74.14 | G13: 0.01 | H13: =IF($C13="",0,$D13*(1+$G13)+$E13+$F13) -> 6910.14 | I13: 0 | J13: 0 | K13: =IFERROR(INDEX($B$56:$B$66,MATCH($A13,$A$56:$A$66,0)),0) -> 0 | L13: 9 | M13: =IF($C13="",0,($D13+$I13+$D13*($J13+$K13))*(1+$G13)+$E13+$F13) -> 6910.14 | N13: 1 | O13: 1 | P13: 1 | Q13: 1 | R13: 1 | S13: 1 | T13: 1 | U13: 1 | V13: 1 | W13: 1 | X13: 1 | Y13: 1 | Z13: =IF(N13="",0,N13*IF(Z$5>=$L13,$M13,$H13)) -> 6910.14 | AA13: =IF(O13="",0,O13*IF(AA$5>=$L13,$M13,$H13)) -> 6910.14 | AB13: =IF(P13="",0,P13*IF(AB$5>=$L13,$M13,$H13)) -> 6910.14 | AC13: =IF(Q13="",0,Q13*IF(AC$5>=$L13,$M13,$H13)) -> 6910.14 | AD13: =IF(R13="",0,R13*IF(AD$5>=$L13,$M13,$H13)) -> 6910.14 | AE13: =IF(S13="",0,S13*IF(AE$5>=$L13,$M13,$H13)) -> 6910.14 | AF13: =IF(T13="",0,T13*IF(AF$5>=$L13,$M13,$H13)) -> 6910.14 | AG13: =IF(U13="",0,U13*IF(AG$5>=$L13,$M13,$H13)) -> 6910.14 | ... AK13: =IF(Y13="",0,Y13*IF(AK$5>=$L13,$M13,$H13)) -> 6910.14 | AL13: =SUM(Z13:AK13) -> 82921.68
A14: Installation Services | B14: Junior Project Manager | C14: 62000 | D14: =IF($C14="",0,$C14/12) -> 5166.6667 | E14: 523.5 | F14: 122 | G14: 0.01 | H14: =IF($C14="",0,$D14*(1+$G14)+$E14+$F14) -> 5863.8333 | I14: 0 | J14: 0 | K14: =IFERROR(INDEX($B$56:$B$66,MATCH($A14,$A$56:$A$66,0)),0) -> 0 | L14: 9 | M14: =IF($C14="",0,($D14+$I14+$D14*($J14+$K14))*(1+$G14)+$E14+$F14) -> 5863.8333 | N14: 1 | O14: 1 | P14: 1 | Q14: 1 | R14: 1 | S14: 1 | T14: 1 | U14: 1 | V14: 1 | W14: 1 | X14: 1 | Y14: 1 | Z14: =IF(N14="",0,N14*IF(Z$5>=$L14,$M14,$H14)) -> 5863.8333 | AA14: =IF(O14="",0,O14*IF(AA$5>=$L14,$M14,$H14)) -> 5863.8333 | AB14: =IF(P14="",0,P14*IF(AB$5>=$L14,$M14,$H14)) -> 5863.8333 | AC14: =IF(Q14="",0,Q14*IF(AC$5>=$L14,$M14,$H14)) -> 5863.8333 | AD14: =IF(R14="",0,R14*IF(AD$5>=$L14,$M14,$H14)) -> 5863.8333 | AE14: =IF(S14="",0,S14*IF(AE$5>=$L14,$M14,$H14)) -> 5863.8333 | AF14: =IF(T14="",0,T14*IF(AF$5>=$L14,$M14,$H14)) -> 5863.8333 | AG14: =IF(U14="",0,U14*IF(AG$5>=$L14,$M14,$H14)) -> 5863.8333 | ... AK14: =IF(Y14="",0,Y14*IF(AK$5>=$L14,$M14,$H14)) -> 5863.8333 | AL14: =SUM(Z14:AK14) -> 70366
A15: Installation Services | B15: Project Coordinator | C15: 50000 | D15: =IF($C15="",0,$C15/12) -> 4166.6667 | E15: 523.5 | F15: 74.14 | G15: 0.01 | H15: =IF($C15="",0,$D15*(1+$G15)+$E15+$F15) -> 4805.9733 | I15: 0 | J15: 0 | K15: =IFERROR(INDEX($B$56:$B$66,MATCH($A15,$A$56:$A$66,0)),0) -> 0 | L15: 9 | M15: =IF($C15="",0,($D15+$I15+$D15*($J15+$K15))*(1+$G15)+$E15+$F15) -> 4805.9733 | N15: 1 | O15: 1 | P15: 1 | Q15: 1 | R15: 1 | S15: 1 | T15: 1 | U15: 1 | V15: 1 | W15: 1 | X15: 1 | Y15: 1 | Z15: =IF(N15="",0,N15*IF(Z$5>=$L15,$M15,$H15)) -> 4805.9733 | AA15: =IF(O15="",0,O15*IF(AA$5>=$L15,$M15,$H15)) -> 4805.9733 | AB15: =IF(P15="",0,P15*IF(AB$5>=$L15,$M15,$H15)) -> 4805.9733 | AC15: =IF(Q15="",0,Q15*IF(AC$5>=$L15,$M15,$H15)) -> 4805.9733 | AD15: =IF(R15="",0,R15*IF(AD$5>=$L15,$M15,$H15)) -> 4805.9733 | AE15: =IF(S15="",0,S15*IF(AE$5>=$L15,$M15,$H15)) -> 4805.9733 | AF15: =IF(T15="",0,T15*IF(AF$5>=$L15,$M15,$H15)) -> 4805.9733 | AG15: =IF(U15="",0,U15*IF(AG$5>=$L15,$M15,$H15)) -> 4805.9733 | ... AK15: =IF(Y15="",0,Y15*IF(AK$5>=$L15,$M15,$H15)) -> 4805.9733 | AL15: =SUM(Z15:AK15) -> 57671.68
A16: Sales | B16: Sales Director - Ben LaRue | C16: 175000 | D16: =IF($C16="",0,$C16/12) -> 14583.333 | E16: 523.5 | F16: 235.5 | G16: 0.01 | H16: =IF($C16="",0,$D16*(1+$G16)+$E16+$F16) -> 15488.167 | I16: 0 | J16: 0 | K16: =IFERROR(INDEX($B$56:$B$66,MATCH($A16,$A$56:$A$66,0)),0) -> 0 | L16: 9 | M16: =IF($C16="",0,($D16+$I16+$D16*($J16+$K16))*(1+$G16)+$E16+$F16) -> 15488.167 | N16: 1 | O16: 1 | P16: 1 | Q16: 1 | R16: 1 | S16: 1 | T16: 1 | U16: 1 | V16: 1 | W16: 1 | X16: 1 | Y16: 1 | Z16: =IF(N16="",0,N16*IF(Z$5>=$L16,$M16,$H16)) -> 15488.167 | AA16: =IF(O16="",0,O16*IF(AA$5>=$L16,$M16,$H16)) -> 15488.167 | AB16: =IF(P16="",0,P16*IF(AB$5>=$L16,$M16,$H16)) -> 15488.167 | AC16: =IF(Q16="",0,Q16*IF(AC$5>=$L16,$M16,$H16)) -> 15488.167 | AD16: =IF(R16="",0,R16*IF(AD$5>=$L16,$M16,$H16)) -> 15488.167 | AE16: =IF(S16="",0,S16*IF(AE$5>=$L16,$M16,$H16)) -> 15488.167 | AF16: =IF(T16="",0,T16*IF(AF$5>=$L16,$M16,$H16)) -> 15488.167 | AG16: =IF(U16="",0,U16*IF(AG$5>=$L16,$M16,$H16)) -> 15488.167 | ... AK16: =IF(Y16="",0,Y16*IF(AK$5>=$L16,$M16,$H16)) -> 15488.167 | AL16: =SUM(Z16:AK16) -> 185858
A17: Sales | B17: Senior Account Executive - Stu Moore | C17: 68000 | D17: =IF($C17="",0,$C17/12) -> 5666.6667 | E17: 523.5 | F17: 219.25 | G17: 0.01 | H17: =IF($C17="",0,$D17*(1+$G17)+$E17+$F17) -> 6466.0833 | I17: 0 | J17: 0 | K17: =IFERROR(INDEX($B$56:$B$66,MATCH($A17,$A$56:$A$66,0)),0) -> 0 | L17: 9 | M17: =IF($C17="",0,($D17+$I17+$D17*($J17+$K17))*(1+$G17)+$E17+$F17) -> 6466.0833 | N17: 1 | O17: 1 | P17: 1 | Q17: 1 | R17: 1 | S17: 1 | T17: 1 | U17: 1 | V17: 1 | W17: 1 | X17: 1 | Y17: 1 | Z17: =IF(N17="",0,N17*IF(Z$5>=$L17,$M17,$H17)) -> 6466.0833 | AA17: =IF(O17="",0,O17*IF(AA$5>=$L17,$M17,$H17)) -> 6466.0833 | AB17: =IF(P17="",0,P17*IF(AB$5>=$L17,$M17,$H17)) -> 6466.0833 | AC17: =IF(Q17="",0,Q17*IF(AC$5>=$L17,$M17,$H17)) -> 6466.0833 | AD17: =IF(R17="",0,R17*IF(AD$5>=$L17,$M17,$H17)) -> 6466.0833 | AE17: =IF(S17="",0,S17*IF(AE$5>=$L17,$M17,$H17)) -> 6466.0833 | AF17: =IF(T17="",0,T17*IF(AF$5>=$L17,$M17,$H17)) -> 6466.0833 | AG17: =IF(U17="",0,U17*IF(AG$5>=$L17,$M17,$H17)) -> 6466.0833 | ... AK17: =IF(Y17="",0,Y17*IF(AK$5>=$L17,$M17,$H17)) -> 6466.0833 | AL17: =SUM(Z17:AK17) -> 77593
A18: Sales | B18: Account Executive - RAMP | C18: 60000 | D18: =IF($C18="",0,$C18/12) -> 5000 | E18: 523.5 | F18: 219.25 | G18: 0.01 | H18: =IF($C18="",0,$D18*(1+$G18)+$E18+$F18) -> 5792.75 | I18: 0 | J18: 0 | K18: =IFERROR(INDEX($B$56:$B$66,MATCH($A18,$A$56:$A$66,0)),0) -> 0 | L18: 9 | M18: =IF($C18="",0,($D18+$I18+$D18*($J18+$K18))*(1+$G18)+$E18+$F18) -> 5792.75 | N18: 8 | O18: 8 | P18: 8 | Q18: 8 | R18: 8 | S18: 8 | T18: 8 | U18: 8 | V18: 8 | W18: 8 | X18: 8 | Y18: 8 | Z18: =IF(N18="",0,N18*IF(Z$5>=$L18,$M18,$H18)) -> 46342 | AA18: =IF(O18="",0,O18*IF(AA$5>=$L18,$M18,$H18)) -> 46342 | AB18: =IF(P18="",0,P18*IF(AB$5>=$L18,$M18,$H18)) -> 46342 | AC18: =IF(Q18="",0,Q18*IF(AC$5>=$L18,$M18,$H18)) -> 46342 | AD18: =IF(R18="",0,R18*IF(AD$5>=$L18,$M18,$H18)) -> 46342 | AE18: =IF(S18="",0,S18*IF(AE$5>=$L18,$M18,$H18)) -> 46342 | AF18: =IF(T18="",0,T18*IF(AF$5>=$L18,$M18,$H18)) -> 46342 | AG18: =IF(U18="",0,U18*IF(AG$5>=$L18,$M18,$H18)) -> 46342 | ... AK18: =IF(Y18="",0,Y18*IF(AK$5>=$L18,$M18,$H18)) -> 46342 | AL18: =SUM(Z18:AK18) -> 556104
... A38: Software Development | B38: Machine Learning Engineer - Michael Kazzi | C38: 85020 | D38: =IF($C38="",0,$C38/12) -> 7085 | E38: 523.5 | F38: 75.08 | G38: 0.01 | H38: =IF($C38="",0,$D38*(1+$G38)+$E38+$F38) -> 7754.43 | I38: 0 | J38: 0 | K38: =IFERROR(INDEX($B$56:$B$66,MATCH($A38,$A$56:$A$66,0)),0) -> 0 | L38: 9 | M38: =IF($C38="",0,($D38+$I38+$D38*($J38+$K38))*(1+$G38)+$E38+$F38) -> 7754.43 | N38: 1 | O38: 1 | P38: 1 | Q38: 1 | R38: 1 | S38: 1 | T38: 1 | U38: 1 | V38: 1 | W38: 1 | X38: 1 | Y38: 1 | Z38: =IF(N38="",0,N38*IF(Z$5>=$L38,$M38,$H38)) -> 7754.43 | AA38: =IF(O38="",0,O38*IF(AA$5>=$L38,$M38,$H38)) -> 7754.43 | AB38: =IF(P38="",0,P38*IF(AB$5>=$L38,$M38,$H38)) -> 7754.43 | AC38: =IF(Q38="",0,Q38*IF(AC$5>=$L38,$M38,$H38)) -> 7754.43 | AD38: =IF(R38="",0,R38*IF(AD$5>=$L38,$M38,$H38)) -> 7754.43 | AE38: =IF(S38="",0,S38*IF(AE$5>=$L38,$M38,$H38)) -> 7754.43 | AF38: =IF(T38="",0,T38*IF(AF$5>=$L38,$M38,$H38)) -> 7754.43 | AG38: =IF(U38="",0,U38*IF(AG$5>=$L38,$M38,$H38)) -> 7754.43 | ... AK38: =IF(Y38="",0,Y38*IF(AK$5>=$L38,$M38,$H38)) -> 7754.43 | AL38: =SUM(Z38:AK38) -> 93053.16
D39: =IF($C39="",0,$C39/12) -> 0 | E39: 523.5 | F39: 75 | G39: 0.1 | H39: =IF($C39="",0,$D39*(1+$G39)+$E39+$F39) -> 0 | I39: 0 | J39: 0 | K39: =IFERROR(INDEX($B$56:$B$66,MATCH($A39,$A$56:$A$66,0)),0) -> 0 | L39: 9 | M39: =IF($C39="",0,($D39+$I39+$D39*($J39+$K39))*(1+$G39)+$E39+$F39) -> 0 | Z39: =IF(N39="",0,N39*IF(Z$5>=$L39,$M39,$H39)) -> 0 | AA39: =IF(O39="",0,O39*IF(AA$5>=$L39,$M39,$H39)) -> 0 | AB39: =IF(P39="",0,P39*IF(AB$5>=$L39,$M39,$H39)) -> 0 | AC39: =IF(Q39="",0,Q39*IF(AC$5>=$L39,$M39,$H39)) -> 0 | AD39: =IF(R39="",0,R39*IF(AD$5>=$L39,$M39,$H39)) -> 0 | AE39: =IF(S39="",0,S39*IF(AE$5>=$L39,$M39,$H39)) -> 0 | AF39: =IF(T39="",0,T39*IF(AF$5>=$L39,$M39,$H39)) -> 0 | AG39: =IF(U39="",0,U39*IF(AG$5>=$L39,$M39,$H39)) -> 0 | ... AK39: =IF(Y39="",0,Y39*IF(AK$5>=$L39,$M39,$H39)) -> 0 | AL39: =SUM(Z39:AK39) -> 0
D40: =IF($C40="",0,$C40/12) -> 0 | E40: 523.5 | F40: 75 | G40: 0.1 | H40: =IF($C40="",0,$D40*(1+$G40)+$E40+$F40) -> 0 | I40: 0 | J40: 0 | K40: =IFERROR(INDEX($B$56:$B$66,MATCH($A40,$A$56:$A$66,0)),0) -> 0 | L40: 9 | M40: =IF($C40="",0,($D40+$I40+$D40*($J40+$K40))*(1+$G40)+$E40+$F40) -> 0 | Z40: =IF(N40="",0,N40*IF(Z$5>=$L40,$M40,$H40)) -> 0 | AA40: =IF(O40="",0,O40*IF(AA$5>=$L40,$M40,$H40)) -> 0 | AB40: =IF(P40="",0,P40*IF(AB$5>=$L40,$M40,$H40)) -> 0 | AC40: =IF(Q40="",0,Q40*IF(AC$5>=$L40,$M40,$H40)) -> 0 | AD40: =IF(R40="",0,R40*IF(AD$5>=$L40,$M40,$H40)) -> 0 | AE40: =IF(S40="",0,S40*IF(AE$5>=$L40,$M40,$H40)) -> 0 | AF40: =IF(T40="",0,T40*IF(AF$5>=$L40,$M40,$H40)) -> 0 | AG40: =IF(U40="",0,U40*IF(AG$5>=$L40,$M40,$H40)) -> 0 | ... AK40: =IF(Y40="",0,Y40*IF(AK$5>=$L40,$M40,$H40)) -> 0 | AL40: =SUM(Z40:AK40) -> 0
D41: =IF($C41="",0,$C41/12) -> 0 | E41: 523.5 | F41: 75 | G41: 0.1 | H41: =IF($C41="",0,$D41*(1+$G41)+$E41+$F41) -> 0 | I41: 0 | J41: 0 | K41: =IFERROR(INDEX($B$56:$B$66,MATCH($A41,$A$56:$A$66,0)),0) -> 0 | L41: 9 | M41: =IF($C41="",0,($D41+$I41+$D41*($J41+$K41))*(1+$G41)+$E41+$F41) -> 0 | Z41: =IF(N41="",0,N41*IF(Z$5>=$L41,$M41,$H41)) -> 0 | AA41: =IF(O41="",0,O41*IF(AA$5>=$L41,$M41,$H41)) -> 0 | AB41: =IF(P41="",0,P41*IF(AB$5>=$L41,$M41,$H41)) -> 0 | AC41: =IF(Q41="",0,Q41*IF(AC$5>=$L41,$M41,$H41)) -> 0 | AD41: =IF(R41="",0,R41*IF(AD$5>=$L41,$M41,$H41)) -> 0 | AE41: =IF(S41="",0,S41*IF(AE$5>=$L41,$M41,$H41)) -> 0 | AF41: =IF(T41="",0,T41*IF(AF$5>=$L41,$M41,$H41)) -> 0 | AG41: =IF(U41="",0,U41*IF(AG$5>=$L41,$M41,$H41)) -> 0 | ... AK41: =IF(Y41="",0,Y41*IF(AK$5>=$L41,$M41,$H41)) -> 0 | AL41: =SUM(Z41:AK41) -> 0
D42: =IF($C42="",0,$C42/12) -> 0 | E42: 523.5 | F42: 75 | G42: 0.1 | H42: =IF($C42="",0,$D42*(1+$G42)+$E42+$F42) -> 0 | I42: 0 | J42: 0 | K42: =IFERROR(INDEX($B$56:$B$66,MATCH($A42,$A$56:$A$66,0)),0) -> 0 | L42: 9 | M42: =IF($C42="",0,($D42+$I42+$D42*($J42+$K42))*(1+$G42)+$E42+$F42) -> 0 | Z42: =IF(N42="",0,N42*IF(Z$5>=$L42,$M42,$H42)) -> 0 | AA42: =IF(O42="",0,O42*IF(AA$5>=$L42,$M42,$H42)) -> 0 | AB42: =IF(P42="",0,P42*IF(AB$5>=$L42,$M42,$H42)) -> 0 | AC42: =IF(Q42="",0,Q42*IF(AC$5>=$L42,$M42,$H42)) -> 0 | AD42: =IF(R42="",0,R42*IF(AD$5>=$L42,$M42,$H42)) -> 0 | AE42: =IF(S42="",0,S42*IF(AE$5>=$L42,$M42,$H42)) -> 0 | AF42: =IF(T42="",0,T42*IF(AF$5>=$L42,$M42,$H42)) -> 0 | AG42: =IF(U42="",0,U42*IF(AG$5>=$L42,$M42,$H42)) -> 0 | ... AK42: =IF(Y42="",0,Y42*IF(AK$5>=$L42,$M42,$H42)) -> 0 | AL42: =SUM(Z42:AK42) -> 0
D43: =IF($C43="",0,$C43/12) -> 0 | E43: 523.5 | F43: 75 | G43: 0.1 | H43: =IF($C43="",0,$D43*(1+$G43)+$E43+$F43) -> 0 | I43: 0 | J43: 0 | K43: =IFERROR(INDEX($B$56:$B$66,MATCH($A43,$A$56:$A$66,0)),0) -> 0 | L43: 9 | M43: =IF($C43="",0,($D43+$I43+$D43*($J43+$K43))*(1+$G43)+$E43+$F43) -> 0 | Z43: =IF(N43="",0,N43*IF(Z$5>=$L43,$M43,$H43)) -> 0 | AA43: =IF(O43="",0,O43*IF(AA$5>=$L43,$M43,$H43)) -> 0 | AB43: =IF(P43="",0,P43*IF(AB$5>=$L43,$M43,$H43)) -> 0 | AC43: =IF(Q43="",0,Q43*IF(AC$5>=$L43,$M43,$H43)) -> 0 | AD43: =IF(R43="",0,R43*IF(AD$5>=$L43,$M43,$H43)) -> 0 | AE43: =IF(S43="",0,S43*IF(AE$5>=$L43,$M43,$H43)) -> 0 | AF43: =IF(T43="",0,T43*IF(AF$5>=$L43,$M43,$H43)) -> 0 | AG43: =IF(U43="",0,U43*IF(AG$5>=$L43,$M43,$H43)) -> 0 | ... AK43: =IF(Y43="",0,Y43*IF(AK$5>=$L43,$M43,$H43)) -> 0 | AL43: =SUM(Z43:AK43) -> 0
D44: =IF($C44="",0,$C44/12) -> 0 | E44: 523.5 | F44: 75 | G44: 0.1 | H44: =IF($C44="",0,$D44*(1+$G44)+$E44+$F44) -> 0 | I44: 0 | J44: 0 | K44: =IFERROR(INDEX($B$56:$B$66,MATCH($A44,$A$56:$A$66,0)),0) -> 0 | L44: 9 | M44: =IF($C44="",0,($D44+$I44+$D44*($J44+$K44))*(1+$G44)+$E44+$F44) -> 0 | Z44: =IF(N44="",0,N44*IF(Z$5>=$L44,$M44,$H44)) -> 0 | AA44: =IF(O44="",0,O44*IF(AA$5>=$L44,$M44,$H44)) -> 0 | AB44: =IF(P44="",0,P44*IF(AB$5>=$L44,$M44,$H44)) -> 0 | AC44: =IF(Q44="",0,Q44*IF(AC$5>=$L44,$M44,$H44)) -> 0 | AD44: =IF(R44="",0,R44*IF(AD$5>=$L44,$M44,$H44)) -> 0 | AE44: =IF(S44="",0,S44*IF(AE$5>=$L44,$M44,$H44)) -> 0 | AF44: =IF(T44="",0,T44*IF(AF$5>=$L44,$M44,$H44)) -> 0 | AG44: =IF(U44="",0,U44*IF(AG$5>=$L44,$M44,$H44)) -> 0 | ... AK44: =IF(Y44="",0,Y44*IF(AK$5>=$L44,$M44,$H44)) -> 0 | AL44: =SUM(Z44:AK44) -> 0
D45: =IF($C45="",0,$C45/12) -> 0 | E45: 523.5 | F45: 75 | G45: 0.1 | H45: =IF($C45="",0,$D45*(1+$G45)+$E45+$F45) -> 0 | I45: 0 | J45: 0 | K45: =IFERROR(INDEX($B$56:$B$66,MATCH($A45,$A$56:$A$66,0)),0) -> 0 | L45: 9 | M45: =IF($C45="",0,($D45+$I45+$D45*($J45+$K45))*(1+$G45)+$E45+$F45) -> 0 | Z45: =IF(N45="",0,N45*IF(Z$5>=$L45,$M45,$H45)) -> 0 | AA45: =IF(O45="",0,O45*IF(AA$5>=$L45,$M45,$H45)) -> 0 | AB45: =IF(P45="",0,P45*IF(AB$5>=$L45,$M45,$H45)) -> 0 | AC45: =IF(Q45="",0,Q45*IF(AC$5>=$L45,$M45,$H45)) -> 0 | AD45: =IF(R45="",0,R45*IF(AD$5>=$L45,$M45,$H45)) -> 0 | AE45: =IF(S45="",0,S45*IF(AE$5>=$L45,$M45,$H45)) -> 0 | AF45: =IF(T45="",0,T45*IF(AF$5>=$L45,$M45,$H45)) -> 0 | AG45: =IF(U45="",0,U45*IF(AG$5>=$L45,$M45,$H45)) -> 0 | ... AK45: =IF(Y45="",0,Y45*IF(AK$5>=$L45,$M45,$H45)) -> 0 | AL45: =SUM(Z45:AK45) -> 0
D46: =IF($C46="",0,$C46/12) -> 0 | E46: 523.5 | F46: 75 | G46: 0.1 | H46: =IF($C46="",0,$D46*(1+$G46)+$E46+$F46) -> 0 | I46: 0 | J46: 0 | K46: =IFERROR(INDEX($B$56:$B$66,MATCH($A46,$A$56:$A$66,0)),0) -> 0 | L46: 9 | M46: =IF($C46="",0,($D46+$I46+$D46*($J46+$K46))*(1+$G46)+$E46+$F46) -> 0 | Z46: =IF(N46="",0,N46*IF(Z$5>=$L46,$M46,$H46)) -> 0 | AA46: =IF(O46="",0,O46*IF(AA$5>=$L46,$M46,$H46)) -> 0 | AB46: =IF(P46="",0,P46*IF(AB$5>=$L46,$M46,$H46)) -> 0 | AC46: =IF(Q46="",0,Q46*IF(AC$5>=$L46,$M46,$H46)) -> 0 | AD46: =IF(R46="",0,R46*IF(AD$5>=$L46,$M46,$H46)) -> 0 | AE46: =IF(S46="",0,S46*IF(AE$5>=$L46,$M46,$H46)) -> 0 | AF46: =IF(T46="",0,T46*IF(AF$5>=$L46,$M46,$H46)) -> 0 | AG46: =IF(U46="",0,U46*IF(AG$5>=$L46,$M46,$H46)) -> 0 | ... AK46: =IF(Y46="",0,Y46*IF(AK$5>=$L46,$M46,$H46)) -> 0 | AL46: =SUM(Z46:AK46) -> 0
B47: TOTALS | N47: =SUM(N7:N46) -> 48 | O47: =SUM(O7:O46) -> 48 | P47: =SUM(P7:P46) -> 48 | Q47: =SUM(Q7:Q46) -> 48 | R47: =SUM(R7:R46) -> 48 | S47: =SUM(S7:S46) -> 48 | T47: =SUM(T7:T46) -> 48 | U47: =SUM(U7:U46) -> 48 | ... AL47: =SUM(AL7:AL46) -> 3916403.8
A49: EXAMPLE (not counted): Technical Support | B49: Support Engineer — new hire Oct | C49: 65000 | E49: 523.5 | F49: 75 | G49: 0.1 | I49: 0 | J49: 0 | L49: 9 | N49: 0 | O49: 0 | P49: 0 | Q49: 0 | R49: 0 | S49: 0 | T49: 0 | U49: 0 | V49: 0 | W49: 1 | X49: → headcount 0 until Oct, 1 after = hire lands Oct 1 | Y49: 1
A51: Xero payroll as booked (wages+tax+benefits — includes sales commissions) | Z51: 340010.78 | AA51: 306521.04 | AB51: 338404.82 | AC51: 356191.85 | AD51: 302930.9 | AE51: 232740.43 | AF51: 285805.48 | AG51: 267791.52
A52: Model vs booked (Δ; model excludes commissions — expect model ≤ booked in strong sales months) | Z52: =Z47-Z51 -> -13643.797 | AA52: =AA47-AA51 -> 19845.943 | AB52: =AB47-AB51 -> -12037.837 | AC52: =AC47-AC51 -> -29824.867 | AD52: =AD47-AD51 -> 23436.083 | AE52: =AE47-AE51 -> 93626.553 | AF52: =AF47-AF51 -> 40561.503 | AG52: =AG47-AG51 -> 58575.463
A54: DEPARTMENT-WIDE % RAISE (applies to every role in the dept, from each row's RAISE EFF. MONTH)
A55: DEPARTMENT | B55: % RAISE
A56: Sales | B56: 0
A57: Marketing | B57: 0
A58: Software Development | B58: 0
A59: Installation Services | B59: 0
A60: Technical Support | B60: 0
A61: Purchasing & Fulfillment | B61: 0
A62: 03 - HR & Business Administration Manager | B62: 0
A63: Facillities | B63: 0
A64: Exec | B64: 0
A65: Product | B65: 0
A66: General Overhead | B66: 0

Sheet EXPENSES
A1: EXPENSES — every recurring cost, with ON/OFF, overrides and timing
A2: Blue = editable. PLANNED $/MO picks: OVERRIDE if set → otherwise XERO SUGGESTED or BUDGET TOOL $ per the USE column → × (1 + % ADJ). Turn an expense off with ON? = N (or end it early with TO MONTH). Add an expense in the blank rows (set DEPT, OVERRIDE $, FROM/TO, ON?=Y). Departments follow the budgeting tool where it disagrees with Xero. Per-seat license costs (Slack, Google, Bonusly, seat portions of Hubspot/Gong/Zoom/Atlassian/Rippling…) are NOT rows here — they ride on STAFFING (Licenses/mo × headcount); SEAT $/MO shows what portion was moved there.
P4: 1 | Q4: 2 | R4: 3 | S4: 4 | T4: 5 | U4: 6 | V4: 7 | W4: 8 | X4: 9 | Y4: 10 | Z4: 11 | AA4: 12
A5: EXPENSE / VENDOR | B5: DEPARTMENT | C5: SOURCE | D5: STATUS (Xero trend) | E5: SHARE OF VENDOR | F5: SEAT $/MO (→STAFFING) | G5: XERO SUGGESTED $/MO | H5: BUDGET TOOL $/MO | I5: USE (XERO/BUDGET) | J5: OVERRIDE $/MO | K5: % ADJ | L5: FROM MO | M5: TO MO | N5: ON? | O5: PLANNED $/MO | P5: Jan | Q5: Feb | R5: Mar | S5: Apr | T5: May | U5: Jun | V5: Jul | W5: Aug | X5: Sep | Y5: Oct | Z5: Nov | AA5: Dec | AB5: FY TOTAL
A6: Install Services Site Surveys | B6: Sales | C6: XERO+BUDGET | D6: STEADY | E6: 1 | G6: =IFERROR(IF($F6>0,MAX(0,INDEX('XERO ACTUALS'!$T$5:$T$132,MATCH($A6,'XERO ACTUALS'!$A$5:$A$132,0))-$F6),INDEX('XERO ACTUALS'!$T$5:$T$132,MATCH($A6,'XERO ACTUALS'!$A$5:$A$132,0)))*IF($E6="",1,$E6),"") -> 22058.667 | H6: 16000 | I6: XERO | K6: 0 | L6: 1 | M6: 12 | N6: Y | O6: =IF($N6="N",0,IF($A6="",0,(IF($J6<>"",$J6,IF($I6="BUDGET",IF($H6="",0,$H6),IF($G6="",0,$G6))))*(1+IF($K6="",0,$K6)))) -> 22058.667 | P6: =IF(AND(P$4>=IF($L6="",1,$L6),P$4<=IF($M6="",12,$M6)),$O6,0) -> 22058.667 | Q6: =IF(AND(Q$4>=IF($L6="",1,$L6),Q$4<=IF($M6="",12,$M6)),$O6,0) -> 22058.667 | R6: =IF(AND(R$4>=IF($L6="",1,$L6),R$4<=IF($M6="",12,$M6)),$O6,0) -> 22058.667 | S6: =IF(AND(S$4>=IF($L6="",1,$L6),S$4<=IF($M6="",12,$M6)),$O6,0) -> 22058.667 | T6: =IF(AND(T$4>=IF($L6="",1,$L6),T$4<=IF($M6="",12,$M6)),$O6,0) -> 22058.667 | U6: =IF(AND(U$4>=IF($L6="",1,$L6),U$4<=IF($M6="",12,$M6)),$O6,0) -> 22058.667 | V6: =IF(AND(V$4>=IF($L6="",1,$L6),V$4<=IF($M6="",12,$M6)),$O6,0) -> 22058.667 | W6: =IF(AND(W$4>=IF($L6="",1,$L6),W$4<=IF($M6="",12,$M6)),$O6,0) -> 22058.667 | ... AA6: =IF(AND(AA$4>=IF($L6="",1,$L6),AA$4<=IF($M6="",12,$M6)),$O6,0) -> 22058.667 | AB6: =SUM(P6:AA6) -> 264704
A7: Hubspot | B7: Sales | C7: XERO+BUDGET | D7: STEADY | E7: 0.3501 | F7: 666.76 | G7: =IFERROR(IF($F7>0,MAX(0,INDEX('XERO ACTUALS'!$T$5:$T$132,MATCH($A7,'XERO ACTUALS'!$A$5:$A$132,0))-$F7),INDEX('XERO ACTUALS'!$T$5:$T$132,MATCH($A7,'XERO ACTUALS'!$A$5:$A$132,0)))*IF($E7="",1,$E7),"") -> 1145.9718 | H7: 1070.19 | I7: XERO | K7: 0 | L7: 1 | M7: 12 | N7: Y | O7: =IF($N7="N",0,IF($A7="",0,(IF($J7<>"",$J7,IF($I7="BUDGET",IF($H7="",0,$H7),IF($G7="",0,$G7))))*(1+IF($K7="",0,$K7)))) -> 1145.9718 | P7: =IF(AND(P$4>=IF($L7="",1,$L7),P$4<=IF($M7="",12,$M7)),$O7,0) -> 1145.9718 | Q7: =IF(AND(Q$4>=IF($L7="",1,$L7),Q$4<=IF($M7="",12,$M7)),$O7,0) -> 1145.9718 | R7: =IF(AND(R$4>=IF($L7="",1,$L7),R$4<=IF($M7="",12,$M7)),$O7,0) -> 1145.9718 | S7: =IF(AND(S$4>=IF($L7="",1,$L7),S$4<=IF($M7="",12,$M7)),$O7,0) -> 1145.9718 | T7: =IF(AND(T$4>=IF($L7="",1,$L7),T$4<=IF($M7="",12,$M7)),$O7,0) -> 1145.9718 | U7: =IF(AND(U$4>=IF($L7="",1,$L7),U$4<=IF($M7="",12,$M7)),$O7,0) -> 1145.9718 | V7: =IF(AND(V$4>=IF($L7="",1,$L7),V$4<=IF($M7="",12,$M7)),$O7,0) -> 1145.9718 | W7: =IF(AND(W$4>=IF($L7="",1,$L7),W$4<=IF($M7="",12,$M7)),$O7,0) -> 1145.9718 | ... AA7: =IF(AND(AA$4>=IF($L7="",1,$L7),AA$4<=IF($M7="",12,$M7)),$O7,0) -> 1145.9718 | AB7: =SUM(P7:AA7) -> 13751.662
A8: Gong.io Inc | B8: Sales | C8: XERO+BUDGET | D8: STEADY | E8: 1 | F8: 2299.77 | G8: =IFERROR(IF($F8>0,MAX(0,INDEX('XERO ACTUALS'!$T$5:$T$132,MATCH($A8,'XERO ACTUALS'!$A$5:$A$132,0))-$F8),INDEX('XERO ACTUALS'!$T$5:$T$132,MATCH($A8,'XERO ACTUALS'!$A$5:$A$132,0)))*IF($E8="",1,$E8),"") -> 1008.24 | H8: 1009.23 | I8: XERO | K8: 0 | L8: 1 | M8: 12 | N8: Y | O8: =IF($N8="N",0,IF($A8="",0,(IF($J8<>"",$J8,IF($I8="BUDGET",IF($H8="",0,$H8),IF($G8="",0,$G8))))*(1+IF($K8="",0,$K8)))) -> 1008.24 | P8: =IF(AND(P$4>=IF($L8="",1,$L8),P$4<=IF($M8="",12,$M8)),$O8,0) -> 1008.24 | Q8: =IF(AND(Q$4>=IF($L8="",1,$L8),Q$4<=IF($M8="",12,$M8)),$O8,0) -> 1008.24 | R8: =IF(AND(R$4>=IF($L8="",1,$L8),R$4<=IF($M8="",12,$M8)),$O8,0) -> 1008.24 | S8: =IF(AND(S$4>=IF($L8="",1,$L8),S$4<=IF($M8="",12,$M8)),$O8,0) -> 1008.24 | T8: =IF(AND(T$4>=IF($L8="",1,$L8),T$4<=IF($M8="",12,$M8)),$O8,0) -> 1008.24 | U8: =IF(AND(U$4>=IF($L8="",1,$L8),U$4<=IF($M8="",12,$M8)),$O8,0) -> 1008.24 | V8: =IF(AND(V$4>=IF($L8="",1,$L8),V$4<=IF($M8="",12,$M8)),$O8,0) -> 1008.24 | W8: =IF(AND(W$4>=IF($L8="",1,$L8),W$4<=IF($M8="",12,$M8)),$O8,0) -> 1008.24 | ... AA8: =IF(AND(AA$4>=IF($L8="",1,$L8),AA$4<=IF($M8="",12,$M8)),$O8,0) -> 1008.24 | AB8: =SUM(P8:AA8) -> 12098.88
A9: Zoom | B9: Sales | C9: XERO+BUDGET | D9: STEADY | E9: 0.5505 | F9: 517.68 | G9: =IFERROR(IF($F9>0,MAX(0,INDEX('XERO ACTUALS'!$T$5:$T$132,MATCH($A9,'XERO ACTUALS'!$A$5:$A$132,0))-$F9),INDEX('XERO ACTUALS'!$T$5:$T$132,MATCH($A9,'XERO ACTUALS'!$A$5:$A$132,0)))*IF($E9="",1,$E9),"") -> 356.76621 | H9: 309.88 | I9: XERO | K9: 0 | L9: 1 | M9: 12 | N9: Y | O9: =IF($N9="N",0,IF($A9="",0,(IF($J9<>"",$J9,IF($I9="BUDGET",IF($H9="",0,$H9),IF($G9="",0,$G9))))*(1+IF($K9="",0,$K9)))) -> 356.76621 | P9: =IF(AND(P$4>=IF($L9="",1,$L9),P$4<=IF($M9="",12,$M9)),$O9,0) -> 356.76621 | Q9: =IF(AND(Q$4>=IF($L9="",1,$L9),Q$4<=IF($M9="",12,$M9)),$O9,0) -> 356.76621 | R9: =IF(AND(R$4>=IF($L9="",1,$L9),R$4<=IF($M9="",12,$M9)),$O9,0) -> 356.76621 | S9: =IF(AND(S$4>=IF($L9="",1,$L9),S$4<=IF($M9="",12,$M9)),$O9,0) -> 356.76621 | T9: =IF(AND(T$4>=IF($L9="",1,$L9),T$4<=IF($M9="",12,$M9)),$O9,0) -> 356.76621 | U9: =IF(AND(U$4>=IF($L9="",1,$L9),U$4<=IF($M9="",12,$M9)),$O9,0) -> 356.76621 | V9: =IF(AND(V$4>=IF($L9="",1,$L9),V$4<=IF($M9="",12,$M9)),$O9,0) -> 356.76621 | W9: =IF(AND(W$4>=IF($L9="",1,$L9),W$4<=IF($M9="",12,$M9)),$O9,0) -> 356.76621 | ... AA9: =IF(AND(AA$4>=IF($L9="",1,$L9),AA$4<=IF($M9="",12,$M9)),$O9,0) -> 356.76621 | AB9: =SUM(P9:AA9) -> 4281.1945
A10: Hilton Garden Inn | B10: Sales | C10: XERO ONLY | D10: NEW | E10: 1 | G10: =IFERROR(IF($F10>0,MAX(0,INDEX('XERO ACTUALS'!$T$5:$T$132,MATCH($A10,'XERO ACTUALS'!$A$5:$A$132,0))-$F10),INDEX('XERO ACTUALS'!$T$5:$T$132,MATCH($A10,'XERO ACTUALS'!$A$5:$A$132,0)))*IF($E10="",1,$E10),"") -> 274.8 | I10: XERO | K10: 0 | L10: 1 | M10: 12 | N10: Y | O10: =IF($N10="N",0,IF($A10="",0,(IF($J10<>"",$J10,IF($I10="BUDGET",IF($H10="",0,$H10),IF($G10="",0,$G10))))*(1+IF($K10="",0,$K10)))) -> 274.8 | P10: =IF(AND(P$4>=IF($L10="",1,$L10),P$4<=IF($M10="",12,$M10)),$O10,0) -> 274.8 | Q10: =IF(AND(Q$4>=IF($L10="",1,$L10),Q$4<=IF($M10="",12,$M10)),$O10,0) -> 274.8 | R10: =IF(AND(R$4>=IF($L10="",1,$L10),R$4<=IF($M10="",12,$M10)),$O10,0) -> 274.8 | S10: =IF(AND(S$4>=IF($L10="",1,$L10),S$4<=IF($M10="",12,$M10)),$O10,0) -> 274.8 | T10: =IF(AND(T$4>=IF($L10="",1,$L10),T$4<=IF($M10="",12,$M10)),$O10,0) -> 274.8 | U10: =IF(AND(U$4>=IF($L10="",1,$L10),U$4<=IF($M10="",12,$M10)),$O10,0) -> 274.8 | V10: =IF(AND(V$4>=IF($L10="",1,$L10),V$4<=IF($M10="",12,$M10)),$O10,0) -> 274.8 | W10: =IF(AND(W$4>=IF($L10="",1,$L10),W$4<=IF($M10="",12,$M10)),$O10,0) -> 274.8 | ... AA10: =IF(AND(AA$4>=IF($L10="",1,$L10),AA$4<=IF($M10="",12,$M10)),$O10,0) -> 274.8 | AB10: =SUM(P10:AA10) -> 3297.6
A11: Adobe | B11: Sales | C11: XERO+BUDGET | D11: STEADY | E11: 0.1234 | G11: =IFERROR(IF($F11>0,MAX(0,INDEX('XERO ACTUALS'!$T$5:$T$132,MATCH($A11,'XERO ACTUALS'!$A$5:$A$132,0))-$F11),INDEX('XERO ACTUALS'!$T$5:$T$132,MATCH($A11,'XERO ACTUALS'!$A$5:$A$132,0)))*IF($E11="",1,$E11),"") -> 36.173476 | H11: 21.39 | I11: XERO | K11: 0 | L11: 1 | M11: 12 | N11: Y | O11: =IF($N11="N",0,IF($A11="",0,(IF($J11<>"",$J11,IF($I11="BUDGET",IF($H11="",0,$H11),IF($G11="",0,$G11))))*(1+IF($K11="",0,$K11)))) -> 36.173476 | P11: =IF(AND(P$4>=IF($L11="",1,$L11),P$4<=IF($M11="",12,$M11)),$O11,0) -> 36.173476 | Q11: =IF(AND(Q$4>=IF($L11="",1,$L11),Q$4<=IF($M11="",12,$M11)),$O11,0) -> 36.173476 | R11: =IF(AND(R$4>=IF($L11="",1,$L11),R$4<=IF($M11="",12,$M11)),$O11,0) -> 36.173476 | S11: =IF(AND(S$4>=IF($L11="",1,$L11),S$4<=IF($M11="",12,$M11)),$O11,0) -> 36.173476 | T11: =IF(AND(T$4>=IF($L11="",1,$L11),T$4<=IF($M11="",12,$M11)),$O11,0) -> 36.173476 | U11: =IF(AND(U$4>=IF($L11="",1,$L11),U$4<=IF($M11="",12,$M11)),$O11,0) -> 36.173476 | V11: =IF(AND(V$4>=IF($L11="",1,$L11),V$4<=IF($M11="",12,$M11)),$O11,0) -> 36.173476 | W11: =IF(AND(W$4>=IF($L11="",1,$L11),W$4<=IF($M11="",12,$M11)),$O11,0) -> 36.173476 | ... AA11: =IF(AND(AA$4>=IF($L11="",1,$L11),AA$4<=IF($M11="",12,$M11)),$O11,0) -> 36.173476 | AB11: =SUM(P11:AA11) -> 434.08171
A12: Netvendor.com | B12: Sales | C12: BUDGET ONLY | D12: NOT IN XERO 2026 | H12: 9.92 | I12: BUDGET | K12: 0 | L12: 1 | M12: 12 | N12: N | O12: =IF($N12="N",0,IF($A12="",0,(IF($J12<>"",$J12,IF($I12="BUDGET",IF($H12="",0,$H12),IF($G12="",0,$G12))))*(1+IF($K12="",0,$K12)))) -> 0 | P12: =IF(AND(P$4>=IF($L12="",1,$L12),P$4<=IF($M12="",12,$M12)),$O12,0) -> 0 | Q12: =IF(AND(Q$4>=IF($L12="",1,$L12),Q$4<=IF($M12="",12,$M12)),$O12,0) -> 0 | R12: =IF(AND(R$4>=IF($L12="",1,$L12),R$4<=IF($M12="",12,$M12)),$O12,0) -> 0 | S12: =IF(AND(S$4>=IF($L12="",1,$L12),S$4<=IF($M12="",12,$M12)),$O12,0) -> 0 | T12: =IF(AND(T$4>=IF($L12="",1,$L12),T$4<=IF($M12="",12,$M12)),$O12,0) -> 0 | U12: =IF(AND(U$4>=IF($L12="",1,$L12),U$4<=IF($M12="",12,$M12)),$O12,0) -> 0 | V12: =IF(AND(V$4>=IF($L12="",1,$L12),V$4<=IF($M12="",12,$M12)),$O12,0) -> 0 | W12: =IF(AND(W$4>=IF($L12="",1,$L12),W$4<=IF($M12="",12,$M12)),$O12,0) -> 0 | ... AA12: =IF(AND(AA$4>=IF($L12="",1,$L12),AA$4<=IF($M12="",12,$M12)),$O12,0) -> 0 | AB12: =SUM(P12:AA12) -> 0
A13: Vendorply.com | B13: Sales | C13: BUDGET ONLY | D13: NOT IN XERO 2026 | H13: 9.92 | I13: BUDGET | K13: 0 | L13: 1 | M13: 12 | N13: N | O13: =IF($N13="N",0,IF($A13="",0,(IF($J13<>"",$J13,IF($I13="BUDGET",IF($H13="",0,$H13),IF($G13="",0,$G13))))*(1+IF($K13="",0,$K13)))) -> 0 | P13: =IF(AND(P$4>=IF($L13="",1,$L13),P$4<=IF($M13="",12,$M13)),$O13,0) -> 0 | Q13: =IF(AND(Q$4>=IF($L13="",1,$L13),Q$4<=IF($M13="",12,$M13)),$O13,0) -> 0 | R13: =IF(AND(R$4>=IF($L13="",1,$L13),R$4<=IF($M13="",12,$M13)),$O13,0) -> 0 | S13: =IF(AND(S$4>=IF($L13="",1,$L13),S$4<=IF($M13="",12,$M13)),$O13,0) -> 0 | T13: =IF(AND(T$4>=IF($L13="",1,$L13),T$4<=IF($M13="",12,$M13)),$O13,0) -> 0 | U13: =IF(AND(U$4>=IF($L13="",1,$L13),U$4<=IF($M13="",12,$M13)),$O13,0) -> 0 | V13: =IF(AND(V$4>=IF($L13="",1,$L13),V$4<=IF($M13="",12,$M13)),$O13,0) -> 0 | W13: =IF(AND(W$4>=IF($L13="",1,$L13),W$4<=IF($M13="",12,$M13)),$O13,0) -> 0 | ... AA13: =IF(AND(AA$4>=IF($L13="",1,$L13),AA$4<=IF($M13="",12,$M13)),$O13,0) -> 0 | AB13: =SUM(P13:AA13) -> 0
A14: Realpage Vendor | B14: Sales | C14: BUDGET ONLY | D14: NOT IN XERO 2026 | H14: 9.08 | I14: BUDGET | K14: 0 | L14: 1 | M14: 12 | N14: N | O14: =IF($N14="N",0,IF($A14="",0,(IF($J14<>"",$J14,IF($I14="BUDGET",IF($H14="",0,$H14),IF($G14="",0,$G14))))*(1+IF($K14="",0,$K14)))) -> 0 | P14: =IF(AND(P$4>=IF($L14="",1,$L14),P$4<=IF($M14="",12,$M14)),$O14,0) -> 0 | Q14: =IF(AND(Q$4>=IF($L14="",1,$L14),Q$4<=IF($M14="",12,$M14)),$O14,0) -> 0 | R14: =IF(AND(R$4>=IF($L14="",1,$L14),R$4<=IF($M14="",12,$M14)),$O14,0) -> 0 | S14: =IF(AND(S$4>=IF($L14="",1,$L14),S$4<=IF($M14="",12,$M14)),$O14,0) -> 0 | T14: =IF(AND(T$4>=IF($L14="",1,$L14),T$4<=IF($M14="",12,$M14)),$O14,0) -> 0 | U14: =IF(AND(U$4>=IF($L14="",1,$L14),U$4<=IF($M14="",12,$M14)),$O14,0) -> 0 | V14: =IF(AND(V$4>=IF($L14="",1,$L14),V$4<=IF($M14="",12,$M14)),$O14,0) -> 0 | W14: =IF(AND(W$4>=IF($L14="",1,$L14),W$4<=IF($M14="",12,$M14)),$O14,0) -> 0 | ... AA14: =IF(AND(AA$4>=IF($L14="",1,$L14),AA$4<=IF($M14="",12,$M14)),$O14,0) -> 0 | AB14: =SUM(P14:AA14) -> 0
A15: Vendor Shield | B15: Sales | C15: BUDGET ONLY | D15: NOT IN XERO 2026 | H15: 8.33 | I15: BUDGET | K15: 0 | L15: 1 | M15: 12 | N15: N | O15: =IF($N15="N",0,IF($A15="",0,(IF($J15<>"",$J15,IF($I15="BUDGET",IF($H15="",0,$H15),IF($G15="",0,$G15))))*(1+IF($K15="",0,$K15)))) -> 0 | P15: =IF(AND(P$4>=IF($L15="",1,$L15),P$4<=IF($M15="",12,$M15)),$O15,0) -> 0 | Q15: =IF(AND(Q$4>=IF($L15="",1,$L15),Q$4<=IF($M15="",12,$M15)),$O15,0) -> 0 | R15: =IF(AND(R$4>=IF($L15="",1,$L15),R$4<=IF($M15="",12,$M15)),$O15,0) -> 0 | S15: =IF(AND(S$4>=IF($L15="",1,$L15),S$4<=IF($M15="",12,$M15)),$O15,0) -> 0 | T15: =IF(AND(T$4>=IF($L15="",1,$L15),T$4<=IF($M15="",12,$M15)),$O15,0) -> 0 | U15: =IF(AND(U$4>=IF($L15="",1,$L15),U$4<=IF($M15="",12,$M15)),$O15,0) -> 0 | V15: =IF(AND(V$4>=IF($L15="",1,$L15),V$4<=IF($M15="",12,$M15)),$O15,0) -> 0 | W15: =IF(AND(W$4>=IF($L15="",1,$L15),W$4<=IF($M15="",12,$M15)),$O15,0) -> 0 | ... AA15: =IF(AND(AA$4>=IF($L15="",1,$L15),AA$4<=IF($M15="",12,$M15)),$O15,0) -> 0 | AB15: =SUM(P15:AA15) -> 0
A16: Commonwealth of Virginia | B16: Sales | C16: BUDGET ONLY | D16: NOT IN XERO 2026 | H16: 7.94 | I16: BUDGET | K16: 0 | L16: 1 | M16: 12 | N16: N | O16: =IF($N16="N",0,IF($A16="",0,(IF($J16<>"",$J16,IF($I16="BUDGET",IF($H16="",0,$H16),IF($G16="",0,$G16))))*(1+IF($K16="",0,$K16)))) -> 0 | P16: =IF(AND(P$4>=IF($L16="",1,$L16),P$4<=IF($M16="",12,$M16)),$O16,0) -> 0 | Q16: =IF(AND(Q$4>=IF($L16="",1,$L16),Q$4<=IF($M16="",12,$M16)),$O16,0) -> 0 | R16: =IF(AND(R$4>=IF($L16="",1,$L16),R$4<=IF($M16="",12,$M16)),$O16,0) -> 0 | S16: =IF(AND(S$4>=IF($L16="",1,$L16),S$4<=IF($M16="",12,$M16)),$O16,0) -> 0 | T16: =IF(AND(T$4>=IF($L16="",1,$L16),T$4<=IF($M16="",12,$M16)),$O16,0) -> 0 | U16: =IF(AND(U$4>=IF($L16="",1,$L16),U$4<=IF($M16="",12,$M16)),$O16,0) -> 0 | V16: =IF(AND(V$4>=IF($L16="",1,$L16),V$4<=IF($M16="",12,$M16)),$O16,0) -> 0 | W16: =IF(AND(W$4>=IF($L16="",1,$L16),W$4<=IF($M16="",12,$M16)),$O16,0) -> 0 | ... AA16: =IF(AND(AA$4>=IF($L16="",1,$L16),AA$4<=IF($M16="",12,$M16)),$O16,0) -> 0 | AB16: =SUM(P16:AA16) -> 0
A17: JB Sales OnDemand | B17: Sales | C17: BUDGET ONLY | D17: NOT IN XERO 2026 | H17: 0 | I17: BUDGET | K17: 0 | L17: 1 | M17: 12 | N17: N | O17: =IF($N17="N",0,IF($A17="",0,(IF($J17<>"",$J17,IF($I17="BUDGET",IF($H17="",0,$H17),IF($G17="",0,$G17))))*(1+IF($K17="",0,$K17)))) -> 0 | P17: =IF(AND(P$4>=IF($L17="",1,$L17),P$4<=IF($M17="",12,$M17)),$O17,0) -> 0 | Q17: =IF(AND(Q$4>=IF($L17="",1,$L17),Q$4<=IF($M17="",12,$M17)),$O17,0) -> 0 | R17: =IF(AND(R$4>=IF($L17="",1,$L17),R$4<=IF($M17="",12,$M17)),$O17,0) -> 0 | S17: =IF(AND(S$4>=IF($L17="",1,$L17),S$4<=IF($M17="",12,$M17)),$O17,0) -> 0 | T17: =IF(AND(T$4>=IF($L17="",1,$L17),T$4<=IF($M17="",12,$M17)),$O17,0) -> 0 | U17: =IF(AND(U$4>=IF($L17="",1,$L17),U$4<=IF($M17="",12,$M17)),$O17,0) -> 0 | V17: =IF(AND(V$4>=IF($L17="",1,$L17),V$4<=IF($M17="",12,$M17)),$O17,0) -> 0 | W17: =IF(AND(W$4>=IF($L17="",1,$L17),W$4<=IF($M17="",12,$M17)),$O17,0) -> 0 | ... AA17: =IF(AND(AA$4>=IF($L17="",1,$L17),AA$4<=IF($M17="",12,$M17)),$O17,0) -> 0 | AB17: =SUM(P17:AA17) -> 0
A18: Google Advertising | B18: Marketing | C18: XERO+BUDGET | D18: STEADY | E18: 1 | G18: =IFERROR(IF($F18>0,MAX(0,INDEX('XERO ACTUALS'!$T$5:$T$132,MATCH($A18,'XERO ACTUALS'!$A$5:$A$132,0))-$F18),INDEX('XERO ACTUALS'!$T$5:$T$132,MATCH($A18,'XERO ACTUALS'!$A$5:$A$132,0)))*IF($E18="",1,$E18),"") -> 74997.053 | H18: 95000 | I18: XERO | K18: 0 | L18: 1 | M18: 12 | N18: Y | O18: =IF($N18="N",0,IF($A18="",0,(IF($J18<>"",$J18,IF($I18="BUDGET",IF($H18="",0,$H18),IF($G18="",0,$G18))))*(1+IF($K18="",0,$K18)))) -> 74997.053 | P18: =IF(AND(P$4>=IF($L18="",1,$L18),P$4<=IF($M18="",12,$M18)),$O18,0) -> 74997.053 | Q18: =IF(AND(Q$4>=IF($L18="",1,$L18),Q$4<=IF($M18="",12,$M18)),$O18,0) -> 74997.053 | R18: =IF(AND(R$4>=IF($L18="",1,$L18),R$4<=IF($M18="",12,$M18)),$O18,0) -> 74997.053 | S18: =IF(AND(S$4>=IF($L18="",1,$L18),S$4<=IF($M18="",12,$M18)),$O18,0) -> 74997.053 | T18: =IF(AND(T$4>=IF($L18="",1,$L18),T$4<=IF($M18="",12,$M18)),$O18,0) -> 74997.053 | U18: =IF(AND(U$4>=IF($L18="",1,$L18),U$4<=IF($M18="",12,$M18)),$O18,0) -> 74997.053 | V18: =IF(AND(V$4>=IF($L18="",1,$L18),V$4<=IF($M18="",12,$M18)),$O18,0) -> 74997.053 | W18: =IF(AND(W$4>=IF($L18="",1,$L18),W$4<=IF($M18="",12,$M18)),$O18,0) -> 74997.053 | ... AA18: =IF(AND(AA$4>=IF($L18="",1,$L18),AA$4<=IF($M18="",12,$M18)),$O18,0) -> 74997.053 | AB18: =SUM(P18:AA18) -> 899964.64
A19: Bing | B19: Marketing | C19: XERO ONLY | D19: STEADY | E19: 1 | G19: =IFERROR(IF($F19>0,MAX(0,INDEX('XERO ACTUALS'!$T$5:$T$132,MATCH($A19,'XERO ACTUALS'!$A$5:$A$132,0))-$F19),INDEX('XERO ACTUALS'!$T$5:$T$132,MATCH($A19,'XERO ACTUALS'!$A$5:$A$132,0)))*IF($E19="",1,$E19),"") -> 15894.383 | I19: XERO | K19: 0 | L19: 1 | M19: 12 | N19: Y | O19: =IF($N19="N",0,IF($A19="",0,(IF($J19<>"",$J19,IF($I19="BUDGET",IF($H19="",0,$H19),IF($G19="",0,$G19))))*(1+IF($K19="",0,$K19)))) -> 15894.383 | P19: =IF(AND(P$4>=IF($L19="",1,$L19),P$4<=IF($M19="",12,$M19)),$O19,0) -> 15894.383 | Q19: =IF(AND(Q$4>=IF($L19="",1,$L19),Q$4<=IF($M19="",12,$M19)),$O19,0) -> 15894.383 | R19: =IF(AND(R$4>=IF($L19="",1,$L19),R$4<=IF($M19="",12,$M19)),$O19,0) -> 15894.383 | S19: =IF(AND(S$4>=IF($L19="",1,$L19),S$4<=IF($M19="",12,$M19)),$O19,0) -> 15894.383 | T19: =IF(AND(T$4>=IF($L19="",1,$L19),T$4<=IF($M19="",12,$M19)),$O19,0) -> 15894.383 | U19: =IF(AND(U$4>=IF($L19="",1,$L19),U$4<=IF($M19="",12,$M19)),$O19,0) -> 15894.383 | V19: =IF(AND(V$4>=IF($L19="",1,$L19),V$4<=IF($M19="",12,$M19)),$O19,0) -> 15894.383 | W19: =IF(AND(W$4>=IF($L19="",1,$L19),W$4<=IF($M19="",12,$M19)),$O19,0) -> 15894.383 | ... AA19: =IF(AND(AA$4>=IF($L19="",1,$L19),AA$4<=IF($M19="",12,$M19)),$O19,0) -> 15894.383 | AB19: =SUM(P19:AA19) -> 190732.6
A20: Dillon Jones LLC | B20: Marketing | C20: XERO+BUDGET | D20: STEADY | E20: 1 | G20: =IFERROR(IF($F20>0,MAX(0,INDEX('XERO ACTUALS'!$T$5:$T$132,MATCH($A20,'XERO ACTUALS'!$A$5:$A$132,0))-$F20),INDEX('XERO ACTUALS'!$T$5:$T$132,MATCH($A20,'XERO ACTUALS'!$A$5:$A$132,0)))*IF($E20="",1,$E20),"") -> 7000 | H20: 1000 | I20: XERO | K20: 0 | L20: 1 | M20: 12 | N20: Y | O20: =IF($N20="N",0,IF($A20="",0,(IF($J20<>"",$J20,IF($I20="BUDGET",IF($H20="",0,$H20),IF($G20="",0,$G20))))*(1+IF($K20="",0,$K20)))) -> 7000 | P20: =IF(AND(P$4>=IF($L20="",1,$L20),P$4<=IF($M20="",12,$M20)),$O20,0) -> 7000 | Q20: =IF(AND(Q$4>=IF($L20="",1,$L20),Q$4<=IF($M20="",12,$M20)),$O20,0) -> 7000 | R20: =IF(AND(R$4>=IF($L20="",1,$L20),R$4<=IF($M20="",12,$M20)),$O20,0) -> 7000 | S20: =IF(AND(S$4>=IF($L20="",1,$L20),S$4<=IF($M20="",12,$M20)),$O20,0) -> 7000 | T20: =IF(AND(T$4>=IF($L20="",1,$L20),T$4<=IF($M20="",12,$M20)),$O20,0) -> 7000 | U20: =IF(AND(U$4>=IF($L20="",1,$L20),U$4<=IF($M20="",12,$M20)),$O20,0) -> 7000 | V20: =IF(AND(V$4>=IF($L20="",1,$L20),V$4<=IF($M20="",12,$M20)),$O20,0) -> 7000 | W20: =IF(AND(W$4>=IF($L20="",1,$L20),W$4<=IF($M20="",12,$M20)),$O20,0) -> 7000 | ... AA20: =IF(AND(AA$4>=IF($L20="",1,$L20),AA$4<=IF($M20="",12,$M20)),$O20,0) -> 7000 | AB20: =SUM(P20:AA20) -> 84000
A21: Hubspot | B21: Marketing | C21: XERO+BUDGET | D21: STEADY | E21: 0.6499 | F21: 666.76 | G21: =IFERROR(IF($F21>0,MAX(0,INDEX('XERO ACTUALS'!$T$5:$T$132,MATCH($A21,'XERO ACTUALS'!$A$5:$A$132,0))-$F21),INDEX('XERO ACTUALS'!$T$5:$T$132,MATCH($A21,'XERO ACTUALS'!$A$5:$A$132,0)))*IF($E21="",1,$E21),"") -> 2127.2982 | H21: 1986.98 | I21: XERO | K21: 0 | L21: 1 | M21: 12 | N21: Y | O21: =IF($N21="N",0,IF($A21="",0,(IF($J21<>"",$J21,IF($I21="BUDGET",IF($H21="",0,$H21),IF($G21="",0,$G21))))*(1+IF($K21="",0,$K21)))) -> 2127.2982 | P21: =IF(AND(P$4>=IF($L21="",1,$L21),P$4<=IF($M21="",12,$M21)),$O21,0) -> 2127.2982 | Q21: =IF(AND(Q$4>=IF($L21="",1,$L21),Q$4<=IF($M21="",12,$M21)),$O21,0) -> 2127.2982 | R21: =IF(AND(R$4>=IF($L21="",1,$L21),R$4<=IF($M21="",12,$M21)),$O21,0) -> 2127.2982 | S21: =IF(AND(S$4>=IF($L21="",1,$L21),S$4<=IF($M21="",12,$M21)),$O21,0) -> 2127.2982 | T21: =IF(AND(T$4>=IF($L21="",1,$L21),T$4<=IF($M21="",12,$M21)),$O21,0) -> 2127.2982 | U21: =IF(AND(U$4>=IF($L21="",1,$L21),U$4<=IF($M21="",12,$M21)),$O21,0) -> 2127.2982 | V21: =IF(AND(V$4>=IF($L21="",1,$L21),V$4<=IF($M21="",12,$M21)),$O21,0) -> 2127.2982 | W21: =IF(AND(W$4>=IF($L21="",1,$L21),W$4<=IF($M21="",12,$M21)),$O21,0) -> 2127.2982 | ... AA21: =IF(AND(AA$4>=IF($L21="",1,$L21),AA$4<=IF($M21="",12,$M21)),$O21,0) -> 2127.2982 | AB21: =SUM(P21:AA21) -> 25527.578
A22: LinkedIn | B22: Marketing | C22: XERO ONLY | D22: STEADY | E22: 1 | G22: =IFERROR(IF($F22>0,MAX(0,INDEX('XERO ACTUALS'!$T$5:$T$132,MATCH($A22,'XERO ACTUALS'!$A$5:$A$132,0))-$F22),INDEX('XERO ACTUALS'!$T$5:$T$132,MATCH($A22,'XERO ACTUALS'!$A$5:$A$132,0)))*IF($E22="",1,$E22),"") -> 746.05 | I22: XERO | K22: 0 | L22: 1 | M22: 12 | N22: Y | O22: =IF($N22="N",0,IF($A22="",0,(IF($J22<>"",$J22,IF($I22="BUDGET",IF($H22="",0,$H22),IF($G22="",0,$G22))))*(1+IF($K22="",0,$K22)))) -> 746.05 | P22: =IF(AND(P$4>=IF($L22="",1,$L22),P$4<=IF($M22="",12,$M22)),$O22,0) -> 746.05 | Q22: =IF(AND(Q$4>=IF($L22="",1,$L22),Q$4<=IF($M22="",12,$M22)),$O22,0) -> 746.05 | R22: =IF(AND(R$4>=IF($L22="",1,$L22),R$4<=IF($M22="",12,$M22)),$O22,0) -> 746.05 | S22: =IF(AND(S$4>=IF($L22="",1,$L22),S$4<=IF($M22="",12,$M22)),$O22,0) -> 746.05 | T22: =IF(AND(T$4>=IF($L22="",1,$L22),T$4<=IF($M22="",12,$M22)),$O22,0) -> 746.05 | U22: =IF(AND(U$4>=IF($L22="",1,$L22),U$4<=IF($M22="",12,$M22)),$O22,0) -> 746.05 | V22: =IF(AND(V$4>=IF($L22="",1,$L22),V$4<=IF($M22="",12,$M22)),$O22,0) -> 746.05 | W22: =IF(AND(W$4>=IF($L22="",1,$L22),W$4<=IF($M22="",12,$M22)),$O22,0) -> 746.05 | ... AA22: =IF(AND(AA$4>=IF($L22="",1,$L22),AA$4<=IF($M22="",12,$M22)),$O22,0) -> 746.05 | AB22: =SUM(P22:AA22) -> 8952.6
A23: CallRail | B23: Marketing | C23: XERO+BUDGET | D23: GROWING | E23: 1 | G23: =IFERROR(IF($F23>0,MAX(0,INDEX('XERO ACTUALS'!$T$5:$T$132,MATCH($A23,'XERO ACTUALS'!$A$5:$A$132,0))-$F23),INDEX('XERO ACTUALS'!$T$5:$T$132,MATCH($A23,'XERO ACTUALS'!$A$5:$A$132,0)))*IF($E23="",1,$E23),"") -> 328.33333 | H23: 235 | I23: XERO | K23: 0 | L23: 1 | M23: 12 | N23: Y | O23: =IF($N23="N",0,IF($A23="",0,(IF($J23<>"",$J23,IF($I23="BUDGET",IF($H23="",0,$H23),IF($G23="",0,$G23))))*(1+IF($K23="",0,$K23)))) -> 328.33333 | P23: =IF(AND(P$4>=IF($L23="",1,$L23),P$4<=IF($M23="",12,$M23)),$O23,0) -> 328.33333 | Q23: =IF(AND(Q$4>=IF($L23="",1,$L23),Q$4<=IF($M23="",12,$M23)),$O23,0) -> 328.33333 | R23: =IF(AND(R$4>=IF($L23="",1,$L23),R$4<=IF($M23="",12,$M23)),$O23,0) -> 328.33333 | S23: =IF(AND(S$4>=IF($L23="",1,$L23),S$4<=IF($M23="",12,$M23)),$O23,0) -> 328.33333 | T23: =IF(AND(T$4>=IF($L23="",1,$L23),T$4<=IF($M23="",12,$M23)),$O23,0) -> 328.33333 | U23: =IF(AND(U$4>=IF($L23="",1,$L23),U$4<=IF($M23="",12,$M23)),$O23,0) -> 328.33333 | V23: =IF(AND(V$4>=IF($L23="",1,$L23),V$4<=IF($M23="",12,$M23)),$O23,0) -> 328.33333 | W23: =IF(AND(W$4>=IF($L23="",1,$L23),W$4<=IF($M23="",12,$M23)),$O23,0) -> 328.33333 | ... AA23: =IF(AND(AA$4>=IF($L23="",1,$L23),AA$4<=IF($M23="",12,$M23)),$O23,0) -> 328.33333 | AB23: =SUM(P23:AA23) -> 3940
A24: Adobe | B24: Marketing | C24: XERO+BUDGET | D24: STEADY | E24: 0.8766 | G24: =IFERROR(IF($F24>0,MAX(0,INDEX('XERO ACTUALS'!$T$5:$T$132,MATCH($A24,'XERO ACTUALS'!$A$5:$A$132,0))-$F24),INDEX('XERO ACTUALS'!$T$5:$T$132,MATCH($A24,'XERO ACTUALS'!$A$5:$A$132,0)))*IF($E24="",1,$E24),"") -> 256.96652 | H24: 151.92 | I24: XERO | K24: 0 | L24: 1 | M24: 12 | N24: Y | O24: =IF($N24="N",0,IF($A24="",0,(IF($J24<>"",$J24,IF($I24="BUDGET",IF($H24="",0,$H24),IF($G24="",0,$G24))))*(1+IF($K24="",0,$K24)))) -> 256.96652 | P24: =IF(AND(P$4>=IF($L24="",1,$L24),P$4<=IF($M24="",12,$M24)),$O24,0) -> 256.96652 | Q24: =IF(AND(Q$4>=IF($L24="",1,$L24),Q$4<=IF($M24="",12,$M24)),$O24,0) -> 256.96652 | R24: =IF(AND(R$4>=IF($L24="",1,$L24),R$4<=IF($M24="",12,$M24)),$O24,0) -> 256.96652 | S24: =IF(AND(S$4>=IF($L24="",1,$L24),S$4<=IF($M24="",12,$M24)),$O24,0) -> 256.96652 | T24: =IF(AND(T$4>=IF($L24="",1,$L24),T$4<=IF($M24="",12,$M24)),$O24,0) -> 256.96652 | U24: =IF(AND(U$4>=IF($L24="",1,$L24),U$4<=IF($M24="",12,$M24)),$O24,0) -> 256.96652 | V24: =IF(AND(V$4>=IF($L24="",1,$L24),V$4<=IF($M24="",12,$M24)),$O24,0) -> 256.96652 | W24: =IF(AND(W$4>=IF($L24="",1,$L24),W$4<=IF($M24="",12,$M24)),$O24,0) -> 256.96652 | ... AA24: =IF(AND(AA$4>=IF($L24="",1,$L24),AA$4<=IF($M24="",12,$M24)),$O24,0) -> 256.96652 | AB24: =SUM(P24:AA24) -> 3083.5983
A25: Klevu | B25: Marketing | C25: XERO+BUDGET | D25: STEADY | E25: 1 | G25: =IFERROR(IF($F25>0,MAX(0,INDEX('XERO ACTUALS'!$T$5:$T$132,MATCH($A25,'XERO ACTUALS'!$A$5:$A$132,0))-$F25),INDEX('XERO ACTUALS'!$T$5:$T$132,MATCH($A25,'XERO ACTUALS'!$A$5:$A$132,0)))*IF($E25="",1,$E25),"") -> 236.19 | H25: 236.19 | I25: XERO | K25: 0 | L25: 1 | M25: 12 | N25: Y | O25: =IF($N25="N",0,IF($A25="",0,(IF($J25<>"",$J25,IF($I25="BUDGET",IF($H25="",0,$H25),IF($G25="",0,$G25))))*(1+IF($K25="",0,$K25)))) -> 236.19 | P25: =IF(AND(P$4>=IF($L25="",1,$L25),P$4<=IF($M25="",12,$M25)),$O25,0) -> 236.19 | Q25: =IF(AND(Q$4>=IF($L25="",1,$L25),Q$4<=IF($M25="",12,$M25)),$O25,0) -> 236.19 | R25: =IF(AND(R$4>=IF($L25="",1,$L25),R$4<=IF($M25="",12,$M25)),$O25,0) -> 236.19 | S25: =IF(AND(S$4>=IF($L25="",1,$L25),S$4<=IF($M25="",12,$M25)),$O25,0) -> 236.19 | T25: =IF(AND(T$4>=IF($L25="",1,$L25),T$4<=IF($M25="",12,$M25)),$O25,0) -> 236.19 | U25: =IF(AND(U$4>=IF($L25="",1,$L25),U$4<=IF($M25="",12,$M25)),$O25,0) -> 236.19 | V25: =IF(AND(V$4>=IF($L25="",1,$L25),V$4<=IF($M25="",12,$M25)),$O25,0) -> 236.19 | W25: =IF(AND(W$4>=IF($L25="",1,$L25),W$4<=IF($M25="",12,$M25)),$O25,0) -> 236.19 | ... AA25: =IF(AND(AA$4>=IF($L25="",1,$L25),AA$4<=IF($M25="",12,$M25)),$O25,0) -> 236.19 | AB25: =SUM(P25:AA25) -> 2834.28
A26: BirdEye Inc | B26: Marketing | C26: BUDGET ONLY | D26: NOT IN XERO 2026 | H26: 192.94 | I26: BUDGET | K26: 0 | L26: 1 | M26: 12 | N26: N | O26: =IF($N26="N",0,IF($A26="",0,(IF($J26<>"",$J26,IF($I26="BUDGET",IF($H26="",0,$H26),IF($G26="",0,$G26))))*(1+IF($K26="",0,$K26)))) -> 0 | P26: =IF(AND(P$4>=IF($L26="",1,$L26),P$4<=IF($M26="",12,$M26)),$O26,0) -> 0 | Q26: =IF(AND(Q$4>=IF($L26="",1,$L26),Q$4<=IF($M26="",12,$M26)),$O26,0) -> 0 | R26: =IF(AND(R$4>=IF($L26="",1,$L26),R$4<=IF($M26="",12,$M26)),$O26,0) -> 0 | S26: =IF(AND(S$4>=IF($L26="",1,$L26),S$4<=IF($M26="",12,$M26)),$O26,0) -> 0 | T26: =IF(AND(T$4>=IF($L26="",1,$L26),T$4<=IF($M26="",12,$M26)),$O26,0) -> 0 | U26: =IF(AND(U$4>=IF($L26="",1,$L26),U$4<=IF($M26="",12,$M26)),$O26,0) -> 0 | V26: =IF(AND(V$4>=IF($L26="",1,$L26),V$4<=IF($M26="",12,$M26)),$O26,0) -> 0 | W26: =IF(AND(W$4>=IF($L26="",1,$L26),W$4<=IF($M26="",12,$M26)),$O26,0) -> 0 | ... AA26: =IF(AND(AA$4>=IF($L26="",1,$L26),AA$4<=IF($M26="",12,$M26)),$O26,0) -> 0 | AB26: =SUM(P26:AA26) -> 0
A27: Shopper Approved | B27: Marketing | C27: XERO+BUDGET | D27: NEW | E27: 1 | G27: =IFERROR(IF($F27>0,MAX(0,INDEX('XERO ACTUALS'!$T$5:$T$132,MATCH($A27,'XERO ACTUALS'!$A$5:$A$132,0))-$F27),INDEX('XERO ACTUALS'!$T$5:$T$132,MATCH($A27,'XERO ACTUALS'!$A$5:$A$132,0)))*IF($E27="",1,$E27),"") -> 159.7 | H27: 26.62 | I27: XERO | K27: 0 | L27: 1 | M27: 12 | N27: Y | O27: =IF($N27="N",0,IF($A27="",0,(IF($J27<>"",$J27,IF($I27="BUDGET",IF($H27="",0,$H27),IF($G27="",0,$G27))))*(1+IF($K27="",0,$K27)))) -> 159.7 | P27: =IF(AND(P$4>=IF($L27="",1,$L27),P$4<=IF($M27="",12,$M27)),$O27,0) -> 159.7 | Q27: =IF(AND(Q$4>=IF($L27="",1,$L27),Q$4<=IF($M27="",12,$M27)),$O27,0) -> 159.7 | R27: =IF(AND(R$4>=IF($L27="",1,$L27),R$4<=IF($M27="",12,$M27)),$O27,0) -> 159.7 | S27: =IF(AND(S$4>=IF($L27="",1,$L27),S$4<=IF($M27="",12,$M27)),$O27,0) -> 159.7 | T27: =IF(AND(T$4>=IF($L27="",1,$L27),T$4<=IF($M27="",12,$M27)),$O27,0) -> 159.7 | U27: =IF(AND(U$4>=IF($L27="",1,$L27),U$4<=IF($M27="",12,$M27)),$O27,0) -> 159.7 | V27: =IF(AND(V$4>=IF($L27="",1,$L27),V$4<=IF($M27="",12,$M27)),$O27,0) -> 159.7 | W27: =IF(AND(W$4>=IF($L27="",1,$L27),W$4<=IF($M27="",12,$M27)),$O27,0) -> 159.7 | ... AA27: =IF(AND(AA$4>=IF($L27="",1,$L27),AA$4<=IF($M27="",12,$M27)),$O27,0) -> 159.7 | AB27: =SUM(P27:AA27) -> 1916.4
A28: Sticker Giant | B28: Marketing | C28: BUDGET ONLY | D28: NOT IN XERO 2026 | H28: 101.65 | I28: BUDGET | K28: 0 | L28: 1 | M28: 12 | N28: N | O28: =IF($N28="N",0,IF($A28="",0,(IF($J28<>"",$J28,IF($I28="BUDGET",IF($H28="",0,$H28),IF($G28="",0,$G28))))*(1+IF($K28="",0,$K28)))) -> 0 | P28: =IF(AND(P$4>=IF($L28="",1,$L28),P$4<=IF($M28="",12,$M28)),$O28,0) -> 0 | Q28: =IF(AND(Q$4>=IF($L28="",1,$L28),Q$4<=IF($M28="",12,$M28)),$O28,0) -> 0 | R28: =IF(AND(R$4>=IF($L28="",1,$L28),R$4<=IF($M28="",12,$M28)),$O28,0) -> 0 | S28: =IF(AND(S$4>=IF($L28="",1,$L28),S$4<=IF($M28="",12,$M28)),$O28,0) -> 0 | T28: =IF(AND(T$4>=IF($L28="",1,$L28),T$4<=IF($M28="",12,$M28)),$O28,0) -> 0 | U28: =IF(AND(U$4>=IF($L28="",1,$L28),U$4<=IF($M28="",12,$M28)),$O28,0) -> 0 | V28: =IF(AND(V$4>=IF($L28="",1,$L28),V$4<=IF($M28="",12,$M28)),$O28,0) -> 0 | W28: =IF(AND(W$4>=IF($L28="",1,$L28),W$4<=IF($M28="",12,$M28)),$O28,0) -> 0 | ... AA28: =IF(AND(AA$4>=IF($L28="",1,$L28),AA$4<=IF($M28="",12,$M28)),$O28,0) -> 0 | AB28: =SUM(P28:AA28) -> 0
A29: Apollo.io | B29: Marketing | C29: XERO+BUDGET | D29: STEADY | E29: 1 | G29: =IFERROR(IF($F29>0,MAX(0,INDEX('XERO ACTUALS'!$T$5:$T$132,MATCH($A29,'XERO ACTUALS'!$A$5:$A$132,0))-$F29),INDEX('XERO ACTUALS'!$T$5:$T$132,MATCH($A29,'XERO ACTUALS'!$A$5:$A$132,0)))*IF($E29="",1,$E29),"") -> 89 | H29: 59 | I29: XERO | K29: 0 | L29: 1 | M29: 12 | N29: Y | O29: =IF($N29="N",0,IF($A29="",0,(IF($J29<>"",$J29,IF($I29="BUDGET",IF($H29="",0,$H29),IF($G29="",0,$G29))))*(1+IF($K29="",0,$K29)))) -> 89 | P29: =IF(AND(P$4>=IF($L29="",1,$L29),P$4<=IF($M29="",12,$M29)),$O29,0) -> 89 | Q29: =IF(AND(Q$4>=IF($L29="",1,$L29),Q$4<=IF($M29="",12,$M29)),$O29,0) -> 89 | R29: =IF(AND(R$4>=IF($L29="",1,$L29),R$4<=IF($M29="",12,$M29)),$O29,0) -> 89 | S29: =IF(AND(S$4>=IF($L29="",1,$L29),S$4<=IF($M29="",12,$M29)),$O29,0) -> 89 | T29: =IF(AND(T$4>=IF($L29="",1,$L29),T$4<=IF($M29="",12,$M29)),$O29,0) -> 89 | U29: =IF(AND(U$4>=IF($L29="",1,$L29),U$4<=IF($M29="",12,$M29)),$O29,0) -> 89 | V29: =IF(AND(V$4>=IF($L29="",1,$L29),V$4<=IF($M29="",12,$M29)),$O29,0) -> 89 | W29: =IF(AND(W$4>=IF($L29="",1,$L29),W$4<=IF($M29="",12,$M29)),$O29,0) -> 89 | ... AA29: =IF(AND(AA$4>=IF($L29="",1,$L29),AA$4<=IF($M29="",12,$M29)),$O29,0) -> 89 | AB29: =SUM(P29:AA29) -> 1068
A30: Zoom | B30: Marketing | C30: XERO+BUDGET | D30: STEADY | E30: 0.1021 | F30: 517.68 | G30: =IFERROR(IF($F30>0,MAX(0,INDEX('XERO ACTUALS'!$T$5:$T$132,MATCH($A30,'XERO ACTUALS'!$A$5:$A$132,0))-$F30),INDEX('XERO ACTUALS'!$T$5:$T$132,MATCH($A30,'XERO ACTUALS'!$A$5:$A$132,0)))*IF($E30="",1,$E30),"") -> 66.168628 | H30: 57.5 | I30: XERO | K30: 0 | L30: 1 | M30: 12 | N30: Y | O30: =IF($N30="N",0,IF($A30="",0,(IF($J30<>"",$J30,IF($I30="BUDGET",IF($H30="",0,$H30),IF($G30="",0,$G30))))*(1+IF($K30="",0,$K30)))) -> 66.168628 | P30: =IF(AND(P$4>=IF($L30="",1,$L30),P$4<=IF($M30="",12,$M30)),$O30,0) -> 66.168628 | Q30: =IF(AND(Q$4>=IF($L30="",1,$L30),Q$4<=IF($M30="",12,$M30)),$O30,0) -> 66.168628 | R30: =IF(AND(R$4>=IF($L30="",1,$L30),R$4<=IF($M30="",12,$M30)),$O30,0) -> 66.168628 | S30: =IF(AND(S$4>=IF($L30="",1,$L30),S$4<=IF($M30="",12,$M30)),$O30,0) -> 66.168628 | T30: =IF(AND(T$4>=IF($L30="",1,$L30),T$4<=IF($M30="",12,$M30)),$O30,0) -> 66.168628 | U30: =IF(AND(U$4>=IF($L30="",1,$L30),U$4<=IF($M30="",12,$M30)),$O30,0) -> 66.168628 | V30: =IF(AND(V$4>=IF($L30="",1,$L30),V$4<=IF($M30="",12,$M30)),$O30,0) -> 66.168628 | W30: =IF(AND(W$4>=IF($L30="",1,$L30),W$4<=IF($M30="",12,$M30)),$O30,0) -> 66.168628 | ... AA30: =IF(AND(AA$4>=IF($L30="",1,$L30),AA$4<=IF($M30="",12,$M30)),$O30,0) -> 66.168628 | AB30: =SUM(P30:AA30) -> 794.02353
A31: Vimeo | B31: Marketing | C31: XERO+BUDGET | D31: ONE-TIME | E31: 1 | G31: =IFERROR(IF($F31>0,MAX(0,INDEX('XERO ACTUALS'!$T$5:$T$132,MATCH($A31,'XERO ACTUALS'!$A$5:$A$132,0))-$F31),INDEX('XERO ACTUALS'!$T$5:$T$132,MATCH($A31,'XERO ACTUALS'!$A$5:$A$132,0)))*IF($E31="",1,$E31),"") -> 51.970719 | H31: 33.25 | I31: XERO | K31: 0 | L31: 1 | M31: 12 | N31: N | O31: =IF($N31="N",0,IF($A31="",0,(IF($J31<>"",$J31,IF($I31="BUDGET",IF($H31="",0,$H31),IF($G31="",0,$G31))))*(1+IF($K31="",0,$K31)))) -> 0 | P31: =IF(AND(P$4>=IF($L31="",1,$L31),P$4<=IF($M31="",12,$M31)),$O31,0) -> 0 | Q31: =IF(AND(Q$4>=IF($L31="",1,$L31),Q$4<=IF($M31="",12,$M31)),$O31,0) -> 0 | R31: =IF(AND(R$4>=IF($L31="",1,$L31),R$4<=IF($M31="",12,$M31)),$O31,0) -> 0 | S31: =IF(AND(S$4>=IF($L31="",1,$L31),S$4<=IF($M31="",12,$M31)),$O31,0) -> 0 | T31: =IF(AND(T$4>=IF($L31="",1,$L31),T$4<=IF($M31="",12,$M31)),$O31,0) -> 0 | U31: =IF(AND(U$4>=IF($L31="",1,$L31),U$4<=IF($M31="",12,$M31)),$O31,0) -> 0 | V31: =IF(AND(V$4>=IF($L31="",1,$L31),V$4<=IF($M31="",12,$M31)),$O31,0) -> 0 | W31: =IF(AND(W$4>=IF($L31="",1,$L31),W$4<=IF($M31="",12,$M31)),$O31,0) -> 0 | ... AA31: =IF(AND(AA$4>=IF($L31="",1,$L31),AA$4<=IF($M31="",12,$M31)),$O31,0) -> 0 | AB31: =SUM(P31:AA31) -> 0
A32: Name-Cheap.com | B32: Marketing | C32: XERO+BUDGET | D32: STEADY | E32: 1 | G32: =IFERROR(IF($F32>0,MAX(0,INDEX('XERO ACTUALS'!$T$5:$T$132,MATCH($A32,'XERO ACTUALS'!$A$5:$A$132,0))-$F32),INDEX('XERO ACTUALS'!$T$5:$T$132,MATCH($A32,'XERO ACTUALS'!$A$5:$A$132,0)))*IF($E32="",1,$E32),"") -> 50.013333 | H32: 38.24 | I32: XERO | K32: 0 | L32: 1 | M32: 12 | N32: Y | O32: =IF($N32="N",0,IF($A32="",0,(IF($J32<>"",$J32,IF($I32="BUDGET",IF($H32="",0,$H32),IF($G32="",0,$G32))))*(1+IF($K32="",0,$K32)))) -> 50.013333 | P32: =IF(AND(P$4>=IF($L32="",1,$L32),P$4<=IF($M32="",12,$M32)),$O32,0) -> 50.013333 | Q32: =IF(AND(Q$4>=IF($L32="",1,$L32),Q$4<=IF($M32="",12,$M32)),$O32,0) -> 50.013333 | R32: =IF(AND(R$4>=IF($L32="",1,$L32),R$4<=IF($M32="",12,$M32)),$O32,0) -> 50.013333 | S32: =IF(AND(S$4>=IF($L32="",1,$L32),S$4<=IF($M32="",12,$M32)),$O32,0) -> 50.013333 | T32: =IF(AND(T$4>=IF($L32="",1,$L32),T$4<=IF($M32="",12,$M32)),$O32,0) -> 50.013333 | U32: =IF(AND(U$4>=IF($L32="",1,$L32),U$4<=IF($M32="",12,$M32)),$O32,0) -> 50.013333 | V32: =IF(AND(V$4>=IF($L32="",1,$L32),V$4<=IF($M32="",12,$M32)),$O32,0) -> 50.013333 | W32: =IF(AND(W$4>=IF($L32="",1,$L32),W$4<=IF($M32="",12,$M32)),$O32,0) -> 50.013333 | ... AA32: =IF(AND(AA$4>=IF($L32="",1,$L32),AA$4<=IF($M32="",12,$M32)),$O32,0) -> 50.013333 | AB32: =SUM(P32:AA32) -> 600.16
A33: Yext Powerlistings | B33: Marketing | C33: BUDGET ONLY | D33: NOT IN XERO 2026 | H33: 41.58 | I33: BUDGET | K33: 0 | L33: 1 | M33: 12 | N33: N | O33: =IF($N33="N",0,IF($A33="",0,(IF($J33<>"",$J33,IF($I33="BUDGET",IF($H33="",0,$H33),IF($G33="",0,$G33))))*(1+IF($K33="",0,$K33)))) -> 0 | P33: =IF(AND(P$4>=IF($L33="",1,$L33),P$4<=IF($M33="",12,$M33)),$O33,0) -> 0 | Q33: =IF(AND(Q$4>=IF($L33="",1,$L33),Q$4<=IF($M33="",12,$M33)),$O33,0) -> 0 | R33: =IF(AND(R$4>=IF($L33="",1,$L33),R$4<=IF($M33="",12,$M33)),$O33,0) -> 0 | S33: =IF(AND(S$4>=IF($L33="",1,$L33),S$4<=IF($M33="",12,$M33)),$O33,0) -> 0 | T33: =IF(AND(T$4>=IF($L33="",1,$L33),T$4<=IF($M33="",12,$M33)),$O33,0) -> 0 | U33: =IF(AND(U$4>=IF($L33="",1,$L33),U$4<=IF($M33="",12,$M33)),$O33,0) -> 0 | V33: =IF(AND(V$4>=IF($L33="",1,$L33),V$4<=IF($M33="",12,$M33)),$O33,0) -> 0 | W33: =IF(AND(W$4>=IF($L33="",1,$L33),W$4<=IF($M33="",12,$M33)),$O33,0) -> 0 | ... AA33: =IF(AND(AA$4>=IF($L33="",1,$L33),AA$4<=IF($M33="",12,$M33)),$O33,0) -> 0 | AB33: =SUM(P33:AA33) -> 0
A34: Mailboxvalid | B34: Marketing | C34: BUDGET ONLY | D34: NOT IN XERO 2026 | H34: 29.95 | I34: BUDGET | K34: 0 | L34: 1 | M34: 12 | N34: N | O34: =IF($N34="N",0,IF($A34="",0,(IF($J34<>"",$J34,IF($I34="BUDGET",IF($H34="",0,$H34),IF($G34="",0,$G34))))*(1+IF($K34="",0,$K34)))) -> 0 | P34: =IF(AND(P$4>=IF($L34="",1,$L34),P$4<=IF($M34="",12,$M34)),$O34,0) -> 0 | Q34: =IF(AND(Q$4>=IF($L34="",1,$L34),Q$4<=IF($M34="",12,$M34)),$O34,0) -> 0 | R34: =IF(AND(R$4>=IF($L34="",1,$L34),R$4<=IF($M34="",12,$M34)),$O34,0) -> 0 | S34: =IF(AND(S$4>=IF($L34="",1,$L34),S$4<=IF($M34="",12,$M34)),$O34,0) -> 0 | T34: =IF(AND(T$4>=IF($L34="",1,$L34),T$4<=IF($M34="",12,$M34)),$O34,0) -> 0 | U34: =IF(AND(U$4>=IF($L34="",1,$L34),U$4<=IF($M34="",12,$M34)),$O34,0) -> 0 | V34: =IF(AND(V$4>=IF($L34="",1,$L34),V$4<=IF($M34="",12,$M34)),$O34,0) -> 0 | W34: =IF(AND(W$4>=IF($L34="",1,$L34),W$4<=IF($M34="",12,$M34)),$O34,0) -> 0 | ... AA34: =IF(AND(AA$4>=IF($L34="",1,$L34),AA$4<=IF($M34="",12,$M34)),$O34,0) -> 0 | AB34: =SUM(P34:AA34) -> 0
A35: Neverbounce | B35: Marketing | C35: BUDGET ONLY | D35: NOT IN XERO 2026 | H35: 25.35 | I35: BUDGET | K35: 0 | L35: 1 | M35: 12 | N35: N | O35: =IF($N35="N",0,IF($A35="",0,(IF($J35<>"",$J35,IF($I35="BUDGET",IF($H35="",0,$H35),IF($G35="",0,$G35))))*(1+IF($K35="",0,$K35)))) -> 0 | P35: =IF(AND(P$4>=IF($L35="",1,$L35),P$4<=IF($M35="",12,$M35)),$O35,0) -> 0 | Q35: =IF(AND(Q$4>=IF($L35="",1,$L35),Q$4<=IF($M35="",12,$M35)),$O35,0) -> 0 | R35: =IF(AND(R$4>=IF($L35="",1,$L35),R$4<=IF($M35="",12,$M35)),$O35,0) -> 0 | S35: =IF(AND(S$4>=IF($L35="",1,$L35),S$4<=IF($M35="",12,$M35)),$O35,0) -> 0 | T35: =IF(AND(T$4>=IF($L35="",1,$L35),T$4<=IF($M35="",12,$M35)),$O35,0) -> 0 | U35: =IF(AND(U$4>=IF($L35="",1,$L35),U$4<=IF($M35="",12,$M35)),$O35,0) -> 0 | V35: =IF(AND(V$4>=IF($L35="",1,$L35),V$4<=IF($M35="",12,$M35)),$O35,0) -> 0 | W35: =IF(AND(W$4>=IF($L35="",1,$L35),W$4<=IF($M35="",12,$M35)),$O35,0) -> 0 | ... AA35: =IF(AND(AA$4>=IF($L35="",1,$L35),AA$4<=IF($M35="",12,$M35)),$O35,0) -> 0 | AB35: =SUM(P35:AA35) -> 0
A36: GoDaddy.com | B36: Marketing | C36: XERO+BUDGET | D36: PERIODIC | E36: 1 | G36: =IFERROR(IF($F36>0,MAX(0,INDEX('XERO ACTUALS'!$T$5:$T$132,MATCH($A36,'XERO ACTUALS'!$A$5:$A$132,0))-$F36),INDEX('XERO ACTUALS'!$T$5:$T$132,MATCH($A36,'XERO ACTUALS'!$A$5:$A$132,0)))*IF($E36="",1,$E36),"") -> 18.51408 | H36: 26.38 | I36: XERO | K36: 0 | L36: 1 | M36: 12 | N36: Y | O36: =IF($N36="N",0,IF($A36="",0,(IF($J36<>"",$J36,IF($I36="BUDGET",IF($H36="",0,$H36),IF($G36="",0,$G36))))*(1+IF($K36="",0,$K36)))) -> 18.51408 | P36: =IF(AND(P$4>=IF($L36="",1,$L36),P$4<=IF($M36="",12,$M36)),$O36,0) -> 18.51408 | Q36: =IF(AND(Q$4>=IF($L36="",1,$L36),Q$4<=IF($M36="",12,$M36)),$O36,0) -> 18.51408 | R36: =IF(AND(R$4>=IF($L36="",1,$L36),R$4<=IF($M36="",12,$M36)),$O36,0) -> 18.51408 | S36: =IF(AND(S$4>=IF($L36="",1,$L36),S$4<=IF($M36="",12,$M36)),$O36,0) -> 18.51408 | T36: =IF(AND(T$4>=IF($L36="",1,$L36),T$4<=IF($M36="",12,$M36)),$O36,0) -> 18.51408 | U36: =IF(AND(U$4>=IF($L36="",1,$L36),U$4<=IF($M36="",12,$M36)),$O36,0) -> 18.51408 | V36: =IF(AND(V$4>=IF($L36="",1,$L36),V$4<=IF($M36="",12,$M36)),$O36,0) -> 18.51408 | W36: =IF(AND(W$4>=IF($L36="",1,$L36),W$4<=IF($M36="",12,$M36)),$O36,0) -> 18.51408 | ... AA36: =IF(AND(AA$4>=IF($L36="",1,$L36),AA$4<=IF($M36="",12,$M36)),$O36,0) -> 18.51408 | AB36: =SUM(P36:AA36) -> 222.16896
A37: IPVM Video Surveillance | B37: Marketing | C37: BUDGET ONLY | D37: NOT IN XERO 2026 | H37: 16.58 | I37: BUDGET | K37: 0 | L37: 1 | M37: 12 | N37: N | O37: =IF($N37="N",0,IF($A37="",0,(IF($J37<>"",$J37,IF($I37="BUDGET",IF($H37="",0,$H37),IF($G37="",0,$G37))))*(1+IF($K37="",0,$K37)))) -> 0 | P37: =IF(AND(P$4>=IF($L37="",1,$L37),P$4<=IF($M37="",12,$M37)),$O37,0) -> 0 | Q37: =IF(AND(Q$4>=IF($L37="",1,$L37),Q$4<=IF($M37="",12,$M37)),$O37,0) -> 0 | R37: =IF(AND(R$4>=IF($L37="",1,$L37),R$4<=IF($M37="",12,$M37)),$O37,0) -> 0 | S37: =IF(AND(S$4>=IF($L37="",1,$L37),S$4<=IF($M37="",12,$M37)),$O37,0) -> 0 | T37: =IF(AND(T$4>=IF($L37="",1,$L37),T$4<=IF($M37="",12,$M37)),$O37,0) -> 0 | U37: =IF(AND(U$4>=IF($L37="",1,$L37),U$4<=IF($M37="",12,$M37)),$O37,0) -> 0 | V37: =IF(AND(V$4>=IF($L37="",1,$L37),V$4<=IF($M37="",12,$M37)),$O37,0) -> 0 | W37: =IF(AND(W$4>=IF($L37="",1,$L37),W$4<=IF($M37="",12,$M37)),$O37,0) -> 0 | ... AA37: =IF(AND(AA$4>=IF($L37="",1,$L37),AA$4<=IF($M37="",12,$M37)),$O37,0) -> 0 | AB37: =SUM(P37:AA37) -> 0
A38: Integration Fox | B38: Marketing | C38: XERO+BUDGET | D38: STEADY | E38: 1 | G38: =IFERROR(IF($F38>0,MAX(0,INDEX('XERO ACTUALS'!$T$5:$T$132,MATCH($A38,'XERO ACTUALS'!$A$5:$A$132,0))-$F38),INDEX('XERO ACTUALS'!$T$5:$T$132,MATCH($A38,'XERO ACTUALS'!$A$5:$A$132,0)))*IF($E38="",1,$E38),"") -> 15 | H38: 15 | I38: XERO | K38: 0 | L38: 1 | M38: 12 | N38: Y | O38: =IF($N38="N",0,IF($A38="",0,(IF($J38<>"",$J38,IF($I38="BUDGET",IF($H38="",0,$H38),IF($G38="",0,$G38))))*(1+IF($K38="",0,$K38)))) -> 15 | P38: =IF(AND(P$4>=IF($L38="",1,$L38),P$4<=IF($M38="",12,$M38)),$O38,0) -> 15 | Q38: =IF(AND(Q$4>=IF($L38="",1,$L38),Q$4<=IF($M38="",12,$M38)),$O38,0) -> 15 | R38: =IF(AND(R$4>=IF($L38="",1,$L38),R$4<=IF($M38="",12,$M38)),$O38,0) -> 15 | S38: =IF(AND(S$4>=IF($L38="",1,$L38),S$4<=IF($M38="",12,$M38)),$O38,0) -> 15 | T38: =IF(AND(T$4>=IF($L38="",1,$L38),T$4<=IF($M38="",12,$M38)),$O38,0) -> 15 | U38: =IF(AND(U$4>=IF($L38="",1,$L38),U$4<=IF($M38="",12,$M38)),$O38,0) -> 15 | V38: =IF(AND(V$4>=IF($L38="",1,$L38),V$4<=IF($M38="",12,$M38)),$O38,0) -> 15 | W38: =IF(AND(W$4>=IF($L38="",1,$L38),W$4<=IF($M38="",12,$M38)),$O38,0) -> 15 | ... AA38: =IF(AND(AA$4>=IF($L38="",1,$L38),AA$4<=IF($M38="",12,$M38)),$O38,0) -> 15 | AB38: =SUM(P38:AA38) -> 180
A39: Rev.com | B39: Marketing | C39: BUDGET ONLY | D39: NOT IN XERO 2026 | H39: 10 | I39: BUDGET | K39: 0 | L39: 1 | M39: 12 | N39: N | O39: =IF($N39="N",0,IF($A39="",0,(IF($J39<>"",$J39,IF($I39="BUDGET",IF($H39="",0,$H39),IF($G39="",0,$G39))))*(1+IF($K39="",0,$K39)))) -> 0 | P39: =IF(AND(P$4>=IF($L39="",1,$L39),P$4<=IF($M39="",12,$M39)),$O39,0) -> 0 | Q39: =IF(AND(Q$4>=IF($L39="",1,$L39),Q$4<=IF($M39="",12,$M39)),$O39,0) -> 0 | R39: =IF(AND(R$4>=IF($L39="",1,$L39),R$4<=IF($M39="",12,$M39)),$O39,0) -> 0 | S39: =IF(AND(S$4>=IF($L39="",1,$L39),S$4<=IF($M39="",12,$M39)),$O39,0) -> 0 | T39: =IF(AND(T$4>=IF($L39="",1,$L39),T$4<=IF($M39="",12,$M39)),$O39,0) -> 0 | U39: =IF(AND(U$4>=IF($L39="",1,$L39),U$4<=IF($M39="",12,$M39)),$O39,0) -> 0 | V39: =IF(AND(V$4>=IF($L39="",1,$L39),V$4<=IF($M39="",12,$M39)),$O39,0) -> 0 | W39: =IF(AND(W$4>=IF($L39="",1,$L39),W$4<=IF($M39="",12,$M39)),$O39,0) -> 0 | ... AA39: =IF(AND(AA$4>=IF($L39="",1,$L39),AA$4<=IF($M39="",12,$M39)),$O39,0) -> 0 | AB39: =SUM(P39:AA39) -> 0
A40: Statcounter.com | B40: Marketing | C40: BUDGET ONLY | D40: NOT IN XERO 2026 | H40: 4.08 | I40: BUDGET | K40: 0 | L40: 1 | M40: 12 | N40: N | O40: =IF($N40="N",0,IF($A40="",0,(IF($J40<>"",$J40,IF($I40="BUDGET",IF($H40="",0,$H40),IF($G40="",0,$G40))))*(1+IF($K40="",0,$K40)))) -> 0 | P40: =IF(AND(P$4>=IF($L40="",1,$L40),P$4<=IF($M40="",12,$M40)),$O40,0) -> 0 | Q40: =IF(AND(Q$4>=IF($L40="",1,$L40),Q$4<=IF($M40="",12,$M40)),$O40,0) -> 0 | R40: =IF(AND(R$4>=IF($L40="",1,$L40),R$4<=IF($M40="",12,$M40)),$O40,0) -> 0 | S40: =IF(AND(S$4>=IF($L40="",1,$L40),S$4<=IF($M40="",12,$M40)),$O40,0) -> 0 | T40: =IF(AND(T$4>=IF($L40="",1,$L40),T$4<=IF($M40="",12,$M40)),$O40,0) -> 0 | U40: =IF(AND(U$4>=IF($L40="",1,$L40),U$4<=IF($M40="",12,$M40)),$O40,0) -> 0 | V40: =IF(AND(V$4>=IF($L40="",1,$L40),V$4<=IF($M40="",12,$M40)),$O40,0) -> 0 | W40: =IF(AND(W$4>=IF($L40="",1,$L40),W$4<=IF($M40="",12,$M40)),$O40,0) -> 0 | ... AA40: =IF(AND(AA$4>=IF($L40="",1,$L40),AA$4<=IF($M40="",12,$M40)),$O40,0) -> 0 | AB40: =SUM(P40:AA40) -> 0
A41: Birdeye 2025-2026 | B41: Marketing | C41: XERO ONLY | D41: DROPPED | E41: 1 | G41: =IFERROR(IF($F41>0,MAX(0,INDEX('XERO ACTUALS'!$T$5:$T$132,MATCH($A41,'XERO ACTUALS'!$A$5:$A$132,0))-$F41),INDEX('XERO ACTUALS'!$T$5:$T$132,MATCH($A41,'XERO ACTUALS'!$A$5:$A$132,0)))*IF($E41="",1,$E41),"") -> 0 | I41: XERO | K41: 0 | L41: 1 | M41: 12 | N41: N | O41: =IF($N41="N",0,IF($A41="",0,(IF($J41<>"",$J41,IF($I41="BUDGET",IF($H41="",0,$H41),IF($G41="",0,$G41))))*(1+IF($K41="",0,$K41)))) -> 0 | P41: =IF(AND(P$4>=IF($L41="",1,$L41),P$4<=IF($M41="",12,$M41)),$O41,0) -> 0 | Q41: =IF(AND(Q$4>=IF($L41="",1,$L41),Q$4<=IF($M41="",12,$M41)),$O41,0) -> 0 | R41: =IF(AND(R$4>=IF($L41="",1,$L41),R$4<=IF($M41="",12,$M41)),$O41,0) -> 0 | S41: =IF(AND(S$4>=IF($L41="",1,$L41),S$4<=IF($M41="",12,$M41)),$O41,0) -> 0 | T41: =IF(AND(T$4>=IF($L41="",1,$L41),T$4<=IF($M41="",12,$M41)),$O41,0) -> 0 | U41: =IF(AND(U$4>=IF($L41="",1,$L41),U$4<=IF($M41="",12,$M41)),$O41,0) -> 0 | V41: =IF(AND(V$4>=IF($L41="",1,$L41),V$4<=IF($M41="",12,$M41)),$O41,0) -> 0 | W41: =IF(AND(W$4>=IF($L41="",1,$L41),W$4<=IF($M41="",12,$M41)),$O41,0) -> 0 | ... AA41: =IF(AND(AA$4>=IF($L41="",1,$L41),AA$4<=IF($M41="",12,$M41)),$O41,0) -> 0 | AB41: =SUM(P41:AA41) -> 0
A42: Survail Website | B42: Marketing | C42: BUDGET ONLY | D42: NOT IN XERO 2026 | H42: 0 | I42: BUDGET | K42: 0 | L42: 1 | M42: 12 | N42: N | O42: =IF($N42="N",0,IF($A42="",0,(IF($J42<>"",$J42,IF($I42="BUDGET",IF($H42="",0,$H42),IF($G42="",0,$G42))))*(1+IF($K42="",0,$K42)))) -> 0 | P42: =IF(AND(P$4>=IF($L42="",1,$L42),P$4<=IF($M42="",12,$M42)),$O42,0) -> 0 | Q42: =IF(AND(Q$4>=IF($L42="",1,$L42),Q$4<=IF($M42="",12,$M42)),$O42,0) -> 0 | R42: =IF(AND(R$4>=IF($L42="",1,$L42),R$4<=IF($M42="",12,$M42)),$O42,0) -> 0 | S42: =IF(AND(S$4>=IF($L42="",1,$L42),S$4<=IF($M42="",12,$M42)),$O42,0) -> 0 | T42: =IF(AND(T$4>=IF($L42="",1,$L42),T$4<=IF($M42="",12,$M42)),$O42,0) -> 0 | U42: =IF(AND(U$4>=IF($L42="",1,$L42),U$4<=IF($M42="",12,$M42)),$O42,0) -> 0 | V42: =IF(AND(V$4>=IF($L42="",1,$L42),V$4<=IF($M42="",12,$M42)),$O42,0) -> 0 | W42: =IF(AND(W$4>=IF($L42="",1,$L42),W$4<=IF($M42="",12,$M42)),$O42,0) -> 0 | ... AA42: =IF(AND(AA$4>=IF($L42="",1,$L42),AA$4<=IF($M42="",12,$M42)),$O42,0) -> 0 | AB42: =SUM(P42:AA42) -> 0
A43: Amazon Web Services | B43: Software Development | C43: XERO+BUDGET | D43: STEADY | E43: 1 | G43: =IFERROR(IF($F43>0,MAX(0,INDEX('XERO ACTUALS'!$T$5:$T$132,MATCH($A43,'XERO ACTUALS'!$A$5:$A$132,0))-$F43),INDEX('XERO ACTUALS'!$T$5:$T$132,MATCH($A43,'XERO ACTUALS'!$A$5:$A$132,0)))*IF($E43="",1,$E43),"") -> 12888.15 | H43: 13000 | I43: XERO | K43: 0 | L43: 1 | M43: 12 | N43: Y | O43: =IF($N43="N",0,IF($A43="",0,(IF($J43<>"",$J43,IF($I43="BUDGET",IF($H43="",0,$H43),IF($G43="",0,$G43))))*(1+IF($K43="",0,$K43)))) -> 12888.15 | P43: =IF(AND(P$4>=IF($L43="",1,$L43),P$4<=IF($M43="",12,$M43)),$O43,0) -> 12888.15 | Q43: =IF(AND(Q$4>=IF($L43="",1,$L43),Q$4<=IF($M43="",12,$M43)),$O43,0) -> 12888.15 | R43: =IF(AND(R$4>=IF($L43="",1,$L43),R$4<=IF($M43="",12,$M43)),$O43,0) -> 12888.15 | S43: =IF(AND(S$4>=IF($L43="",1,$L43),S$4<=IF($M43="",12,$M43)),$O43,0) -> 12888.15 | T43: =IF(AND(T$4>=IF($L43="",1,$L43),T$4<=IF($M43="",12,$M43)),$O43,0) -> 12888.15 | U43: =IF(AND(U$4>=IF($L43="",1,$L43),U$4<=IF($M43="",12,$M43)),$O43,0) -> 12888.15 | V43: =IF(AND(V$4>=IF($L43="",1,$L43),V$4<=IF($M43="",12,$M43)),$O43,0) -> 12888.15 | W43: =IF(AND(W$4>=IF($L43="",1,$L43),W$4<=IF($M43="",12,$M43)),$O43,0) -> 12888.15 | ... AA43: =IF(AND(AA$4>=IF($L43="",1,$L43),AA$4<=IF($M43="",12,$M43)),$O43,0) -> 12888.15 | AB43: =SUM(P43:AA43) -> 154657.8
A44: Sliger | B44: Software Development | C44: XERO ONLY | D44: NEW | E44: 1 | G44: =IFERROR(IF($F44>0,MAX(0,INDEX('XERO ACTUALS'!$T$5:$T$132,MATCH($A44,'XERO ACTUALS'!$A$5:$A$132,0))-$F44),INDEX('XERO ACTUALS'!$T$5:$T$132,MATCH($A44,'XERO ACTUALS'!$A$5:$A$132,0)))*IF($E44="",1,$E44),"") -> 1003 | I44: XERO | K44: 0 | L44: 1 | M44: 12 | N44: Y | O44: =IF($N44="N",0,IF($A44="",0,(IF($J44<>"",$J44,IF($I44="BUDGET",IF($H44="",0,$H44),IF($G44="",0,$G44))))*(1+IF($K44="",0,$K44)))) -> 1003 | P44: =IF(AND(P$4>=IF($L44="",1,$L44),P$4<=IF($M44="",12,$M44)),$O44,0) -> 1003 | Q44: =IF(AND(Q$4>=IF($L44="",1,$L44),Q$4<=IF($M44="",12,$M44)),$O44,0) -> 1003 | R44: =IF(AND(R$4>=IF($L44="",1,$L44),R$4<=IF($M44="",12,$M44)),$O44,0) -> 1003 | S44: =IF(AND(S$4>=IF($L44="",1,$L44),S$4<=IF($M44="",12,$M44)),$O44,0) -> 1003 | T44: =IF(AND(T$4>=IF($L44="",1,$L44),T$4<=IF($M44="",12,$M44)),$O44,0) -> 1003 | U44: =IF(AND(U$4>=IF($L44="",1,$L44),U$4<=IF($M44="",12,$M44)),$O44,0) -> 1003 | V44: =IF(AND(V$4>=IF($L44="",1,$L44),V$4<=IF($M44="",12,$M44)),$O44,0) -> 1003 | W44: =IF(AND(W$4>=IF($L44="",1,$L44),W$4<=IF($M44="",12,$M44)),$O44,0) -> 1003 | ... AA44: =IF(AND(AA$4>=IF($L44="",1,$L44),AA$4<=IF($M44="",12,$M44)),$O44,0) -> 1003 | AB44: =SUM(P44:AA44) -> 12036
A45: CoCoa Flex Center LLC | B45: Software Development | C45: XERO+BUDGET | D45: STEADY | E45: 1 | G45: =IFERROR(IF($F45>0,MAX(0,INDEX('XERO ACTUALS'!$T$5:$T$132,MATCH($A45,'XERO ACTUALS'!$A$5:$A$132,0))-$F45),INDEX('XERO ACTUALS'!$T$5:$T$132,MATCH($A45,'XERO ACTUALS'!$A$5:$A$132,0)))*IF($E45="",1,$E45),"") -> 925 | H45: 875.5 | I45: XERO | K45: 0 | L45: 1 | M45: 12 | N45: Y | O45: =IF($N45="N",0,IF($A45="",0,(IF($J45<>"",$J45,IF($I45="BUDGET",IF($H45="",0,$H45),IF($G45="",0,$G45))))*(1+IF($K45="",0,$K45)))) -> 925 | P45: =IF(AND(P$4>=IF($L45="",1,$L45),P$4<=IF($M45="",12,$M45)),$O45,0) -> 925 | Q45: =IF(AND(Q$4>=IF($L45="",1,$L45),Q$4<=IF($M45="",12,$M45)),$O45,0) -> 925 | R45: =IF(AND(R$4>=IF($L45="",1,$L45),R$4<=IF($M45="",12,$M45)),$O45,0) -> 925 | S45: =IF(AND(S$4>=IF($L45="",1,$L45),S$4<=IF($M45="",12,$M45)),$O45,0) -> 925 | T45: =IF(AND(T$4>=IF($L45="",1,$L45),T$4<=IF($M45="",12,$M45)),$O45,0) -> 925 | U45: =IF(AND(U$4>=IF($L45="",1,$L45),U$4<=IF($M45="",12,$M45)),$O45,0) -> 925 | V45: =IF(AND(V$4>=IF($L45="",1,$L45),V$4<=IF($M45="",12,$M45)),$O45,0) -> 925 | W45: =IF(AND(W$4>=IF($L45="",1,$L45),W$4<=IF($M45="",12,$M45)),$O45,0) -> 925 | ... AA45: =IF(AND(AA$4>=IF($L45="",1,$L45),AA$4<=IF($M45="",12,$M45)),$O45,0) -> 925 | AB45: =SUM(P45:AA45) -> 11100
A46: OPENAI (Survail LLM) | B46: Software Development | C46: XERO ONLY | D46: GROWING | E46: 1 | G46: =IFERROR(IF($F46>0,MAX(0,INDEX('XERO ACTUALS'!$T$5:$T$132,MATCH($A46,'XERO ACTUALS'!$A$5:$A$132,0))-$F46),INDEX('XERO ACTUALS'!$T$5:$T$132,MATCH($A46,'XERO ACTUALS'!$A$5:$A$132,0)))*IF($E46="",1,$E46),"") -> 773.50333 | I46: XERO | K46: 0 | L46: 1 | M46: 12 | N46: Y | O46: =IF($N46="N",0,IF($A46="",0,(IF($J46<>"",$J46,IF($I46="BUDGET",IF($H46="",0,$H46),IF($G46="",0,$G46))))*(1+IF($K46="",0,$K46)))) -> 773.50333 | P46: =IF(AND(P$4>=IF($L46="",1,$L46),P$4<=IF($M46="",12,$M46)),$O46,0) -> 773.50333 | Q46: =IF(AND(Q$4>=IF($L46="",1,$L46),Q$4<=IF($M46="",12,$M46)),$O46,0) -> 773.50333 | R46: =IF(AND(R$4>=IF($L46="",1,$L46),R$4<=IF($M46="",12,$M46)),$O46,0) -> 773.50333 | S46: =IF(AND(S$4>=IF($L46="",1,$L46),S$4<=IF($M46="",12,$M46)),$O46,0) -> 773.50333 | T46: =IF(AND(T$4>=IF($L46="",1,$L46),T$4<=IF($M46="",12,$M46)),$O46,0) -> 773.50333 | U46: =IF(AND(U$4>=IF($L46="",1,$L46),U$4<=IF($M46="",12,$M46)),$O46,0) -> 773.50333 | V46: =IF(AND(V$4>=IF($L46="",1,$L46),V$4<=IF($M46="",12,$M46)),$O46,0) -> 773.50333 | W46: =IF(AND(W$4>=IF($L46="",1,$L46),W$4<=IF($M46="",12,$M46)),$O46,0) -> 773.50333 | ... AA46: =IF(AND(AA$4>=IF($L46="",1,$L46),AA$4<=IF($M46="",12,$M46)),$O46,0) -> 773.50333 | AB46: =SUM(P46:AA46) -> 9282.04
A47: DivioTec Inc | B47: Software Development | C47: XERO ONLY | D47: ONE-TIME | E47: 1 | G47: =IFERROR(IF($F47>0,MAX(0,INDEX('XERO ACTUALS'!$T$5:$T$132,MATCH($A47,'XERO ACTUALS'!$A$5:$A$132,0))-$F47),INDEX('XERO ACTUALS'!$T$5:$T$132,MATCH($A47,'XERO ACTUALS'!$A$5:$A$132,0)))*IF($E47="",1,$E47),"") -> 386.71946 | I47: XERO | K47: 0 | L47: 1 | M47: 12 | N47: N | O47: =IF($N47="N",0,IF($A47="",0,(IF($J47<>"",$J47,IF($I47="BUDGET",IF($H47="",0,$H47),IF($G47="",0,$G47))))*(1+IF($K47="",0,$K47)))) -> 0 | P47: =IF(AND(P$4>=IF($L47="",1,$L47),P$4<=IF($M47="",12,$M47)),$O47,0) -> 0 | Q47: =IF(AND(Q$4>=IF($L47="",1,$L47),Q$4<=IF($M47="",12,$M47)),$O47,0) -> 0 | R47: =IF(AND(R$4>=IF($L47="",1,$L47),R$4<=IF($M47="",12,$M47)),$O47,0) -> 0 | S47: =IF(AND(S$4>=IF($L47="",1,$L47),S$4<=IF($M47="",12,$M47)),$O47,0) -> 0 | T47: =IF(AND(T$4>=IF($L47="",1,$L47),T$4<=IF($M47="",12,$M47)),$O47,0) -> 0 | U47: =IF(AND(U$4>=IF($L47="",1,$L47),U$4<=IF($M47="",12,$M47)),$O47,0) -> 0 | V47: =IF(AND(V$4>=IF($L47="",1,$L47),V$4<=IF($M47="",12,$M47)),$O47,0) -> 0 | W47: =IF(AND(W$4>=IF($L47="",1,$L47),W$4<=IF($M47="",12,$M47)),$O47,0) -> 0 | ... AA47: =IF(AND(AA$4>=IF($L47="",1,$L47),AA$4<=IF($M47="",12,$M47)),$O47,0) -> 0 | AB47: =SUM(P47:AA47) -> 0
A48: QT Company | B48: Software Development | C48: BUDGET ONLY | D48: NOT IN XERO 2026 | H48: 329.17 | I48: BUDGET | K48: 0 | L48: 1 | M48: 12 | N48: N | O48: =IF($N48="N",0,IF($A48="",0,(IF($J48<>"",$J48,IF($I48="BUDGET",IF($H48="",0,$H48),IF($G48="",0,$G48))))*(1+IF($K48="",0,$K48)))) -> 0 | P48: =IF(AND(P$4>=IF($L48="",1,$L48),P$4<=IF($M48="",12,$M48)),$O48,0) -> 0 | Q48: =IF(AND(Q$4>=IF($L48="",1,$L48),Q$4<=IF($M48="",12,$M48)),$O48,0) -> 0 | R48: =IF(AND(R$4>=IF($L48="",1,$L48),R$4<=IF($M48="",12,$M48)),$O48,0) -> 0 | S48: =IF(AND(S$4>=IF($L48="",1,$L48),S$4<=IF($M48="",12,$M48)),$O48,0) -> 0 | T48: =IF(AND(T$4>=IF($L48="",1,$L48),T$4<=IF($M48="",12,$M48)),$O48,0) -> 0 | U48: =IF(AND(U$4>=IF($L48="",1,$L48),U$4<=IF($M48="",12,$M48)),$O48,0) -> 0 | V48: =IF(AND(V$4>=IF($L48="",1,$L48),V$4<=IF($M48="",12,$M48)),$O48,0) -> 0 | W48: =IF(AND(W$4>=IF($L48="",1,$L48),W$4<=IF($M48="",12,$M48)),$O48,0) -> 0 | ... AA48: =IF(AND(AA$4>=IF($L48="",1,$L48),AA$4<=IF($M48="",12,$M48)),$O48,0) -> 0 | AB48: =SUM(P48:AA48) -> 0
A49: ChatGPT (OpenAI subscriptions) | B49: Software Development | C49: XERO ONLY | D49: STEADY | E49: 1 | G49: =IFERROR(IF($F49>0,MAX(0,INDEX('XERO ACTUALS'!$T$5:$T$132,MATCH($A49,'XERO ACTUALS'!$A$5:$A$132,0))-$F49),INDEX('XERO ACTUALS'!$T$5:$T$132,MATCH($A49,'XERO ACTUALS'!$A$5:$A$132,0)))*IF($E49="",1,$E49),"") -> 190.33333 | I49: XERO | K49: 0 | L49: 1 | M49: 12 | N49: Y | O49: =IF($N49="N",0,IF($A49="",0,(IF($J49<>"",$J49,IF($I49="BUDGET",IF($H49="",0,$H49),IF($G49="",0,$G49))))*(1+IF($K49="",0,$K49)))) -> 190.33333 | P49: =IF(AND(P$4>=IF($L49="",1,$L49),P$4<=IF($M49="",12,$M49)),$O49,0) -> 190.33333 | Q49: =IF(AND(Q$4>=IF($L49="",1,$L49),Q$4<=IF($M49="",12,$M49)),$O49,0) -> 190.33333 | R49: =IF(AND(R$4>=IF($L49="",1,$L49),R$4<=IF($M49="",12,$M49)),$O49,0) -> 190.33333 | S49: =IF(AND(S$4>=IF($L49="",1,$L49),S$4<=IF($M49="",12,$M49)),$O49,0) -> 190.33333 | T49: =IF(AND(T$4>=IF($L49="",1,$L49),T$4<=IF($M49="",12,$M49)),$O49,0) -> 190.33333 | U49: =IF(AND(U$4>=IF($L49="",1,$L49),U$4<=IF($M49="",12,$M49)),$O49,0) -> 190.33333 | V49: =IF(AND(V$4>=IF($L49="",1,$L49),V$4<=IF($M49="",12,$M49)),$O49,0) -> 190.33333 | W49: =IF(AND(W$4>=IF($L49="",1,$L49),W$4<=IF($M49="",12,$M49)),$O49,0) -> 190.33333 | ... AA49: =IF(AND(AA$4>=IF($L49="",1,$L49),AA$4<=IF($M49="",12,$M49)),$O49,0) -> 190.33333 | AB49: =SUM(P49:AA49) -> 2284
A50: Florida Power & Light | B50: Software Development | C50: XERO+BUDGET | D50: STEADY | E50: 1 | G50: =IFERROR(IF($F50>0,MAX(0,INDEX('XERO ACTUALS'!$T$5:$T$132,MATCH($A50,'XERO ACTUALS'!$A$5:$A$132,0))-$F50),INDEX('XERO ACTUALS'!$T$5:$T$132,MATCH($A50,'XERO ACTUALS'!$A$5:$A$132,0)))*IF($E50="",1,$E50),"") -> 164.66667 | H50: 89.2 | I50: XERO | K50: 0 | L50: 1 | M50: 12 | N50: Y | O50: =IF($N50="N",0,IF($A50="",0,(IF($J50<>"",$J50,IF($I50="BUDGET",IF($H50="",0,$H50),IF($G50="",0,$G50))))*(1+IF($K50="",0,$K50)))) -> 164.66667 | P50: =IF(AND(P$4>=IF($L50="",1,$L50),P$4<=IF($M50="",12,$M50)),$O50,0) -> 164.66667 | Q50: =IF(AND(Q$4>=IF($L50="",1,$L50),Q$4<=IF($M50="",12,$M50)),$O50,0) -> 164.66667 | R50: =IF(AND(R$4>=IF($L50="",1,$L50),R$4<=IF($M50="",12,$M50)),$O50,0) -> 164.66667 | S50: =IF(AND(S$4>=IF($L50="",1,$L50),S$4<=IF($M50="",12,$M50)),$O50,0) -> 164.66667 | T50: =IF(AND(T$4>=IF($L50="",1,$L50),T$4<=IF($M50="",12,$M50)),$O50,0) -> 164.66667 | U50: =IF(AND(U$4>=IF($L50="",1,$L50),U$4<=IF($M50="",12,$M50)),$O50,0) -> 164.66667 | V50: =IF(AND(V$4>=IF($L50="",1,$L50),V$4<=IF($M50="",12,$M50)),$O50,0) -> 164.66667 | W50: =IF(AND(W$4>=IF($L50="",1,$L50),W$4<=IF($M50="",12,$M50)),$O50,0) -> 164.66667 | ... AA50: =IF(AND(AA$4>=IF($L50="",1,$L50),AA$4<=IF($M50="",12,$M50)),$O50,0) -> 164.66667 | AB50: =SUM(P50:AA50) -> 1976
A51: DigitalOcean.com | B51: Software Development | C51: XERO+BUDGET | D51: STEADY | E51: 1 | G51: =IFERROR(IF($F51>0,MAX(0,INDEX('XERO ACTUALS'!$T$5:$T$132,MATCH($A51,'XERO ACTUALS'!$A$5:$A$132,0))-$F51),INDEX('XERO ACTUALS'!$T$5:$T$132,MATCH($A51,'XERO ACTUALS'!$A$5:$A$132,0)))*IF($E51="",1,$E51),"") -> 122 | H51: 98 | I51: XERO | K51: 0 | L51: 1 | M51: 12 | N51: Y | O51: =IF($N51="N",0,IF($A51="",0,(IF($J51<>"",$J51,IF($I51="BUDGET",IF($H51="",0,$H51),IF($G51="",0,$G51))))*(1+IF($K51="",0,$K51)))) -> 122 | P51: =IF(AND(P$4>=IF($L51="",1,$L51),P$4<=IF($M51="",12,$M51)),$O51,0) -> 122 | Q51: =IF(AND(Q$4>=IF($L51="",1,$L51),Q$4<=IF($M51="",12,$M51)),$O51,0) -> 122 | R51: =IF(AND(R$4>=IF($L51="",1,$L51),R$4<=IF($M51="",12,$M51)),$O51,0) -> 122 | S51: =IF(AND(S$4>=IF($L51="",1,$L51),S$4<=IF($M51="",12,$M51)),$O51,0) -> 122 | T51: =IF(AND(T$4>=IF($L51="",1,$L51),T$4<=IF($M51="",12,$M51)),$O51,0) -> 122 | U51: =IF(AND(U$4>=IF($L51="",1,$L51),U$4<=IF($M51="",12,$M51)),$O51,0) -> 122 | V51: =IF(AND(V$4>=IF($L51="",1,$L51),V$4<=IF($M51="",12,$M51)),$O51,0) -> 122 | W51: =IF(AND(W$4>=IF($L51="",1,$L51),W$4<=IF($M51="",12,$M51)),$O51,0) -> 122 | ... AA51: =IF(AND(AA$4>=IF($L51="",1,$L51),AA$4<=IF($M51="",12,$M51)),$O51,0) -> 122 | AB51: =SUM(P51:AA51) -> 1464
A52: Figma Monthly | B52: Software Development | C52: XERO+BUDGET | D52: STEADY | E52: 1 | G52: =IFERROR(IF($F52>0,MAX(0,INDEX('XERO ACTUALS'!$T$5:$T$132,MATCH($A52,'XERO ACTUALS'!$A$5:$A$132,0))-$F52),INDEX('XERO ACTUALS'!$T$5:$T$132,MATCH($A52,'XERO ACTUALS'!$A$5:$A$132,0)))*IF($E52="",1,$E52),"") -> 120 | H52: 120 | I52: XERO | K52: 0 | L52: 1 | M52: 12 | N52: Y | O52: =IF($N52="N",0,IF($A52="",0,(IF($J52<>"",$J52,IF($I52="BUDGET",IF($H52="",0,$H52),IF($G52="",0,$G52))))*(1+IF($K52="",0,$K52)))) -> 120 | P52: =IF(AND(P$4>=IF($L52="",1,$L52),P$4<=IF($M52="",12,$M52)),$O52,0) -> 120 | Q52: =IF(AND(Q$4>=IF($L52="",1,$L52),Q$4<=IF($M52="",12,$M52)),$O52,0) -> 120 | R52: =IF(AND(R$4>=IF($L52="",1,$L52),R$4<=IF($M52="",12,$M52)),$O52,0) -> 120 | S52: =IF(AND(S$4>=IF($L52="",1,$L52),S$4<=IF($M52="",12,$M52)),$O52,0) -> 120 | T52: =IF(AND(T$4>=IF($L52="",1,$L52),T$4<=IF($M52="",12,$M52)),$O52,0) -> 120 | U52: =IF(AND(U$4>=IF($L52="",1,$L52),U$4<=IF($M52="",12,$M52)),$O52,0) -> 120 | V52: =IF(AND(V$4>=IF($L52="",1,$L52),V$4<=IF($M52="",12,$M52)),$O52,0) -> 120 | W52: =IF(AND(W$4>=IF($L52="",1,$L52),W$4<=IF($M52="",12,$M52)),$O52,0) -> 120 | ... AA52: =IF(AND(AA$4>=IF($L52="",1,$L52),AA$4<=IF($M52="",12,$M52)),$O52,0) -> 120 | AB52: =SUM(P52:AA52) -> 1440
A53: Doppler Technologies | B53: Software Development | C53: XERO+BUDGET | D53: STEADY | E53: 1 | G53: =IFERROR(IF($F53>0,MAX(0,INDEX('XERO ACTUALS'!$T$5:$T$132,MATCH($A53,'XERO ACTUALS'!$A$5:$A$132,0))-$F53),INDEX('XERO ACTUALS'!$T$5:$T$132,MATCH($A53,'XERO ACTUALS'!$A$5:$A$132,0)))*IF($E53="",1,$E53),"") -> 105 | H53: 84 | I53: XERO | K53: 0 | L53: 1 | M53: 12 | N53: Y | O53: =IF($N53="N",0,IF($A53="",0,(IF($J53<>"",$J53,IF($I53="BUDGET",IF($H53="",0,$H53),IF($G53="",0,$G53))))*(1+IF($K53="",0,$K53)))) -> 105 | P53: =IF(AND(P$4>=IF($L53="",1,$L53),P$4<=IF($M53="",12,$M53)),$O53,0) -> 105 | Q53: =IF(AND(Q$4>=IF($L53="",1,$L53),Q$4<=IF($M53="",12,$M53)),$O53,0) -> 105 | R53: =IF(AND(R$4>=IF($L53="",1,$L53),R$4<=IF($M53="",12,$M53)),$O53,0) -> 105 | S53: =IF(AND(S$4>=IF($L53="",1,$L53),S$4<=IF($M53="",12,$M53)),$O53,0) -> 105 | T53: =IF(AND(T$4>=IF($L53="",1,$L53),T$4<=IF($M53="",12,$M53)),$O53,0) -> 105 | U53: =IF(AND(U$4>=IF($L53="",1,$L53),U$4<=IF($M53="",12,$M53)),$O53,0) -> 105 | V53: =IF(AND(V$4>=IF($L53="",1,$L53),V$4<=IF($M53="",12,$M53)),$O53,0) -> 105 | W53: =IF(AND(W$4>=IF($L53="",1,$L53),W$4<=IF($M53="",12,$M53)),$O53,0) -> 105 | ... AA53: =IF(AND(AA$4>=IF($L53="",1,$L53),AA$4<=IF($M53="",12,$M53)),$O53,0) -> 105 | AB53: =SUM(P53:AA53) -> 1260
A54: Docker, Inc | B54: Software Development | C54: XERO+BUDGET | D54: STEADY | E54: 1 | G54: =IFERROR(IF($F54>0,MAX(0,INDEX('XERO ACTUALS'!$T$5:$T$132,MATCH($A54,'XERO ACTUALS'!$A$5:$A$132,0))-$F54),INDEX('XERO ACTUALS'!$T$5:$T$132,MATCH($A54,'XERO ACTUALS'!$A$5:$A$132,0)))*IF($E54="",1,$E54),"") -> 91 | H54: 91 | I54: XERO | K54: 0 | L54: 1 | M54: 12 | N54: Y | O54: =IF($N54="N",0,IF($A54="",0,(IF($J54<>"",$J54,IF($I54="BUDGET",IF($H54="",0,$H54),IF($G54="",0,$G54))))*(1+IF($K54="",0,$K54)))) -> 91 | P54: =IF(AND(P$4>=IF($L54="",1,$L54),P$4<=IF($M54="",12,$M54)),$O54,0) -> 91 | Q54: =IF(AND(Q$4>=IF($L54="",1,$L54),Q$4<=IF($M54="",12,$M54)),$O54,0) -> 91 | R54: =IF(AND(R$4>=IF($L54="",1,$L54),R$4<=IF($M54="",12,$M54)),$O54,0) -> 91 | S54: =IF(AND(S$4>=IF($L54="",1,$L54),S$4<=IF($M54="",12,$M54)),$O54,0) -> 91 | T54: =IF(AND(T$4>=IF($L54="",1,$L54),T$4<=IF($M54="",12,$M54)),$O54,0) -> 91 | U54: =IF(AND(U$4>=IF($L54="",1,$L54),U$4<=IF($M54="",12,$M54)),$O54,0) -> 91 | V54: =IF(AND(V$4>=IF($L54="",1,$L54),V$4<=IF($M54="",12,$M54)),$O54,0) -> 91 | W54: =IF(AND(W$4>=IF($L54="",1,$L54),W$4<=IF($M54="",12,$M54)),$O54,0) -> 91 | ... AA54: =IF(AND(AA$4>=IF($L54="",1,$L54),AA$4<=IF($M54="",12,$M54)),$O54,0) -> 91 | AB54: =SUM(P54:AA54) -> 1092
A55: GitHub | B55: Software Development | C55: XERO+BUDGET | D55: STEADY | E55: 1 | G55: =IFERROR(IF($F55>0,MAX(0,INDEX('XERO ACTUALS'!$T$5:$T$132,MATCH($A55,'XERO ACTUALS'!$A$5:$A$132,0))-$F55),INDEX('XERO ACTUALS'!$T$5:$T$132,MATCH($A55,'XERO ACTUALS'!$A$5:$A$132,0)))*IF($E55="",1,$E55),"") -> 82 | H55: 82 | I55: XERO | K55: 0 | L55: 1 | M55: 12 | N55: Y | O55: =IF($N55="N",0,IF($A55="",0,(IF($J55<>"",$J55,IF($I55="BUDGET",IF($H55="",0,$H55),IF($G55="",0,$G55))))*(1+IF($K55="",0,$K55)))) -> 82 | P55: =IF(AND(P$4>=IF($L55="",1,$L55),P$4<=IF($M55="",12,$M55)),$O55,0) -> 82 | Q55: =IF(AND(Q$4>=IF($L55="",1,$L55),Q$4<=IF($M55="",12,$M55)),$O55,0) -> 82 | R55: =IF(AND(R$4>=IF($L55="",1,$L55),R$4<=IF($M55="",12,$M55)),$O55,0) -> 82 | S55: =IF(AND(S$4>=IF($L55="",1,$L55),S$4<=IF($M55="",12,$M55)),$O55,0) -> 82 | T55: =IF(AND(T$4>=IF($L55="",1,$L55),T$4<=IF($M55="",12,$M55)),$O55,0) -> 82 | U55: =IF(AND(U$4>=IF($L55="",1,$L55),U$4<=IF($M55="",12,$M55)),$O55,0) -> 82 | V55: =IF(AND(V$4>=IF($L55="",1,$L55),V$4<=IF($M55="",12,$M55)),$O55,0) -> 82 | W55: =IF(AND(W$4>=IF($L55="",1,$L55),W$4<=IF($M55="",12,$M55)),$O55,0) -> 82 | ... AA55: =IF(AND(AA$4>=IF($L55="",1,$L55),AA$4<=IF($M55="",12,$M55)),$O55,0) -> 82 | AB55: =SUM(P55:AA55) -> 984
A56: Sentry | B56: Software Development | C56: XERO+BUDGET | D56: STEADY | E56: 1 | G56: =IFERROR(IF($F56>0,MAX(0,INDEX('XERO ACTUALS'!$T$5:$T$132,MATCH($A56,'XERO ACTUALS'!$A$5:$A$132,0))-$F56),INDEX('XERO ACTUALS'!$T$5:$T$132,MATCH($A56,'XERO ACTUALS'!$A$5:$A$132,0)))*IF($E56="",1,$E56),"") -> 35.54 | H56: 39 | I56: XERO | K56: 0 | L56: 1 | M56: 12 | N56: Y | O56: =IF($N56="N",0,IF($A56="",0,(IF($J56<>"",$J56,IF($I56="BUDGET",IF($H56="",0,$H56),IF($G56="",0,$G56))))*(1+IF($K56="",0,$K56)))) -> 35.54 | P56: =IF(AND(P$4>=IF($L56="",1,$L56),P$4<=IF($M56="",12,$M56)),$O56,0) -> 35.54 | Q56: =IF(AND(Q$4>=IF($L56="",1,$L56),Q$4<=IF($M56="",12,$M56)),$O56,0) -> 35.54 | R56: =IF(AND(R$4>=IF($L56="",1,$L56),R$4<=IF($M56="",12,$M56)),$O56,0) -> 35.54 | S56: =IF(AND(S$4>=IF($L56="",1,$L56),S$4<=IF($M56="",12,$M56)),$O56,0) -> 35.54 | T56: =IF(AND(T$4>=IF($L56="",1,$L56),T$4<=IF($M56="",12,$M56)),$O56,0) -> 35.54 | U56: =IF(AND(U$4>=IF($L56="",1,$L56),U$4<=IF($M56="",12,$M56)),$O56,0) -> 35.54 | V56: =IF(AND(V$4>=IF($L56="",1,$L56),V$4<=IF($M56="",12,$M56)),$O56,0) -> 35.54 | W56: =IF(AND(W$4>=IF($L56="",1,$L56),W$4<=IF($M56="",12,$M56)),$O56,0) -> 35.54 | ... AA56: =IF(AND(AA$4>=IF($L56="",1,$L56),AA$4<=IF($M56="",12,$M56)),$O56,0) -> 35.54 | AB56: =SUM(P56:AA56) -> 426.48
A57: SendGrid | B57: Software Development | C57: XERO ONLY | D57: STEADY | E57: 1 | G57: =IFERROR(IF($F57>0,MAX(0,INDEX('XERO ACTUALS'!$T$5:$T$132,MATCH($A57,'XERO ACTUALS'!$A$5:$A$132,0))-$F57),INDEX('XERO ACTUALS'!$T$5:$T$132,MATCH($A57,'XERO ACTUALS'!$A$5:$A$132,0)))*IF($E57="",1,$E57),"") -> 34.95 | I57: XERO | K57: 0 | L57: 1 | M57: 12 | N57: Y | O57: =IF($N57="N",0,IF($A57="",0,(IF($J57<>"",$J57,IF($I57="BUDGET",IF($H57="",0,$H57),IF($G57="",0,$G57))))*(1+IF($K57="",0,$K57)))) -> 34.95 | P57: =IF(AND(P$4>=IF($L57="",1,$L57),P$4<=IF($M57="",12,$M57)),$O57,0) -> 34.95 | Q57: =IF(AND(Q$4>=IF($L57="",1,$L57),Q$4<=IF($M57="",12,$M57)),$O57,0) -> 34.95 | R57: =IF(AND(R$4>=IF($L57="",1,$L57),R$4<=IF($M57="",12,$M57)),$O57,0) -> 34.95 | S57: =IF(AND(S$4>=IF($L57="",1,$L57),S$4<=IF($M57="",12,$M57)),$O57,0) -> 34.95 | T57: =IF(AND(T$4>=IF($L57="",1,$L57),T$4<=IF($M57="",12,$M57)),$O57,0) -> 34.95 | U57: =IF(AND(U$4>=IF($L57="",1,$L57),U$4<=IF($M57="",12,$M57)),$O57,0) -> 34.95 | V57: =IF(AND(V$4>=IF($L57="",1,$L57),V$4<=IF($M57="",12,$M57)),$O57,0) -> 34.95 | W57: =IF(AND(W$4>=IF($L57="",1,$L57),W$4<=IF($M57="",12,$M57)),$O57,0) -> 34.95 | ... AA57: =IF(AND(AA$4>=IF($L57="",1,$L57),AA$4<=IF($M57="",12,$M57)),$O57,0) -> 34.95 | AB57: =SUM(P57:AA57) -> 419.4
A58: Twilio | B58: Software Development | C58: BUDGET ONLY | D58: NOT IN XERO 2026 | H58: 24.5 | I58: BUDGET | K58: 0 | L58: 1 | M58: 12 | N58: N | O58: =IF($N58="N",0,IF($A58="",0,(IF($J58<>"",$J58,IF($I58="BUDGET",IF($H58="",0,$H58),IF($G58="",0,$G58))))*(1+IF($K58="",0,$K58)))) -> 0 | P58: =IF(AND(P$4>=IF($L58="",1,$L58),P$4<=IF($M58="",12,$M58)),$O58,0) -> 0 | Q58: =IF(AND(Q$4>=IF($L58="",1,$L58),Q$4<=IF($M58="",12,$M58)),$O58,0) -> 0 | R58: =IF(AND(R$4>=IF($L58="",1,$L58),R$4<=IF($M58="",12,$M58)),$O58,0) -> 0 | S58: =IF(AND(S$4>=IF($L58="",1,$L58),S$4<=IF($M58="",12,$M58)),$O58,0) -> 0 | T58: =IF(AND(T$4>=IF($L58="",1,$L58),T$4<=IF($M58="",12,$M58)),$O58,0) -> 0 | U58: =IF(AND(U$4>=IF($L58="",1,$L58),U$4<=IF($M58="",12,$M58)),$O58,0) -> 0 | V58: =IF(AND(V$4>=IF($L58="",1,$L58),V$4<=IF($M58="",12,$M58)),$O58,0) -> 0 | W58: =IF(AND(W$4>=IF($L58="",1,$L58),W$4<=IF($M58="",12,$M58)),$O58,0) -> 0 | ... AA58: =IF(AND(AA$4>=IF($L58="",1,$L58),AA$4<=IF($M58="",12,$M58)),$O58,0) -> 0 | AB58: =SUM(P58:AA58) -> 0
A59: Vercel | B59: Software Development | C59: XERO+BUDGET | D59: STEADY | E59: 1 | G59: =IFERROR(IF($F59>0,MAX(0,INDEX('XERO ACTUALS'!$T$5:$T$132,MATCH($A59,'XERO ACTUALS'!$A$5:$A$132,0))-$F59),INDEX('XERO ACTUALS'!$T$5:$T$132,MATCH($A59,'XERO ACTUALS'!$A$5:$A$132,0)))*IF($E59="",1,$E59),"") -> 20 | H59: 8.33 | I59: XERO | K59: 0 | L59: 1 | M59: 12 | N59: Y | O59: =IF($N59="N",0,IF($A59="",0,(IF($J59<>"",$J59,IF($I59="BUDGET",IF($H59="",0,$H59),IF($G59="",0,$G59))))*(1+IF($K59="",0,$K59)))) -> 20 | P59: =IF(AND(P$4>=IF($L59="",1,$L59),P$4<=IF($M59="",12,$M59)),$O59,0) -> 20 | Q59: =IF(AND(Q$4>=IF($L59="",1,$L59),Q$4<=IF($M59="",12,$M59)),$O59,0) -> 20 | R59: =IF(AND(R$4>=IF($L59="",1,$L59),R$4<=IF($M59="",12,$M59)),$O59,0) -> 20 | S59: =IF(AND(S$4>=IF($L59="",1,$L59),S$4<=IF($M59="",12,$M59)),$O59,0) -> 20 | T59: =IF(AND(T$4>=IF($L59="",1,$L59),T$4<=IF($M59="",12,$M59)),$O59,0) -> 20 | U59: =IF(AND(U$4>=IF($L59="",1,$L59),U$4<=IF($M59="",12,$M59)),$O59,0) -> 20 | V59: =IF(AND(V$4>=IF($L59="",1,$L59),V$4<=IF($M59="",12,$M59)),$O59,0) -> 20 | W59: =IF(AND(W$4>=IF($L59="",1,$L59),W$4<=IF($M59="",12,$M59)),$O59,0) -> 20 | ... AA59: =IF(AND(AA$4>=IF($L59="",1,$L59),AA$4<=IF($M59="",12,$M59)),$O59,0) -> 20 | AB59: =SUM(P59:AA59) -> 240
A60: Heroku | B60: Software Development | C60: BUDGET ONLY | D60: NOT IN XERO 2026 | H60: 8 | I60: BUDGET | K60: 0 | L60: 1 | M60: 12 | N60: N | O60: =IF($N60="N",0,IF($A60="",0,(IF($J60<>"",$J60,IF($I60="BUDGET",IF($H60="",0,$H60),IF($G60="",0,$G60))))*(1+IF($K60="",0,$K60)))) -> 0 | P60: =IF(AND(P$4>=IF($L60="",1,$L60),P$4<=IF($M60="",12,$M60)),$O60,0) -> 0 | Q60: =IF(AND(Q$4>=IF($L60="",1,$L60),Q$4<=IF($M60="",12,$M60)),$O60,0) -> 0 | R60: =IF(AND(R$4>=IF($L60="",1,$L60),R$4<=IF($M60="",12,$M60)),$O60,0) -> 0 | S60: =IF(AND(S$4>=IF($L60="",1,$L60),S$4<=IF($M60="",12,$M60)),$O60,0) -> 0 | T60: =IF(AND(T$4>=IF($L60="",1,$L60),T$4<=IF($M60="",12,$M60)),$O60,0) -> 0 | U60: =IF(AND(U$4>=IF($L60="",1,$L60),U$4<=IF($M60="",12,$M60)),$O60,0) -> 0 | V60: =IF(AND(V$4>=IF($L60="",1,$L60),V$4<=IF($M60="",12,$M60)),$O60,0) -> 0 | W60: =IF(AND(W$4>=IF($L60="",1,$L60),W$4<=IF($M60="",12,$M60)),$O60,0) -> 0 | ... AA60: =IF(AND(AA$4>=IF($L60="",1,$L60),AA$4<=IF($M60="",12,$M60)),$O60,0) -> 0 | AB60: =SUM(P60:AA60) -> 0
A61: Digital River | B61: Software Development | C61: BUDGET ONLY | D61: NOT IN XERO 2026 | H61: 0 | I61: BUDGET | K61: 0 | L61: 1 | M61: 12 | N61: N | O61: =IF($N61="N",0,IF($A61="",0,(IF($J61<>"",$J61,IF($I61="BUDGET",IF($H61="",0,$H61),IF($G61="",0,$G61))))*(1+IF($K61="",0,$K61)))) -> 0 | P61: =IF(AND(P$4>=IF($L61="",1,$L61),P$4<=IF($M61="",12,$M61)),$O61,0) -> 0 | Q61: =IF(AND(Q$4>=IF($L61="",1,$L61),Q$4<=IF($M61="",12,$M61)),$O61,0) -> 0 | R61: =IF(AND(R$4>=IF($L61="",1,$L61),R$4<=IF($M61="",12,$M61)),$O61,0) -> 0 | S61: =IF(AND(S$4>=IF($L61="",1,$L61),S$4<=IF($M61="",12,$M61)),$O61,0) -> 0 | T61: =IF(AND(T$4>=IF($L61="",1,$L61),T$4<=IF($M61="",12,$M61)),$O61,0) -> 0 | U61: =IF(AND(U$4>=IF($L61="",1,$L61),U$4<=IF($M61="",12,$M61)),$O61,0) -> 0 | V61: =IF(AND(V$4>=IF($L61="",1,$L61),V$4<=IF($M61="",12,$M61)),$O61,0) -> 0 | W61: =IF(AND(W$4>=IF($L61="",1,$L61),W$4<=IF($M61="",12,$M61)),$O61,0) -> 0 | ... AA61: =IF(AND(AA$4>=IF($L61="",1,$L61),AA$4<=IF($M61="",12,$M61)),$O61,0) -> 0 | AB61: =SUM(P61:AA61) -> 0
A62: Vehicle Expenses | B62: Installation Services | C62: BUDGET ONLY | D62: NOT IN XERO 2026 | H62: 2000 | I62: BUDGET | K62: 0 | L62: 1 | M62: 12 | N62: N | O62: =IF($N62="N",0,IF($A62="",0,(IF($J62<>"",$J62,IF($I62="BUDGET",IF($H62="",0,$H62),IF($G62="",0,$G62))))*(1+IF($K62="",0,$K62)))) -> 0 | P62: =IF(AND(P$4>=IF($L62="",1,$L62),P$4<=IF($M62="",12,$M62)),$O62,0) -> 0 | Q62: =IF(AND(Q$4>=IF($L62="",1,$L62),Q$4<=IF($M62="",12,$M62)),$O62,0) -> 0 | R62: =IF(AND(R$4>=IF($L62="",1,$L62),R$4<=IF($M62="",12,$M62)),$O62,0) -> 0 | S62: =IF(AND(S$4>=IF($L62="",1,$L62),S$4<=IF($M62="",12,$M62)),$O62,0) -> 0 | T62: =IF(AND(T$4>=IF($L62="",1,$L62),T$4<=IF($M62="",12,$M62)),$O62,0) -> 0 | U62: =IF(AND(U$4>=IF($L62="",1,$L62),U$4<=IF($M62="",12,$M62)),$O62,0) -> 0 | V62: =IF(AND(V$4>=IF($L62="",1,$L62),V$4<=IF($M62="",12,$M62)),$O62,0) -> 0 | W62: =IF(AND(W$4>=IF($L62="",1,$L62),W$4<=IF($M62="",12,$M62)),$O62,0) -> 0 | ... AA62: =IF(AND(AA$4>=IF($L62="",1,$L62),AA$4<=IF($M62="",12,$M62)),$O62,0) -> 0 | AB62: =SUM(P62:AA62) -> 0
A63: Auto Owners Insurance | B63: Installation Services | C63: XERO+BUDGET | D63: STEADY | E63: 0.357 | G63: =IFERROR(IF($F63>0,MAX(0,INDEX('XERO ACTUALS'!$T$5:$T$132,MATCH($A63,'XERO ACTUALS'!$A$5:$A$132,0))-$F63),INDEX('XERO ACTUALS'!$T$5:$T$132,MATCH($A63,'XERO ACTUALS'!$A$5:$A$132,0)))*IF($E63="",1,$E63),"") -> 1354.458 | H63: 1211.76 | I63: XERO | K63: 0 | L63: 1 | M63: 12 | N63: Y | O63: =IF($N63="N",0,IF($A63="",0,(IF($J63<>"",$J63,IF($I63="BUDGET",IF($H63="",0,$H63),IF($G63="",0,$G63))))*(1+IF($K63="",0,$K63)))) -> 1354.458 | P63: =IF(AND(P$4>=IF($L63="",1,$L63),P$4<=IF($M63="",12,$M63)),$O63,0) -> 1354.458 | Q63: =IF(AND(Q$4>=IF($L63="",1,$L63),Q$4<=IF($M63="",12,$M63)),$O63,0) -> 1354.458 | R63: =IF(AND(R$4>=IF($L63="",1,$L63),R$4<=IF($M63="",12,$M63)),$O63,0) -> 1354.458 | S63: =IF(AND(S$4>=IF($L63="",1,$L63),S$4<=IF($M63="",12,$M63)),$O63,0) -> 1354.458 | T63: =IF(AND(T$4>=IF($L63="",1,$L63),T$4<=IF($M63="",12,$M63)),$O63,0) -> 1354.458 | U63: =IF(AND(U$4>=IF($L63="",1,$L63),U$4<=IF($M63="",12,$M63)),$O63,0) -> 1354.458 | V63: =IF(AND(V$4>=IF($L63="",1,$L63),V$4<=IF($M63="",12,$M63)),$O63,0) -> 1354.458 | W63: =IF(AND(W$4>=IF($L63="",1,$L63),W$4<=IF($M63="",12,$M63)),$O63,0) -> 1354.458 | ... AA63: =IF(AND(AA$4>=IF($L63="",1,$L63),AA$4<=IF($M63="",12,$M63)),$O63,0) -> 1354.458 | AB63: =SUM(P63:AA63) -> 16253.496
A64: Brown Investment Properties | B64: Installation Services | C64: XERO ONLY | D64: STEADY | E64: 1 | G64: =IFERROR(IF($F64>0,MAX(0,INDEX('XERO ACTUALS'!$T$5:$T$132,MATCH($A64,'XERO ACTUALS'!$A$5:$A$132,0))-$F64),INDEX('XERO ACTUALS'!$T$5:$T$132,MATCH($A64,'XERO ACTUALS'!$A$5:$A$132,0)))*IF($E64="",1,$E64),"") -> 288.4 | I64: XERO | K64: 0 | L64: 1 | M64: 12 | N64: Y | O64: =IF($N64="N",0,IF($A64="",0,(IF($J64<>"",$J64,IF($I64="BUDGET",IF($H64="",0,$H64),IF($G64="",0,$G64))))*(1+IF($K64="",0,$K64)))) -> 288.4 | P64: =IF(AND(P$4>=IF($L64="",1,$L64),P$4<=IF($M64="",12,$M64)),$O64,0) -> 288.4 | Q64: =IF(AND(Q$4>=IF($L64="",1,$L64),Q$4<=IF($M64="",12,$M64)),$O64,0) -> 288.4 | R64: =IF(AND(R$4>=IF($L64="",1,$L64),R$4<=IF($M64="",12,$M64)),$O64,0) -> 288.4 | S64: =IF(AND(S$4>=IF($L64="",1,$L64),S$4<=IF($M64="",12,$M64)),$O64,0) -> 288.4 | T64: =IF(AND(T$4>=IF($L64="",1,$L64),T$4<=IF($M64="",12,$M64)),$O64,0) -> 288.4 | U64: =IF(AND(U$4>=IF($L64="",1,$L64),U$4<=IF($M64="",12,$M64)),$O64,0) -> 288.4 | V64: =IF(AND(V$4>=IF($L64="",1,$L64),V$4<=IF($M64="",12,$M64)),$O64,0) -> 288.4 | W64: =IF(AND(W$4>=IF($L64="",1,$L64),W$4<=IF($M64="",12,$M64)),$O64,0) -> 288.4 | ... AA64: =IF(AND(AA$4>=IF($L64="",1,$L64),AA$4<=IF($M64="",12,$M64)),$O64,0) -> 288.4 | AB64: =SUM(P64:AA64) -> 3460.8
A65: DKL Investments, LLC | B65: Installation Services | C65: BUDGET ONLY | D65: NOT IN XERO 2026 | H65: 280 | I65: BUDGET | K65: 0 | L65: 1 | M65: 12 | N65: N | O65: =IF($N65="N",0,IF($A65="",0,(IF($J65<>"",$J65,IF($I65="BUDGET",IF($H65="",0,$H65),IF($G65="",0,$G65))))*(1+IF($K65="",0,$K65)))) -> 0 | P65: =IF(AND(P$4>=IF($L65="",1,$L65),P$4<=IF($M65="",12,$M65)),$O65,0) -> 0 | Q65: =IF(AND(Q$4>=IF($L65="",1,$L65),Q$4<=IF($M65="",12,$M65)),$O65,0) -> 0 | R65: =IF(AND(R$4>=IF($L65="",1,$L65),R$4<=IF($M65="",12,$M65)),$O65,0) -> 0 | S65: =IF(AND(S$4>=IF($L65="",1,$L65),S$4<=IF($M65="",12,$M65)),$O65,0) -> 0 | T65: =IF(AND(T$4>=IF($L65="",1,$L65),T$4<=IF($M65="",12,$M65)),$O65,0) -> 0 | U65: =IF(AND(U$4>=IF($L65="",1,$L65),U$4<=IF($M65="",12,$M65)),$O65,0) -> 0 | V65: =IF(AND(V$4>=IF($L65="",1,$L65),V$4<=IF($M65="",12,$M65)),$O65,0) -> 0 | W65: =IF(AND(W$4>=IF($L65="",1,$L65),W$4<=IF($M65="",12,$M65)),$O65,0) -> 0 | ... AA65: =IF(AND(AA$4>=IF($L65="",1,$L65),AA$4<=IF($M65="",12,$M65)),$O65,0) -> 0 | AB65: =SUM(P65:AA65) -> 0
A66: Verizon Wireless | B66: Installation Services | C66: XERO+BUDGET | D66: STEADY | E66: 0.5134 | G66: =IFERROR(IF($F66>0,MAX(0,INDEX('XERO ACTUALS'!$T$5:$T$132,MATCH($A66,'XERO ACTUALS'!$A$5:$A$132,0))-$F66),INDEX('XERO ACTUALS'!$T$5:$T$132,MATCH($A66,'XERO ACTUALS'!$A$5:$A$132,0)))*IF($E66="",1,$E66),"") -> 160.84309 | H66: 323.67 | I66: XERO | K66: 0 | L66: 1 | M66: 12 | N66: Y | O66: =IF($N66="N",0,IF($A66="",0,(IF($J66<>"",$J66,IF($I66="BUDGET",IF($H66="",0,$H66),IF($G66="",0,$G66))))*(1+IF($K66="",0,$K66)))) -> 160.84309 | P66: =IF(AND(P$4>=IF($L66="",1,$L66),P$4<=IF($M66="",12,$M66)),$O66,0) -> 160.84309 | Q66: =IF(AND(Q$4>=IF($L66="",1,$L66),Q$4<=IF($M66="",12,$M66)),$O66,0) -> 160.84309 | R66: =IF(AND(R$4>=IF($L66="",1,$L66),R$4<=IF($M66="",12,$M66)),$O66,0) -> 160.84309 | S66: =IF(AND(S$4>=IF($L66="",1,$L66),S$4<=IF($M66="",12,$M66)),$O66,0) -> 160.84309 | T66: =IF(AND(T$4>=IF($L66="",1,$L66),T$4<=IF($M66="",12,$M66)),$O66,0) -> 160.84309 | U66: =IF(AND(U$4>=IF($L66="",1,$L66),U$4<=IF($M66="",12,$M66)),$O66,0) -> 160.84309 | V66: =IF(AND(V$4>=IF($L66="",1,$L66),V$4<=IF($M66="",12,$M66)),$O66,0) -> 160.84309 | W66: =IF(AND(W$4>=IF($L66="",1,$L66),W$4<=IF($M66="",12,$M66)),$O66,0) -> 160.84309 | ... AA66: =IF(AND(AA$4>=IF($L66="",1,$L66),AA$4<=IF($M66="",12,$M66)),$O66,0) -> 160.84309 | AB66: =SUM(P66:AA66) -> 1930.117
A67: NCBEEC | B67: Installation Services | C67: XERO ONLY | D67: NEW | E67: 1 | G67: =IFERROR(IF($F67>0,MAX(0,INDEX('XERO ACTUALS'!$T$5:$T$132,MATCH($A67,'XERO ACTUALS'!$A$5:$A$132,0))-$F67),INDEX('XERO ACTUALS'!$T$5:$T$132,MATCH($A67,'XERO ACTUALS'!$A$5:$A$132,0)))*IF($E67="",1,$E67),"") -> 151.31 | I67: XERO | K67: 0 | L67: 1 | M67: 12 | N67: Y | O67: =IF($N67="N",0,IF($A67="",0,(IF($J67<>"",$J67,IF($I67="BUDGET",IF($H67="",0,$H67),IF($G67="",0,$G67))))*(1+IF($K67="",0,$K67)))) -> 151.31 | P67: =IF(AND(P$4>=IF($L67="",1,$L67),P$4<=IF($M67="",12,$M67)),$O67,0) -> 151.31 | Q67: =IF(AND(Q$4>=IF($L67="",1,$L67),Q$4<=IF($M67="",12,$M67)),$O67,0) -> 151.31 | R67: =IF(AND(R$4>=IF($L67="",1,$L67),R$4<=IF($M67="",12,$M67)),$O67,0) -> 151.31 | S67: =IF(AND(S$4>=IF($L67="",1,$L67),S$4<=IF($M67="",12,$M67)),$O67,0) -> 151.31 | T67: =IF(AND(T$4>=IF($L67="",1,$L67),T$4<=IF($M67="",12,$M67)),$O67,0) -> 151.31 | U67: =IF(AND(U$4>=IF($L67="",1,$L67),U$4<=IF($M67="",12,$M67)),$O67,0) -> 151.31 | V67: =IF(AND(V$4>=IF($L67="",1,$L67),V$4<=IF($M67="",12,$M67)),$O67,0) -> 151.31 | W67: =IF(AND(W$4>=IF($L67="",1,$L67),W$4<=IF($M67="",12,$M67)),$O67,0) -> 151.31 | ... AA67: =IF(AND(AA$4>=IF($L67="",1,$L67),AA$4<=IF($M67="",12,$M67)),$O67,0) -> 151.31 | AB67: =SUM(P67:AA67) -> 1815.72
A68: ClickUp | B68: Installation Services | C68: XERO+BUDGET | D68: STEADY | E68: 1 | F68: 99.45 | G68: =IFERROR(IF($F68>0,MAX(0,INDEX('XERO ACTUALS'!$T$5:$T$132,MATCH($A68,'XERO ACTUALS'!$A$5:$A$132,0))-$F68),INDEX('XERO ACTUALS'!$T$5:$T$132,MATCH($A68,'XERO ACTUALS'!$A$5:$A$132,0)))*IF($E68="",1,$E68),"") -> 106.55 | H68: 7.65 | I68: XERO | K68: 0 | L68: 1 | M68: 12 | N68: Y | O68: =IF($N68="N",0,IF($A68="",0,(IF($J68<>"",$J68,IF($I68="BUDGET",IF($H68="",0,$H68),IF($G68="",0,$G68))))*(1+IF($K68="",0,$K68)))) -> 106.55 | P68: =IF(AND(P$4>=IF($L68="",1,$L68),P$4<=IF($M68="",12,$M68)),$O68,0) -> 106.55 | Q68: =IF(AND(Q$4>=IF($L68="",1,$L68),Q$4<=IF($M68="",12,$M68)),$O68,0) -> 106.55 | R68: =IF(AND(R$4>=IF($L68="",1,$L68),R$4<=IF($M68="",12,$M68)),$O68,0) -> 106.55 | S68: =IF(AND(S$4>=IF($L68="",1,$L68),S$4<=IF($M68="",12,$M68)),$O68,0) -> 106.55 | T68: =IF(AND(T$4>=IF($L68="",1,$L68),T$4<=IF($M68="",12,$M68)),$O68,0) -> 106.55 | U68: =IF(AND(U$4>=IF($L68="",1,$L68),U$4<=IF($M68="",12,$M68)),$O68,0) -> 106.55 | V68: =IF(AND(V$4>=IF($L68="",1,$L68),V$4<=IF($M68="",12,$M68)),$O68,0) -> 106.55 | W68: =IF(AND(W$4>=IF($L68="",1,$L68),W$4<=IF($M68="",12,$M68)),$O68,0) -> 106.55 | ... AA68: =IF(AND(AA$4>=IF($L68="",1,$L68),AA$4<=IF($M68="",12,$M68)),$O68,0) -> 106.55 | AB68: =SUM(P68:AA68) -> 1278.6
A69: ISNetworld | B69: Installation Services | C69: BUDGET ONLY | D69: NOT IN XERO 2026 | H69: 106.25 | I69: BUDGET | K69: 0 | L69: 1 | M69: 12 | N69: N | O69: =IF($N69="N",0,IF($A69="",0,(IF($J69<>"",$J69,IF($I69="BUDGET",IF($H69="",0,$H69),IF($G69="",0,$G69))))*(1+IF($K69="",0,$K69)))) -> 0 | P69: =IF(AND(P$4>=IF($L69="",1,$L69),P$4<=IF($M69="",12,$M69)),$O69,0) -> 0 | Q69: =IF(AND(Q$4>=IF($L69="",1,$L69),Q$4<=IF($M69="",12,$M69)),$O69,0) -> 0 | R69: =IF(AND(R$4>=IF($L69="",1,$L69),R$4<=IF($M69="",12,$M69)),$O69,0) -> 0 | S69: =IF(AND(S$4>=IF($L69="",1,$L69),S$4<=IF($M69="",12,$M69)),$O69,0) -> 0 | T69: =IF(AND(T$4>=IF($L69="",1,$L69),T$4<=IF($M69="",12,$M69)),$O69,0) -> 0 | U69: =IF(AND(U$4>=IF($L69="",1,$L69),U$4<=IF($M69="",12,$M69)),$O69,0) -> 0 | V69: =IF(AND(V$4>=IF($L69="",1,$L69),V$4<=IF($M69="",12,$M69)),$O69,0) -> 0 | W69: =IF(AND(W$4>=IF($L69="",1,$L69),W$4<=IF($M69="",12,$M69)),$O69,0) -> 0 | ... AA69: =IF(AND(AA$4>=IF($L69="",1,$L69),AA$4<=IF($M69="",12,$M69)),$O69,0) -> 0 | AB69: =SUM(P69:AA69) -> 0
A70: OWYN Safety Management Platform | B70: Installation Services | C70: XERO ONLY | D70: ONE-TIME | E70: 1 | G70: =IFERROR(IF($F70>0,MAX(0,INDEX('XERO ACTUALS'!$T$5:$T$132,MATCH($A70,'XERO ACTUALS'!$A$5:$A$132,0))-$F70),INDEX('XERO ACTUALS'!$T$5:$T$132,MATCH($A70,'XERO ACTUALS'!$A$5:$A$132,0)))*IF($E70="",1,$E70),"") -> 64.735457 | I70: XERO | K70: 0 | L70: 1 | M70: 12 | N70: N | O70: =IF($N70="N",0,IF($A70="",0,(IF($J70<>"",$J70,IF($I70="BUDGET",IF($H70="",0,$H70),IF($G70="",0,$G70))))*(1+IF($K70="",0,$K70)))) -> 0 | P70: =IF(AND(P$4>=IF($L70="",1,$L70),P$4<=IF($M70="",12,$M70)),$O70,0) -> 0 | Q70: =IF(AND(Q$4>=IF($L70="",1,$L70),Q$4<=IF($M70="",12,$M70)),$O70,0) -> 0 | R70: =IF(AND(R$4>=IF($L70="",1,$L70),R$4<=IF($M70="",12,$M70)),$O70,0) -> 0 | S70: =IF(AND(S$4>=IF($L70="",1,$L70),S$4<=IF($M70="",12,$M70)),$O70,0) -> 0 | T70: =IF(AND(T$4>=IF($L70="",1,$L70),T$4<=IF($M70="",12,$M70)),$O70,0) -> 0 | U70: =IF(AND(U$4>=IF($L70="",1,$L70),U$4<=IF($M70="",12,$M70)),$O70,0) -> 0 | V70: =IF(AND(V$4>=IF($L70="",1,$L70),V$4<=IF($M70="",12,$M70)),$O70,0) -> 0 | W70: =IF(AND(W$4>=IF($L70="",1,$L70),W$4<=IF($M70="",12,$M70)),$O70,0) -> 0 | ... AA70: =IF(AND(AA$4>=IF($L70="",1,$L70),AA$4<=IF($M70="",12,$M70)),$O70,0) -> 0 | AB70: =SUM(P70:AA70) -> 0
A71: CraftMyPDF | B71: Installation Services | C71: BUDGET ONLY | D71: NOT IN XERO 2026 | H71: 35 | I71: BUDGET | K71: 0 | L71: 1 | M71: 12 | N71: N | O71: =IF($N71="N",0,IF($A71="",0,(IF($J71<>"",$J71,IF($I71="BUDGET",IF($H71="",0,$H71),IF($G71="",0,$G71))))*(1+IF($K71="",0,$K71)))) -> 0 | P71: =IF(AND(P$4>=IF($L71="",1,$L71),P$4<=IF($M71="",12,$M71)),$O71,0) -> 0 | Q71: =IF(AND(Q$4>=IF($L71="",1,$L71),Q$4<=IF($M71="",12,$M71)),$O71,0) -> 0 | R71: =IF(AND(R$4>=IF($L71="",1,$L71),R$4<=IF($M71="",12,$M71)),$O71,0) -> 0 | S71: =IF(AND(S$4>=IF($L71="",1,$L71),S$4<=IF($M71="",12,$M71)),$O71,0) -> 0 | T71: =IF(AND(T$4>=IF($L71="",1,$L71),T$4<=IF($M71="",12,$M71)),$O71,0) -> 0 | U71: =IF(AND(U$4>=IF($L71="",1,$L71),U$4<=IF($M71="",12,$M71)),$O71,0) -> 0 | V71: =IF(AND(V$4>=IF($L71="",1,$L71),V$4<=IF($M71="",12,$M71)),$O71,0) -> 0 | W71: =IF(AND(W$4>=IF($L71="",1,$L71),W$4<=IF($M71="",12,$M71)),$O71,0) -> 0 | ... AA71: =IF(AND(AA$4>=IF($L71="",1,$L71),AA$4<=IF($M71="",12,$M71)),$O71,0) -> 0 | AB71: =SUM(P71:AA71) -> 0
A72: Alarm Systems Licensing Board | B72: Installation Services | C72: XERO ONLY | D72: PERIODIC | E72: 1 | G72: =IFERROR(IF($F72>0,MAX(0,INDEX('XERO ACTUALS'!$T$5:$T$132,MATCH($A72,'XERO ACTUALS'!$A$5:$A$132,0))-$F72),INDEX('XERO ACTUALS'!$T$5:$T$132,MATCH($A72,'XERO ACTUALS'!$A$5:$A$132,0)))*IF($E72="",1,$E72),"") -> 25.104853 | I72: XERO | K72: 0 | L72: 1 | M72: 12 | N72: Y | O72: =IF($N72="N",0,IF($A72="",0,(IF($J72<>"",$J72,IF($I72="BUDGET",IF($H72="",0,$H72),IF($G72="",0,$G72))))*(1+IF($K72="",0,$K72)))) -> 25.104853 | P72: =IF(AND(P$4>=IF($L72="",1,$L72),P$4<=IF($M72="",12,$M72)),$O72,0) -> 25.104853 | Q72: =IF(AND(Q$4>=IF($L72="",1,$L72),Q$4<=IF($M72="",12,$M72)),$O72,0) -> 25.104853 | R72: =IF(AND(R$4>=IF($L72="",1,$L72),R$4<=IF($M72="",12,$M72)),$O72,0) -> 25.104853 | S72: =IF(AND(S$4>=IF($L72="",1,$L72),S$4<=IF($M72="",12,$M72)),$O72,0) -> 25.104853 | T72: =IF(AND(T$4>=IF($L72="",1,$L72),T$4<=IF($M72="",12,$M72)),$O72,0) -> 25.104853 | U72: =IF(AND(U$4>=IF($L72="",1,$L72),U$4<=IF($M72="",12,$M72)),$O72,0) -> 25.104853 | V72: =IF(AND(V$4>=IF($L72="",1,$L72),V$4<=IF($M72="",12,$M72)),$O72,0) -> 25.104853 | W72: =IF(AND(W$4>=IF($L72="",1,$L72),W$4<=IF($M72="",12,$M72)),$O72,0) -> 25.104853 | ... AA72: =IF(AND(AA$4>=IF($L72="",1,$L72),AA$4<=IF($M72="",12,$M72)),$O72,0) -> 25.104853 | AB72: =SUM(P72:AA72) -> 301.25824
A73: PDF4me | B73: Installation Services | C73: BUDGET ONLY | D73: NOT IN XERO 2026 | H73: 6 | I73: BUDGET | K73: 0 | L73: 1 | M73: 12 | N73: N | O73: =IF($N73="N",0,IF($A73="",0,(IF($J73<>"",$J73,IF($I73="BUDGET",IF($H73="",0,$H73),IF($G73="",0,$G73))))*(1+IF($K73="",0,$K73)))) -> 0 | P73: =IF(AND(P$4>=IF($L73="",1,$L73),P$4<=IF($M73="",12,$M73)),$O73,0) -> 0 | Q73: =IF(AND(Q$4>=IF($L73="",1,$L73),Q$4<=IF($M73="",12,$M73)),$O73,0) -> 0 | R73: =IF(AND(R$4>=IF($L73="",1,$L73),R$4<=IF($M73="",12,$M73)),$O73,0) -> 0 | S73: =IF(AND(S$4>=IF($L73="",1,$L73),S$4<=IF($M73="",12,$M73)),$O73,0) -> 0 | T73: =IF(AND(T$4>=IF($L73="",1,$L73),T$4<=IF($M73="",12,$M73)),$O73,0) -> 0 | U73: =IF(AND(U$4>=IF($L73="",1,$L73),U$4<=IF($M73="",12,$M73)),$O73,0) -> 0 | V73: =IF(AND(V$4>=IF($L73="",1,$L73),V$4<=IF($M73="",12,$M73)),$O73,0) -> 0 | W73: =IF(AND(W$4>=IF($L73="",1,$L73),W$4<=IF($M73="",12,$M73)),$O73,0) -> 0 | ... AA73: =IF(AND(AA$4>=IF($L73="",1,$L73),AA$4<=IF($M73="",12,$M73)),$O73,0) -> 0 | AB73: =SUM(P73:AA73) -> 0
A74: Logmein (Go To Meeting) | B74: Technical Support | C74: XERO+BUDGET | D74: STEADY | E74: 1 | G74: =IFERROR(IF($F74>0,MAX(0,INDEX('XERO ACTUALS'!$T$5:$T$132,MATCH($A74,'XERO ACTUALS'!$A$5:$A$132,0))-$F74),INDEX('XERO ACTUALS'!$T$5:$T$132,MATCH($A74,'XERO ACTUALS'!$A$5:$A$132,0)))*IF($E74="",1,$E74),"") -> 341.33 | H74: 319 | I74: XERO | K74: 0 | L74: 1 | M74: 12 | N74: Y | O74: =IF($N74="N",0,IF($A74="",0,(IF($J74<>"",$J74,IF($I74="BUDGET",IF($H74="",0,$H74),IF($G74="",0,$G74))))*(1+IF($K74="",0,$K74)))) -> 341.33 | P74: =IF(AND(P$4>=IF($L74="",1,$L74),P$4<=IF($M74="",12,$M74)),$O74,0) -> 341.33 | Q74: =IF(AND(Q$4>=IF($L74="",1,$L74),Q$4<=IF($M74="",12,$M74)),$O74,0) -> 341.33 | R74: =IF(AND(R$4>=IF($L74="",1,$L74),R$4<=IF($M74="",12,$M74)),$O74,0) -> 341.33 | S74: =IF(AND(S$4>=IF($L74="",1,$L74),S$4<=IF($M74="",12,$M74)),$O74,0) -> 341.33 | T74: =IF(AND(T$4>=IF($L74="",1,$L74),T$4<=IF($M74="",12,$M74)),$O74,0) -> 341.33 | U74: =IF(AND(U$4>=IF($L74="",1,$L74),U$4<=IF($M74="",12,$M74)),$O74,0) -> 341.33 | V74: =IF(AND(V$4>=IF($L74="",1,$L74),V$4<=IF($M74="",12,$M74)),$O74,0) -> 341.33 | W74: =IF(AND(W$4>=IF($L74="",1,$L74),W$4<=IF($M74="",12,$M74)),$O74,0) -> 341.33 | ... AA74: =IF(AND(AA$4>=IF($L74="",1,$L74),AA$4<=IF($M74="",12,$M74)),$O74,0) -> 341.33 | AB74: =SUM(P74:AA74) -> 4095.96
A75: Rippling | B75: Technical Support | C75: XERO+BUDGET | D75: STEADY | E75: 0.0513 | F75: 986.69 | G75: =IFERROR(IF($F75>0,MAX(0,INDEX('XERO ACTUALS'!$T$5:$T$132,MATCH($A75,'XERO ACTUALS'!$A$5:$A$132,0))-$F75),INDEX('XERO ACTUALS'!$T$5:$T$132,MATCH($A75,'XERO ACTUALS'!$A$5:$A$132,0)))*IF($E75="",1,$E75),"") -> 30.982122 | H75: 5.16 | I75: XERO | K75: 0 | L75: 1 | M75: 12 | N75: Y | O75: =IF($N75="N",0,IF($A75="",0,(IF($J75<>"",$J75,IF($I75="BUDGET",IF($H75="",0,$H75),IF($G75="",0,$G75))))*(1+IF($K75="",0,$K75)))) -> 30.982122 | P75: =IF(AND(P$4>=IF($L75="",1,$L75),P$4<=IF($M75="",12,$M75)),$O75,0) -> 30.982122 | Q75: =IF(AND(Q$4>=IF($L75="",1,$L75),Q$4<=IF($M75="",12,$M75)),$O75,0) -> 30.982122 | R75: =IF(AND(R$4>=IF($L75="",1,$L75),R$4<=IF($M75="",12,$M75)),$O75,0) -> 30.982122 | S75: =IF(AND(S$4>=IF($L75="",1,$L75),S$4<=IF($M75="",12,$M75)),$O75,0) -> 30.982122 | T75: =IF(AND(T$4>=IF($L75="",1,$L75),T$4<=IF($M75="",12,$M75)),$O75,0) -> 30.982122 | U75: =IF(AND(U$4>=IF($L75="",1,$L75),U$4<=IF($M75="",12,$M75)),$O75,0) -> 30.982122 | V75: =IF(AND(V$4>=IF($L75="",1,$L75),V$4<=IF($M75="",12,$M75)),$O75,0) -> 30.982122 | W75: =IF(AND(W$4>=IF($L75="",1,$L75),W$4<=IF($M75="",12,$M75)),$O75,0) -> 30.982122 | ... AA75: =IF(AND(AA$4>=IF($L75="",1,$L75),AA$4<=IF($M75="",12,$M75)),$O75,0) -> 30.982122 | AB75: =SUM(P75:AA75) -> 371.78546
A76: No-IP | B76: Technical Support | C76: BUDGET ONLY | D76: NOT IN XERO 2026 | H76: 3.99 | I76: BUDGET | K76: 0 | L76: 1 | M76: 12 | N76: N | O76: =IF($N76="N",0,IF($A76="",0,(IF($J76<>"",$J76,IF($I76="BUDGET",IF($H76="",0,$H76),IF($G76="",0,$G76))))*(1+IF($K76="",0,$K76)))) -> 0 | P76: =IF(AND(P$4>=IF($L76="",1,$L76),P$4<=IF($M76="",12,$M76)),$O76,0) -> 0 | Q76: =IF(AND(Q$4>=IF($L76="",1,$L76),Q$4<=IF($M76="",12,$M76)),$O76,0) -> 0 | R76: =IF(AND(R$4>=IF($L76="",1,$L76),R$4<=IF($M76="",12,$M76)),$O76,0) -> 0 | S76: =IF(AND(S$4>=IF($L76="",1,$L76),S$4<=IF($M76="",12,$M76)),$O76,0) -> 0 | T76: =IF(AND(T$4>=IF($L76="",1,$L76),T$4<=IF($M76="",12,$M76)),$O76,0) -> 0 | U76: =IF(AND(U$4>=IF($L76="",1,$L76),U$4<=IF($M76="",12,$M76)),$O76,0) -> 0 | V76: =IF(AND(V$4>=IF($L76="",1,$L76),V$4<=IF($M76="",12,$M76)),$O76,0) -> 0 | W76: =IF(AND(W$4>=IF($L76="",1,$L76),W$4<=IF($M76="",12,$M76)),$O76,0) -> 0 | ... AA76: =IF(AND(AA$4>=IF($L76="",1,$L76),AA$4<=IF($M76="",12,$M76)),$O76,0) -> 0 | AB76: =SUM(P76:AA76) -> 0
A77: ShipEdge | B77: Purchasing & Fulfillment | C77: XERO+BUDGET | D77: STEADY | E77: 1 | G77: =IFERROR(IF($F77>0,MAX(0,INDEX('XERO ACTUALS'!$T$5:$T$132,MATCH($A77,'XERO ACTUALS'!$A$5:$A$132,0))-$F77),INDEX('XERO ACTUALS'!$T$5:$T$132,MATCH($A77,'XERO ACTUALS'!$A$5:$A$132,0)))*IF($E77="",1,$E77),"") -> 1043 | H77: 1043 | I77: XERO | K77: 0 | L77: 1 | M77: 12 | N77: Y | O77: =IF($N77="N",0,IF($A77="",0,(IF($J77<>"",$J77,IF($I77="BUDGET",IF($H77="",0,$H77),IF($G77="",0,$G77))))*(1+IF($K77="",0,$K77)))) -> 1043 | P77: =IF(AND(P$4>=IF($L77="",1,$L77),P$4<=IF($M77="",12,$M77)),$O77,0) -> 1043 | Q77: =IF(AND(Q$4>=IF($L77="",1,$L77),Q$4<=IF($M77="",12,$M77)),$O77,0) -> 1043 | R77: =IF(AND(R$4>=IF($L77="",1,$L77),R$4<=IF($M77="",12,$M77)),$O77,0) -> 1043 | S77: =IF(AND(S$4>=IF($L77="",1,$L77),S$4<=IF($M77="",12,$M77)),$O77,0) -> 1043 | T77: =IF(AND(T$4>=IF($L77="",1,$L77),T$4<=IF($M77="",12,$M77)),$O77,0) -> 1043 | U77: =IF(AND(U$4>=IF($L77="",1,$L77),U$4<=IF($M77="",12,$M77)),$O77,0) -> 1043 | V77: =IF(AND(V$4>=IF($L77="",1,$L77),V$4<=IF($M77="",12,$M77)),$O77,0) -> 1043 | W77: =IF(AND(W$4>=IF($L77="",1,$L77),W$4<=IF($M77="",12,$M77)),$O77,0) -> 1043 | ... AA77: =IF(AND(AA$4>=IF($L77="",1,$L77),AA$4<=IF($M77="",12,$M77)),$O77,0) -> 1043 | AB77: =SUM(P77:AA77) -> 12516
A78: UPS Capital Insurance Agency, Inc | B78: Purchasing & Fulfillment | C78: BUDGET ONLY | D78: NOT IN XERO 2026 | H78: 550 | I78: BUDGET | K78: 0 | L78: 1 | M78: 12 | N78: N | O78: =IF($N78="N",0,IF($A78="",0,(IF($J78<>"",$J78,IF($I78="BUDGET",IF($H78="",0,$H78),IF($G78="",0,$G78))))*(1+IF($K78="",0,$K78)))) -> 0 | P78: =IF(AND(P$4>=IF($L78="",1,$L78),P$4<=IF($M78="",12,$M78)),$O78,0) -> 0 | Q78: =IF(AND(Q$4>=IF($L78="",1,$L78),Q$4<=IF($M78="",12,$M78)),$O78,0) -> 0 | R78: =IF(AND(R$4>=IF($L78="",1,$L78),R$4<=IF($M78="",12,$M78)),$O78,0) -> 0 | S78: =IF(AND(S$4>=IF($L78="",1,$L78),S$4<=IF($M78="",12,$M78)),$O78,0) -> 0 | T78: =IF(AND(T$4>=IF($L78="",1,$L78),T$4<=IF($M78="",12,$M78)),$O78,0) -> 0 | U78: =IF(AND(U$4>=IF($L78="",1,$L78),U$4<=IF($M78="",12,$M78)),$O78,0) -> 0 | V78: =IF(AND(V$4>=IF($L78="",1,$L78),V$4<=IF($M78="",12,$M78)),$O78,0) -> 0 | W78: =IF(AND(W$4>=IF($L78="",1,$L78),W$4<=IF($M78="",12,$M78)),$O78,0) -> 0 | ... AA78: =IF(AND(AA$4>=IF($L78="",1,$L78),AA$4<=IF($M78="",12,$M78)),$O78,0) -> 0 | AB78: =SUM(P78:AA78) -> 0
A79: Misc Warehouse Supplies | B79: Purchasing & Fulfillment | C79: BUDGET ONLY | D79: NOT IN XERO 2026 | H79: 150 | I79: BUDGET | K79: 0 | L79: 1 | M79: 12 | N79: N | O79: =IF($N79="N",0,IF($A79="",0,(IF($J79<>"",$J79,IF($I79="BUDGET",IF($H79="",0,$H79),IF($G79="",0,$G79))))*(1+IF($K79="",0,$K79)))) -> 0 | P79: =IF(AND(P$4>=IF($L79="",1,$L79),P$4<=IF($M79="",12,$M79)),$O79,0) -> 0 | Q79: =IF(AND(Q$4>=IF($L79="",1,$L79),Q$4<=IF($M79="",12,$M79)),$O79,0) -> 0 | R79: =IF(AND(R$4>=IF($L79="",1,$L79),R$4<=IF($M79="",12,$M79)),$O79,0) -> 0 | S79: =IF(AND(S$4>=IF($L79="",1,$L79),S$4<=IF($M79="",12,$M79)),$O79,0) -> 0 | T79: =IF(AND(T$4>=IF($L79="",1,$L79),T$4<=IF($M79="",12,$M79)),$O79,0) -> 0 | U79: =IF(AND(U$4>=IF($L79="",1,$L79),U$4<=IF($M79="",12,$M79)),$O79,0) -> 0 | V79: =IF(AND(V$4>=IF($L79="",1,$L79),V$4<=IF($M79="",12,$M79)),$O79,0) -> 0 | W79: =IF(AND(W$4>=IF($L79="",1,$L79),W$4<=IF($M79="",12,$M79)),$O79,0) -> 0 | ... AA79: =IF(AND(AA$4>=IF($L79="",1,$L79),AA$4<=IF($M79="",12,$M79)),$O79,0) -> 0 | AB79: =SUM(P79:AA79) -> 0
A80: Shit I've missed | B80: 03 - HR & Business Administration Manager | C80: BUDGET ONLY | D80: NOT IN XERO 2026 | H80: 5000 | I80: BUDGET | K80: 0 | L80: 1 | M80: 12 | N80: N | O80: =IF($N80="N",0,IF($A80="",0,(IF($J80<>"",$J80,IF($I80="BUDGET",IF($H80="",0,$H80),IF($G80="",0,$G80))))*(1+IF($K80="",0,$K80)))) -> 0 | P80: =IF(AND(P$4>=IF($L80="",1,$L80),P$4<=IF($M80="",12,$M80)),$O80,0) -> 0 | Q80: =IF(AND(Q$4>=IF($L80="",1,$L80),Q$4<=IF($M80="",12,$M80)),$O80,0) -> 0 | R80: =IF(AND(R$4>=IF($L80="",1,$L80),R$4<=IF($M80="",12,$M80)),$O80,0) -> 0 | S80: =IF(AND(S$4>=IF($L80="",1,$L80),S$4<=IF($M80="",12,$M80)),$O80,0) -> 0 | T80: =IF(AND(T$4>=IF($L80="",1,$L80),T$4<=IF($M80="",12,$M80)),$O80,0) -> 0 | U80: =IF(AND(U$4>=IF($L80="",1,$L80),U$4<=IF($M80="",12,$M80)),$O80,0) -> 0 | V80: =IF(AND(V$4>=IF($L80="",1,$L80),V$4<=IF($M80="",12,$M80)),$O80,0) -> 0 | W80: =IF(AND(W$4>=IF($L80="",1,$L80),W$4<=IF($M80="",12,$M80)),$O80,0) -> 0 | ... AA80: =IF(AND(AA$4>=IF($L80="",1,$L80),AA$4<=IF($M80="",12,$M80)),$O80,0) -> 0 | AB80: =SUM(P80:AA80) -> 0
A81: Google (Rippling) | B81: 03 - HR & Business Administration Manager | C81: BUDGET ONLY | D81: NOT IN XERO 2026 | F81: 828 | H81: 1259.08 | I81: BUDGET | K81: 0 | L81: 1 | M81: 12 | N81: N | O81: =IF($N81="N",0,IF($A81="",0,(IF($J81<>"",$J81,IF($I81="BUDGET",IF($H81="",0,$H81),IF($G81="",0,$G81))))*(1+IF($K81="",0,$K81)))) -> 0 | P81: =IF(AND(P$4>=IF($L81="",1,$L81),P$4<=IF($M81="",12,$M81)),$O81,0) -> 0 | Q81: =IF(AND(Q$4>=IF($L81="",1,$L81),Q$4<=IF($M81="",12,$M81)),$O81,0) -> 0 | R81: =IF(AND(R$4>=IF($L81="",1,$L81),R$4<=IF($M81="",12,$M81)),$O81,0) -> 0 | S81: =IF(AND(S$4>=IF($L81="",1,$L81),S$4<=IF($M81="",12,$M81)),$O81,0) -> 0 | T81: =IF(AND(T$4>=IF($L81="",1,$L81),T$4<=IF($M81="",12,$M81)),$O81,0) -> 0 | U81: =IF(AND(U$4>=IF($L81="",1,$L81),U$4<=IF($M81="",12,$M81)),$O81,0) -> 0 | V81: =IF(AND(V$4>=IF($L81="",1,$L81),V$4<=IF($M81="",12,$M81)),$O81,0) -> 0 | W81: =IF(AND(W$4>=IF($L81="",1,$L81),W$4<=IF($M81="",12,$M81)),$O81,0) -> 0 | ... AA81: =IF(AND(AA$4>=IF($L81="",1,$L81),AA$4<=IF($M81="",12,$M81)),$O81,0) -> 0 | AB81: =SUM(P81:AA81) -> 0
A82: Knack | B82: 03 - HR & Business Administration Manager | C82: XERO+BUDGET | D82: STEADY | E82: 1 | G82: =IFERROR(IF($F82>0,MAX(0,INDEX('XERO ACTUALS'!$T$5:$T$132,MATCH($A82,'XERO ACTUALS'!$A$5:$A$132,0))-$F82),INDEX('XERO ACTUALS'!$T$5:$T$132,MATCH($A82,'XERO ACTUALS'!$A$5:$A$132,0)))*IF($E82="",1,$E82),"") -> 1200 | H82: 1307 | I82: XERO | K82: 0 | L82: 1 | M82: 12 | N82: Y | O82: =IF($N82="N",0,IF($A82="",0,(IF($J82<>"",$J82,IF($I82="BUDGET",IF($H82="",0,$H82),IF($G82="",0,$G82))))*(1+IF($K82="",0,$K82)))) -> 1200 | P82: =IF(AND(P$4>=IF($L82="",1,$L82),P$4<=IF($M82="",12,$M82)),$O82,0) -> 1200 | Q82: =IF(AND(Q$4>=IF($L82="",1,$L82),Q$4<=IF($M82="",12,$M82)),$O82,0) -> 1200 | R82: =IF(AND(R$4>=IF($L82="",1,$L82),R$4<=IF($M82="",12,$M82)),$O82,0) -> 1200 | S82: =IF(AND(S$4>=IF($L82="",1,$L82),S$4<=IF($M82="",12,$M82)),$O82,0) -> 1200 | T82: =IF(AND(T$4>=IF($L82="",1,$L82),T$4<=IF($M82="",12,$M82)),$O82,0) -> 1200 | U82: =IF(AND(U$4>=IF($L82="",1,$L82),U$4<=IF($M82="",12,$M82)),$O82,0) -> 1200 | V82: =IF(AND(V$4>=IF($L82="",1,$L82),V$4<=IF($M82="",12,$M82)),$O82,0) -> 1200 | W82: =IF(AND(W$4>=IF($L82="",1,$L82),W$4<=IF($M82="",12,$M82)),$O82,0) -> 1200 | ... AA82: =IF(AND(AA$4>=IF($L82="",1,$L82),AA$4<=IF($M82="",12,$M82)),$O82,0) -> 1200 | AB82: =SUM(P82:AA82) -> 14400
A83: General Office Expenses | B83: 03 - HR & Business Administration Manager | C83: BUDGET ONLY | D83: NOT IN XERO 2026 | H83: 1000 | I83: BUDGET | K83: 0 | L83: 1 | M83: 12 | N83: N | O83: =IF($N83="N",0,IF($A83="",0,(IF($J83<>"",$J83,IF($I83="BUDGET",IF($H83="",0,$H83),IF($G83="",0,$G83))))*(1+IF($K83="",0,$K83)))) -> 0 | P83: =IF(AND(P$4>=IF($L83="",1,$L83),P$4<=IF($M83="",12,$M83)),$O83,0) -> 0 | Q83: =IF(AND(Q$4>=IF($L83="",1,$L83),Q$4<=IF($M83="",12,$M83)),$O83,0) -> 0 | R83: =IF(AND(R$4>=IF($L83="",1,$L83),R$4<=IF($M83="",12,$M83)),$O83,0) -> 0 | S83: =IF(AND(S$4>=IF($L83="",1,$L83),S$4<=IF($M83="",12,$M83)),$O83,0) -> 0 | T83: =IF(AND(T$4>=IF($L83="",1,$L83),T$4<=IF($M83="",12,$M83)),$O83,0) -> 0 | U83: =IF(AND(U$4>=IF($L83="",1,$L83),U$4<=IF($M83="",12,$M83)),$O83,0) -> 0 | V83: =IF(AND(V$4>=IF($L83="",1,$L83),V$4<=IF($M83="",12,$M83)),$O83,0) -> 0 | W83: =IF(AND(W$4>=IF($L83="",1,$L83),W$4<=IF($M83="",12,$M83)),$O83,0) -> 0 | ... AA83: =IF(AND(AA$4>=IF($L83="",1,$L83),AA$4<=IF($M83="",12,$M83)),$O83,0) -> 0 | AB83: =SUM(P83:AA83) -> 0
A84: TaxJar | B84: 03 - HR & Business Administration Manager | C84: XERO+BUDGET | D84: STEADY | E84: 1 | G84: =IFERROR(IF($F84>0,MAX(0,INDEX('XERO ACTUALS'!$T$5:$T$132,MATCH($A84,'XERO ACTUALS'!$A$5:$A$132,0))-$F84),INDEX('XERO ACTUALS'!$T$5:$T$132,MATCH($A84,'XERO ACTUALS'!$A$5:$A$132,0)))*IF($E84="",1,$E84),"") -> 737.33333 | H84: 591.17 | I84: XERO | K84: 0 | L84: 1 | M84: 12 | N84: Y | O84: =IF($N84="N",0,IF($A84="",0,(IF($J84<>"",$J84,IF($I84="BUDGET",IF($H84="",0,$H84),IF($G84="",0,$G84))))*(1+IF($K84="",0,$K84)))) -> 737.33333 | P84: =IF(AND(P$4>=IF($L84="",1,$L84),P$4<=IF($M84="",12,$M84)),$O84,0) -> 737.33333 | Q84: =IF(AND(Q$4>=IF($L84="",1,$L84),Q$4<=IF($M84="",12,$M84)),$O84,0) -> 737.33333 | R84: =IF(AND(R$4>=IF($L84="",1,$L84),R$4<=IF($M84="",12,$M84)),$O84,0) -> 737.33333 | S84: =IF(AND(S$4>=IF($L84="",1,$L84),S$4<=IF($M84="",12,$M84)),$O84,0) -> 737.33333 | T84: =IF(AND(T$4>=IF($L84="",1,$L84),T$4<=IF($M84="",12,$M84)),$O84,0) -> 737.33333 | U84: =IF(AND(U$4>=IF($L84="",1,$L84),U$4<=IF($M84="",12,$M84)),$O84,0) -> 737.33333 | V84: =IF(AND(V$4>=IF($L84="",1,$L84),V$4<=IF($M84="",12,$M84)),$O84,0) -> 737.33333 | W84: =IF(AND(W$4>=IF($L84="",1,$L84),W$4<=IF($M84="",12,$M84)),$O84,0) -> 737.33333 | ... AA84: =IF(AND(AA$4>=IF($L84="",1,$L84),AA$4<=IF($M84="",12,$M84)),$O84,0) -> 737.33333 | AB84: =SUM(P84:AA84) -> 8848
A85: Small Business Administration | B85: 03 - HR & Business Administration Manager | C85: XERO+BUDGET | D85: STEADY | E85: 1 | G85: =IFERROR(IF($F85>0,MAX(0,INDEX('XERO ACTUALS'!$T$5:$T$132,MATCH($A85,'XERO ACTUALS'!$A$5:$A$132,0))-$F85),INDEX('XERO ACTUALS'!$T$5:$T$132,MATCH($A85,'XERO ACTUALS'!$A$5:$A$132,0)))*IF($E85="",1,$E85),"") -> 731 | H85: 731 | I85: XERO | K85: 0 | L85: 1 | M85: 12 | N85: Y | O85: =IF($N85="N",0,IF($A85="",0,(IF($J85<>"",$J85,IF($I85="BUDGET",IF($H85="",0,$H85),IF($G85="",0,$G85))))*(1+IF($K85="",0,$K85)))) -> 731 | P85: =IF(AND(P$4>=IF($L85="",1,$L85),P$4<=IF($M85="",12,$M85)),$O85,0) -> 731 | Q85: =IF(AND(Q$4>=IF($L85="",1,$L85),Q$4<=IF($M85="",12,$M85)),$O85,0) -> 731 | R85: =IF(AND(R$4>=IF($L85="",1,$L85),R$4<=IF($M85="",12,$M85)),$O85,0) -> 731 | S85: =IF(AND(S$4>=IF($L85="",1,$L85),S$4<=IF($M85="",12,$M85)),$O85,0) -> 731 | T85: =IF(AND(T$4>=IF($L85="",1,$L85),T$4<=IF($M85="",12,$M85)),$O85,0) -> 731 | U85: =IF(AND(U$4>=IF($L85="",1,$L85),U$4<=IF($M85="",12,$M85)),$O85,0) -> 731 | V85: =IF(AND(V$4>=IF($L85="",1,$L85),V$4<=IF($M85="",12,$M85)),$O85,0) -> 731 | W85: =IF(AND(W$4>=IF($L85="",1,$L85),W$4<=IF($M85="",12,$M85)),$O85,0) -> 731 | ... AA85: =IF(AND(AA$4>=IF($L85="",1,$L85),AA$4<=IF($M85="",12,$M85)),$O85,0) -> 731 | AB85: =SUM(P85:AA85) -> 8772
A86: Rippling | B86: 03 - HR & Business Administration Manager | C86: XERO+BUDGET | D86: STEADY | E86: 0.9487 | F86: 986.69 | G86: =IFERROR(IF($F86>0,MAX(0,INDEX('XERO ACTUALS'!$T$5:$T$132,MATCH($A86,'XERO ACTUALS'!$A$5:$A$132,0))-$F86),INDEX('XERO ACTUALS'!$T$5:$T$132,MATCH($A86,'XERO ACTUALS'!$A$5:$A$132,0)))*IF($E86="",1,$E86),"") -> 572.95788 | H86: 95.49 | I86: XERO | K86: 0 | L86: 1 | M86: 12 | N86: Y | O86: =IF($N86="N",0,IF($A86="",0,(IF($J86<>"",$J86,IF($I86="BUDGET",IF($H86="",0,$H86),IF($G86="",0,$G86))))*(1+IF($K86="",0,$K86)))) -> 572.95788 | P86: =IF(AND(P$4>=IF($L86="",1,$L86),P$4<=IF($M86="",12,$M86)),$O86,0) -> 572.95788 | Q86: =IF(AND(Q$4>=IF($L86="",1,$L86),Q$4<=IF($M86="",12,$M86)),$O86,0) -> 572.95788 | R86: =IF(AND(R$4>=IF($L86="",1,$L86),R$4<=IF($M86="",12,$M86)),$O86,0) -> 572.95788 | S86: =IF(AND(S$4>=IF($L86="",1,$L86),S$4<=IF($M86="",12,$M86)),$O86,0) -> 572.95788 | T86: =IF(AND(T$4>=IF($L86="",1,$L86),T$4<=IF($M86="",12,$M86)),$O86,0) -> 572.95788 | U86: =IF(AND(U$4>=IF($L86="",1,$L86),U$4<=IF($M86="",12,$M86)),$O86,0) -> 572.95788 | V86: =IF(AND(V$4>=IF($L86="",1,$L86),V$4<=IF($M86="",12,$M86)),$O86,0) -> 572.95788 | W86: =IF(AND(W$4>=IF($L86="",1,$L86),W$4<=IF($M86="",12,$M86)),$O86,0) -> 572.95788 | ... AA86: =IF(AND(AA$4>=IF($L86="",1,$L86),AA$4<=IF($M86="",12,$M86)),$O86,0) -> 572.95788 | AB86: =SUM(P86:AA86) -> 6875.4945
